Workbook

Sheet README
A1: Africa's mobile-money frontier: market-selection model
A2: Question: which two sub-Saharan markets should a Kenya-based mobile-money operator enter by 2030?
A4: How to use
A5: 1 | B5: Change blue cells on Inputs (assumptions) or Data (market facts). Everything else is a formula and recalculates.
A6: 2 | B6: Read Summary for the ranking, Cases for the NPV by market and scenario, Sensitivity for what moves the answer, Checks for integrity.
A7: 3 | B7: Robustness and PyRef hold results estimated in Python (analysis/model.py). They are static. Re-run the script to refresh them.
A8: Sheets
A9: Summary | B9: Ranking of candidate markets with attractiveness, ease, quadrant, pools and NPV.
A10: Inputs | B10: All assumptions with a tag and a source or rationale. Includes calibration of revenue per user to company disclosures.
A11: Data | B11: Findex 2024 and World Development Indicators for 34 markets, plus judgement inputs (proximity) and the World Bank fragility score.
A12: Forecast | B12: Adoption to 2030 in three scenarios using a logistic curve.
A13: Pools | B13: Users x revenue per user, winnable revenue, pool growth, and cost scale.
A14: Scorecard | B14: Min-max scoring, attractiveness and ease, priority = sqrt(A x E), rank, discount rate, quadrant.
A15: Cases | B15: Year-by-year business case for the top five markets in three scenarios; break-even share.
A16: Sensitivity | B16: NPV grids for the top three markets: share x revenue per user, and margin x fixed cost.
A17: Colour code | B17: Blue = input. Black = formula. Green = link to another sheet. Yellow fill = key assumption or key output.
A18: Tags | B18: [S] sourced, [A] analyst assumption, [E] estimated in Python, [S/A] sourced with analyst adjustment.
A19: Not a valuation | B19: The business case is an entry screen for choosing between markets. It ignores tax, working capital and detailed currency paths.

Sheet Summary
A1: Where should a Kenyan mobile-money operator expand next? Summary of results
A2: Everything here is a live link into the model. Change an input on the Inputs sheet and this page updates.
A3: Model integrity: | B3: =Checks!D29 -> ALL CHECKS PASS
A5: Rank | B5: Market | C5: ISO3 | D5: Attractiveness (0-100) | E5: Ease of entry (0-100) | F5: Priority score | G5: Quadrant | H5: Adoption 2024 | I5: Adoption 2030 Base | J5: Revenue pool 2030 Base ($m) | K5: Winnable revenue 2030 Base ($m) | L5: Discount rate | M5: NPV Base ($m, top five)
A6: 1 | B6: =INDEX(Scorecard!$A$6:$A$39,MATCH(1,Scorecard!$AS$6:$AS$39,0)) -> Tanzania | C6: =INDEX(Scorecard!$B$6:$B$39,MATCH(1,Scorecard!$AS$6:$AS$39,0)) -> TZA | D6: =INDEX(Scorecard!$AC$6:$AC$39,MATCH(1,Scorecard!$AS$6:$AS$39,0)) -> 54.317622 | E6: =INDEX(Scorecard!$AQ$6:$AQ$39,MATCH(1,Scorecard!$AS$6:$AS$39,0)) -> 79.420807 | F6: =INDEX(Scorecard!$AR$6:$AR$39,MATCH(1,Scorecard!$AS$6:$AS$39,0)) -> 65.680662 | G6: =INDEX(Scorecard!$AU$6:$AU$39,MATCH(1,Scorecard!$AS$6:$AS$39,0)) -> Prioritise | H6: =INDEX(Data!$E$6:$E$39,MATCH(1,Scorecard!$AS$6:$AS$39,0)) -> 0.52853984 | I6: =INDEX(Forecast!$J$6:$J$39,MATCH(1,Scorecard!$AS$6:$AS$39,0)) -> 0.76614066 | J6: =INDEX(Pools!$L$6:$L$39,MATCH(1,Scorecard!$AS$6:$AS$39,0)) -> 672.62386 | K6: =INDEX(Pools!$R$6:$R$39,MATCH(1,Scorecard!$AS$6:$AS$39,0)) -> 45.210565 | L6: =INDEX(Scorecard!$AT$6:$AT$39,MATCH(1,Scorecard!$AS$6:$AS$39,0)) -> 0.12799263 | M6: =IFERROR(INDEX(Cases!$F$6:$F$10,MATCH(C6,Cases!$C$6:$C$10,0)),"") -> 13.478933
A7: 2 | B7: =INDEX(Scorecard!$A$6:$A$39,MATCH(2,Scorecard!$AS$6:$AS$39,0)) -> Cote d'Ivoire | C7: =INDEX(Scorecard!$B$6:$B$39,MATCH(2,Scorecard!$AS$6:$AS$39,0)) -> CIV | D7: =INDEX(Scorecard!$AC$6:$AC$39,MATCH(2,Scorecard!$AS$6:$AS$39,0)) -> 51.384197 | E7: =INDEX(Scorecard!$AQ$6:$AQ$39,MATCH(2,Scorecard!$AS$6:$AS$39,0)) -> 71.547241 | F7: =INDEX(Scorecard!$AR$6:$AR$39,MATCH(2,Scorecard!$AS$6:$AS$39,0)) -> 60.633303 | G7: =INDEX(Scorecard!$AU$6:$AU$39,MATCH(2,Scorecard!$AS$6:$AS$39,0)) -> Prioritise | H7: =INDEX(Data!$E$6:$E$39,MATCH(2,Scorecard!$AS$6:$AS$39,0)) -> 0.53381779 | I7: =INDEX(Forecast!$J$6:$J$39,MATCH(2,Scorecard!$AS$6:$AS$39,0)) -> 0.7699166 | J7: =INDEX(Pools!$L$6:$L$39,MATCH(2,Scorecard!$AS$6:$AS$39,0)) -> 408.8148 | K7: =INDEX(Pools!$R$6:$R$39,MATCH(2,Scorecard!$AS$6:$AS$39,0)) -> 27.308259 | L7: =INDEX(Scorecard!$AT$6:$AT$39,MATCH(2,Scorecard!$AS$6:$AS$39,0)) -> 0.12533993 | M7: =IFERROR(INDEX(Cases!$F$6:$F$10,MATCH(C7,Cases!$C$6:$C$10,0)),"") -> -10.323053
A8: 3 | B8: =INDEX(Scorecard!$A$6:$A$39,MATCH(3,Scorecard!$AS$6:$AS$39,0)) -> Uganda | C8: =INDEX(Scorecard!$B$6:$B$39,MATCH(3,Scorecard!$AS$6:$AS$39,0)) -> UGA | D8: =INDEX(Scorecard!$AC$6:$AC$39,MATCH(3,Scorecard!$AS$6:$AS$39,0)) -> 47.416766 | E8: =INDEX(Scorecard!$AQ$6:$AQ$39,MATCH(3,Scorecard!$AS$6:$AS$39,0)) -> 77.268162 | F8: =INDEX(Scorecard!$AR$6:$AR$39,MATCH(3,Scorecard!$AS$6:$AS$39,0)) -> 60.529385 | G8: =INDEX(Scorecard!$AU$6:$AU$39,MATCH(3,Scorecard!$AS$6:$AS$39,0)) -> Prioritise | H8: =INDEX(Data!$E$6:$E$39,MATCH(3,Scorecard!$AS$6:$AS$39,0)) -> 0.67738295 | I8: =INDEX(Forecast!$J$6:$J$39,MATCH(3,Scorecard!$AS$6:$AS$39,0)) -> 0.85986066 | J8: =INDEX(Pools!$L$6:$L$39,MATCH(3,Scorecard!$AS$6:$AS$39,0)) -> 516.18182 | K8: =INDEX(Pools!$R$6:$R$39,MATCH(3,Scorecard!$AS$6:$AS$39,0)) -> 28.630609 | L8: =INDEX(Scorecard!$AT$6:$AT$39,MATCH(3,Scorecard!$AS$6:$AS$39,0)) -> 0.12717103 | M8: =IFERROR(INDEX(Cases!$F$6:$F$10,MATCH(C8,Cases!$C$6:$C$10,0)),"") -> -29.90096
A9: 4 | B9: =INDEX(Scorecard!$A$6:$A$39,MATCH(4,Scorecard!$AS$6:$AS$39,0)) -> Congo, Dem. Rep. | C9: =INDEX(Scorecard!$B$6:$B$39,MATCH(4,Scorecard!$AS$6:$AS$39,0)) -> COD | D9: =INDEX(Scorecard!$AC$6:$AC$39,MATCH(4,Scorecard!$AS$6:$AS$39,0)) -> 63.786352 | E9: =INDEX(Scorecard!$AQ$6:$AQ$39,MATCH(4,Scorecard!$AS$6:$AS$39,0)) -> 56.945809 | F9: =INDEX(Scorecard!$AR$6:$AR$39,MATCH(4,Scorecard!$AS$6:$AS$39,0)) -> 60.269108 | G9: =INDEX(Scorecard!$AU$6:$AU$39,MATCH(4,Scorecard!$AS$6:$AS$39,0)) -> Big but hard | H9: =INDEX(Data!$E$6:$E$39,MATCH(4,Scorecard!$AS$6:$AS$39,0)) -> 0.35118239 | I9: =INDEX(Forecast!$J$6:$J$39,MATCH(4,Scorecard!$AS$6:$AS$39,0)) -> 0.61266217 | J9: =INDEX(Pools!$L$6:$L$39,MATCH(4,Scorecard!$AS$6:$AS$39,0)) -> 620.39175 | K9: =INDEX(Pools!$R$6:$R$39,MATCH(4,Scorecard!$AS$6:$AS$39,0)) -> 50.385198 | L9: =INDEX(Scorecard!$AT$6:$AT$39,MATCH(4,Scorecard!$AS$6:$AS$39,0)) -> 0.16466025 | M9: =IFERROR(INDEX(Cases!$F$6:$F$10,MATCH(C9,Cases!$C$6:$C$10,0)),"") -> 2.1813478
A10: 5 | B10: =INDEX(Scorecard!$A$6:$A$39,MATCH(5,Scorecard!$AS$6:$AS$39,0)) -> Benin | C10: =INDEX(Scorecard!$B$6:$B$39,MATCH(5,Scorecard!$AS$6:$AS$39,0)) -> BEN | D10: =INDEX(Scorecard!$AC$6:$AC$39,MATCH(5,Scorecard!$AS$6:$AS$39,0)) -> 43.37119 | E10: =INDEX(Scorecard!$AQ$6:$AQ$39,MATCH(5,Scorecard!$AS$6:$AS$39,0)) -> 71.033009 | F10: =INDEX(Scorecard!$AR$6:$AR$39,MATCH(5,Scorecard!$AS$6:$AS$39,0)) -> 55.504829 | G10: =INDEX(Scorecard!$AU$6:$AU$39,MATCH(5,Scorecard!$AS$6:$AS$39,0)) -> Easy but small | H10: =INDEX(Data!$E$6:$E$39,MATCH(5,Scorecard!$AS$6:$AS$39,0)) -> 0.44872852 | I10: =INDEX(Forecast!$J$6:$J$39,MATCH(5,Scorecard!$AS$6:$AS$39,0)) -> 0.70402795 | J10: =INDEX(Pools!$L$6:$L$39,MATCH(5,Scorecard!$AS$6:$AS$39,0)) -> 129.37709 | K10: =INDEX(Pools!$R$6:$R$39,MATCH(5,Scorecard!$AS$6:$AS$39,0)) -> 9.5111853 | L10: =INDEX(Scorecard!$AT$6:$AT$39,MATCH(5,Scorecard!$AS$6:$AS$39,0)) -> 0.12375724 | M10: =IFERROR(INDEX(Cases!$F$6:$F$10,MATCH(C10,Cases!$C$6:$C$10,0)),"") -> -40.6569
A11: 6 | B11: =INDEX(Scorecard!$A$6:$A$39,MATCH(6,Scorecard!$AS$6:$AS$39,0)) -> Senegal | C11: =INDEX(Scorecard!$B$6:$B$39,MATCH(6,Scorecard!$AS$6:$AS$39,0)) -> SEN | D11: =INDEX(Scorecard!$AC$6:$AC$39,MATCH(6,Scorecard!$AS$6:$AS$39,0)) -> 41.41908 | E11: =INDEX(Scorecard!$AQ$6:$AQ$39,MATCH(6,Scorecard!$AS$6:$AS$39,0)) -> 74.128645 | F11: =INDEX(Scorecard!$AR$6:$AR$39,MATCH(6,Scorecard!$AS$6:$AS$39,0)) -> 55.410651 | G11: =INDEX(Scorecard!$AU$6:$AU$39,MATCH(6,Scorecard!$AS$6:$AS$39,0)) -> Easy but small | H11: =INDEX(Data!$E$6:$E$39,MATCH(6,Scorecard!$AS$6:$AS$39,0)) -> 0.66912649 | I11: =INDEX(Forecast!$J$6:$J$39,MATCH(6,Scorecard!$AS$6:$AS$39,0)) -> 0.85527644 | J11: =INDEX(Pools!$L$6:$L$39,MATCH(6,Scorecard!$AS$6:$AS$39,0)) -> 223.56055 | K11: =INDEX(Pools!$R$6:$R$39,MATCH(6,Scorecard!$AS$6:$AS$39,0)) -> 12.545741 | L11: =INDEX(Scorecard!$AT$6:$AT$39,MATCH(6,Scorecard!$AS$6:$AS$39,0)) -> 0.1286206 | M11: =IFERROR(INDEX(Cases!$F$6:$F$10,MATCH(C11,Cases!$C$6:$C$10,0)),"")
A12: 7 | B12: =INDEX(Scorecard!$A$6:$A$39,MATCH(7,Scorecard!$AS$6:$AS$39,0)) -> Zambia | C12: =INDEX(Scorecard!$B$6:$B$39,MATCH(7,Scorecard!$AS$6:$AS$39,0)) -> ZMB | D12: =INDEX(Scorecard!$AC$6:$AC$39,MATCH(7,Scorecard!$AS$6:$AS$39,0)) -> 39.798722 | E12: =INDEX(Scorecard!$AQ$6:$AQ$39,MATCH(7,Scorecard!$AS$6:$AS$39,0)) -> 75.539456 | F12: =INDEX(Scorecard!$AR$6:$AR$39,MATCH(7,Scorecard!$AS$6:$AS$39,0)) -> 54.830409 | G12: =INDEX(Scorecard!$AU$6:$AU$39,MATCH(7,Scorecard!$AS$6:$AS$39,0)) -> Easy but small | H12: =INDEX(Data!$E$6:$E$39,MATCH(7,Scorecard!$AS$6:$AS$39,0)) -> 0.69310751 | I12: =INDEX(Forecast!$J$6:$J$39,MATCH(7,Scorecard!$AS$6:$AS$39,0)) -> 0.86841881 | J12: =INDEX(Pools!$L$6:$L$39,MATCH(7,Scorecard!$AS$6:$AS$39,0)) -> 258.31363 | K12: =INDEX(Pools!$R$6:$R$39,MATCH(7,Scorecard!$AS$6:$AS$39,0)) -> 14.00703 | L12: =INDEX(Scorecard!$AT$6:$AT$39,MATCH(7,Scorecard!$AS$6:$AS$39,0)) -> 0.13304865 | M12: =IFERROR(INDEX(Cases!$F$6:$F$10,MATCH(C12,Cases!$C$6:$C$10,0)),"")
A13: 8 | B13: =INDEX(Scorecard!$A$6:$A$39,MATCH(8,Scorecard!$AS$6:$AS$39,0)) -> Togo | C13: =INDEX(Scorecard!$B$6:$B$39,MATCH(8,Scorecard!$AS$6:$AS$39,0)) -> TGO | D13: =INDEX(Scorecard!$AC$6:$AC$39,MATCH(8,Scorecard!$AS$6:$AS$39,0)) -> 44.886226 | E13: =INDEX(Scorecard!$AQ$6:$AQ$39,MATCH(8,Scorecard!$AS$6:$AS$39,0)) -> 66.784967 | F13: =INDEX(Scorecard!$AR$6:$AR$39,MATCH(8,Scorecard!$AS$6:$AS$39,0)) -> 54.751485 | G13: =INDEX(Scorecard!$AU$6:$AU$39,MATCH(8,Scorecard!$AS$6:$AS$39,0)) -> Easy but small | H13: =INDEX(Data!$E$6:$E$39,MATCH(8,Scorecard!$AS$6:$AS$39,0)) -> 0.47991838 | I13: =INDEX(Forecast!$J$6:$J$39,MATCH(8,Scorecard!$AS$6:$AS$39,0)) -> 0.72948133 | J13: =INDEX(Pools!$L$6:$L$39,MATCH(8,Scorecard!$AS$6:$AS$39,0)) -> 82.344863 | K13: =INDEX(Pools!$R$6:$R$39,MATCH(8,Scorecard!$AS$6:$AS$39,0)) -> 5.8508673 | L13: =INDEX(Scorecard!$AT$6:$AT$39,MATCH(8,Scorecard!$AS$6:$AS$39,0)) -> 0.12571994 | M13: =IFERROR(INDEX(Cases!$F$6:$F$10,MATCH(C13,Cases!$C$6:$C$10,0)),"")
A14: 9 | B14: =INDEX(Scorecard!$A$6:$A$39,MATCH(9,Scorecard!$AS$6:$AS$39,0)) -> Madagascar | C14: =INDEX(Scorecard!$B$6:$B$39,MATCH(9,Scorecard!$AS$6:$AS$39,0)) -> MDG | D14: =INDEX(Scorecard!$AC$6:$AC$39,MATCH(9,Scorecard!$AS$6:$AS$39,0)) -> 53.522103 | E14: =INDEX(Scorecard!$AQ$6:$AQ$39,MATCH(9,Scorecard!$AS$6:$AS$39,0)) -> 54.901383 | F14: =INDEX(Scorecard!$AR$6:$AR$39,MATCH(9,Scorecard!$AS$6:$AS$39,0)) -> 54.207356 | G14: =INDEX(Scorecard!$AU$6:$AU$39,MATCH(9,Scorecard!$AS$6:$AS$39,0)) -> Big but hard | H14: =INDEX(Data!$E$6:$E$39,MATCH(9,Scorecard!$AS$6:$AS$39,0)) -> 0.19355017 | I14: =INDEX(Forecast!$J$6:$J$39,MATCH(9,Scorecard!$AS$6:$AS$39,0)) -> 0.41223283 | J14: =INDEX(Pools!$L$6:$L$39,MATCH(9,Scorecard!$AS$6:$AS$39,0)) -> 117.79208 | K14: =INDEX(Pools!$R$6:$R$39,MATCH(9,Scorecard!$AS$6:$AS$39,0)) -> 11.032172 | L14: =INDEX(Scorecard!$AT$6:$AT$39,MATCH(9,Scorecard!$AS$6:$AS$39,0)) -> 0.13175402 | M14: =IFERROR(INDEX(Cases!$F$6:$F$10,MATCH(C14,Cases!$C$6:$C$10,0)),"")
A15: 10 | B15: =INDEX(Scorecard!$A$6:$A$39,MATCH(10,Scorecard!$AS$6:$AS$39,0)) -> Liberia | C15: =INDEX(Scorecard!$B$6:$B$39,MATCH(10,Scorecard!$AS$6:$AS$39,0)) -> LBR | D15: =INDEX(Scorecard!$AC$6:$AC$39,MATCH(10,Scorecard!$AS$6:$AS$39,0)) -> 46.72092 | E15: =INDEX(Scorecard!$AQ$6:$AQ$39,MATCH(10,Scorecard!$AS$6:$AS$39,0)) -> 61.940661 | F15: =INDEX(Scorecard!$AR$6:$AR$39,MATCH(10,Scorecard!$AS$6:$AS$39,0)) -> 53.795211 | G15: =INDEX(Scorecard!$AU$6:$AU$39,MATCH(10,Scorecard!$AS$6:$AS$39,0)) -> Prioritise | H15: =INDEX(Data!$E$6:$E$39,MATCH(10,Scorecard!$AS$6:$AS$39,0)) -> 0.47529254 | I15: =INDEX(Forecast!$J$6:$J$39,MATCH(10,Scorecard!$AS$6:$AS$39,0)) -> 0.72580701 | J15: =INDEX(Pools!$L$6:$L$39,MATCH(10,Scorecard!$AS$6:$AS$39,0)) -> 40.90941 | K15: =INDEX(Pools!$R$6:$R$39,MATCH(10,Scorecard!$AS$6:$AS$39,0)) -> 2.921683 | L15: =INDEX(Scorecard!$AT$6:$AT$39,MATCH(10,Scorecard!$AS$6:$AS$39,0)) -> 0.13096788 | M15: =IFERROR(INDEX(Cases!$F$6:$F$10,MATCH(C15,Cases!$C$6:$C$10,0)),"")
A16: 11 | B16: =INDEX(Scorecard!$A$6:$A$39,MATCH(11,Scorecard!$AS$6:$AS$39,0)) -> Ghana | C16: =INDEX(Scorecard!$B$6:$B$39,MATCH(11,Scorecard!$AS$6:$AS$39,0)) -> GHA | D16: =INDEX(Scorecard!$AC$6:$AC$39,MATCH(11,Scorecard!$AS$6:$AS$39,0)) -> 39.312784 | E16: =INDEX(Scorecard!$AQ$6:$AQ$39,MATCH(11,Scorecard!$AS$6:$AS$39,0)) -> 68.744969 | F16: =INDEX(Scorecard!$AR$6:$AR$39,MATCH(11,Scorecard!$AS$6:$AS$39,0)) -> 51.986114 | G16: =INDEX(Scorecard!$AU$6:$AU$39,MATCH(11,Scorecard!$AS$6:$AS$39,0)) -> Easy but small | H16: =INDEX(Data!$E$6:$E$39,MATCH(11,Scorecard!$AS$6:$AS$39,0)) -> 0.78281364 | I16: =INDEX(Forecast!$J$6:$J$39,MATCH(11,Scorecard!$AS$6:$AS$39,0)) -> 0.91329134 | J16: =INDEX(Pools!$L$6:$L$39,MATCH(11,Scorecard!$AS$6:$AS$39,0)) -> 584.03577 | K16: =INDEX(Pools!$R$6:$R$39,MATCH(11,Scorecard!$AS$6:$AS$39,0)) -> 27.533692 | L16: =INDEX(Scorecard!$AT$6:$AT$39,MATCH(11,Scorecard!$AS$6:$AS$39,0)) -> 0.1473334 | M16: =IFERROR(INDEX(Cases!$F$6:$F$10,MATCH(C16,Cases!$C$6:$C$10,0)),"")
A17: 12 | B17: =INDEX(Scorecard!$A$6:$A$39,MATCH(12,Scorecard!$AS$6:$AS$39,0)) -> Guinea | C17: =INDEX(Scorecard!$B$6:$B$39,MATCH(12,Scorecard!$AS$6:$AS$39,0)) -> GIN | D17: =INDEX(Scorecard!$AC$6:$AC$39,MATCH(12,Scorecard!$AS$6:$AS$39,0)) -> 45.636315 | E17: =INDEX(Scorecard!$AQ$6:$AQ$39,MATCH(12,Scorecard!$AS$6:$AS$39,0)) -> 58.825665 | F17: =INDEX(Scorecard!$AR$6:$AR$39,MATCH(12,Scorecard!$AS$6:$AS$39,0)) -> 51.812996 | G17: =INDEX(Scorecard!$AU$6:$AU$39,MATCH(12,Scorecard!$AS$6:$AS$39,0)) -> Prioritise | H17: =INDEX(Data!$E$6:$E$39,MATCH(12,Scorecard!$AS$6:$AS$39,0)) -> 0.2582194 | I17: =INDEX(Forecast!$J$6:$J$39,MATCH(12,Scorecard!$AS$6:$AS$39,0)) -> 0.50427951 | J17: =INDEX(Pools!$L$6:$L$39,MATCH(12,Scorecard!$AS$6:$AS$39,0)) -> 79.592719 | K17: =INDEX(Pools!$R$6:$R$39,MATCH(12,Scorecard!$AS$6:$AS$39,0)) -> 7.0481954 | L17: =INDEX(Scorecard!$AT$6:$AT$39,MATCH(12,Scorecard!$AS$6:$AS$39,0)) -> 0.13015186 | M17: =IFERROR(INDEX(Cases!$F$6:$F$10,MATCH(C17,Cases!$C$6:$C$10,0)),"")
A18: 13 | B18: =INDEX(Scorecard!$A$6:$A$39,MATCH(13,Scorecard!$AS$6:$AS$39,0)) -> Malawi | C18: =INDEX(Scorecard!$B$6:$B$39,MATCH(13,Scorecard!$AS$6:$AS$39,0)) -> MWI | D18: =INDEX(Scorecard!$AC$6:$AC$39,MATCH(13,Scorecard!$AS$6:$AS$39,0)) -> 44.375404 | E18: =INDEX(Scorecard!$AQ$6:$AQ$39,MATCH(13,Scorecard!$AS$6:$AS$39,0)) -> 57.564393 | F18: =INDEX(Scorecard!$AR$6:$AR$39,MATCH(13,Scorecard!$AS$6:$AS$39,0)) -> 50.5415 | G18: =INDEX(Scorecard!$AU$6:$AU$39,MATCH(13,Scorecard!$AS$6:$AS$39,0)) -> Easy but small | H18: =INDEX(Data!$E$6:$E$39,MATCH(13,Scorecard!$AS$6:$AS$39,0)) -> 0.47399198 | I18: =INDEX(Forecast!$J$6:$J$39,MATCH(13,Scorecard!$AS$6:$AS$39,0)) -> 0.72476782 | J18: =INDEX(Pools!$L$6:$L$39,MATCH(13,Scorecard!$AS$6:$AS$39,0)) -> 162.22223 | K18: =INDEX(Pools!$R$6:$R$39,MATCH(13,Scorecard!$AS$6:$AS$39,0)) -> 11.6023 | L18: =INDEX(Scorecard!$AT$6:$AT$39,MATCH(13,Scorecard!$AS$6:$AS$39,0)) -> 0.14773061 | M18: =IFERROR(INDEX(Cases!$F$6:$F$10,MATCH(C18,Cases!$C$6:$C$10,0)),"")
A19: 14 | B19: =INDEX(Scorecard!$A$6:$A$39,MATCH(14,Scorecard!$AS$6:$AS$39,0)) -> Cameroon | C19: =INDEX(Scorecard!$B$6:$B$39,MATCH(14,Scorecard!$AS$6:$AS$39,0)) -> CMR | D19: =INDEX(Scorecard!$AC$6:$AC$39,MATCH(14,Scorecard!$AS$6:$AS$39,0)) -> 48.177479 | E19: =INDEX(Scorecard!$AQ$6:$AQ$39,MATCH(14,Scorecard!$AS$6:$AS$39,0)) -> 51.923556 | F19: =INDEX(Scorecard!$AR$6:$AR$39,MATCH(14,Scorecard!$AS$6:$AS$39,0)) -> 50.015458 | G19: =INDEX(Scorecard!$AU$6:$AU$39,MATCH(14,Scorecard!$AS$6:$AS$39,0)) -> Big but hard | H19: =INDEX(Data!$E$6:$E$39,MATCH(14,Scorecard!$AS$6:$AS$39,0)) -> 0.55065452 | I19: =INDEX(Forecast!$J$6:$J$39,MATCH(14,Scorecard!$AS$6:$AS$39,0)) -> 0.78171317 | J19: =INDEX(Pools!$L$6:$L$39,MATCH(14,Scorecard!$AS$6:$AS$39,0)) -> 330.66089 | K19: =INDEX(Pools!$R$6:$R$39,MATCH(14,Scorecard!$AS$6:$AS$39,0)) -> 21.64823 | L19: =INDEX(Scorecard!$AT$6:$AT$39,MATCH(14,Scorecard!$AS$6:$AS$39,0)) -> 0.17139103 | M19: =IFERROR(INDEX(Cases!$F$6:$F$10,MATCH(C19,Cases!$C$6:$C$10,0)),"")
A20: 15 | B20: =INDEX(Scorecard!$A$6:$A$39,MATCH(15,Scorecard!$AS$6:$AS$39,0)) -> South Africa | C20: =INDEX(Scorecard!$B$6:$B$39,MATCH(15,Scorecard!$AS$6:$AS$39,0)) -> ZAF | D20: =INDEX(Scorecard!$AC$6:$AC$39,MATCH(15,Scorecard!$AS$6:$AS$39,0)) -> 41.456257 | E20: =INDEX(Scorecard!$AQ$6:$AQ$39,MATCH(15,Scorecard!$AS$6:$AS$39,0)) -> 58.540753 | F20: =INDEX(Scorecard!$AR$6:$AR$39,MATCH(15,Scorecard!$AS$6:$AS$39,0)) -> 49.263379 | G20: =INDEX(Scorecard!$AU$6:$AU$39,MATCH(15,Scorecard!$AS$6:$AS$39,0)) -> Easy but small | H20: =INDEX(Data!$E$6:$E$39,MATCH(15,Scorecard!$AS$6:$AS$39,0)) -> 0.31623202 | I20: =INDEX(Forecast!$J$6:$J$39,MATCH(15,Scorecard!$AS$6:$AS$39,0)) -> 0.5747407 | J20: =INDEX(Pools!$L$6:$L$39,MATCH(15,Scorecard!$AS$6:$AS$39,0)) -> 377.49392 | K20: =INDEX(Pools!$R$6:$R$39,MATCH(15,Scorecard!$AS$6:$AS$39,0)) -> 31.699666 | L20: =INDEX(Scorecard!$AT$6:$AT$39,MATCH(15,Scorecard!$AS$6:$AS$39,0)) -> 0.13736149 | M20: =IFERROR(INDEX(Cases!$F$6:$F$10,MATCH(C20,Cases!$C$6:$C$10,0)),"")
A21: 16 | B21: =INDEX(Scorecard!$A$6:$A$39,MATCH(16,Scorecard!$AS$6:$AS$39,0)) -> Mozambique | C21: =INDEX(Scorecard!$B$6:$B$39,MATCH(16,Scorecard!$AS$6:$AS$39,0)) -> MOZ | D21: =INDEX(Scorecard!$AC$6:$AC$39,MATCH(16,Scorecard!$AS$6:$AS$39,0)) -> 49.845521 | E21: =INDEX(Scorecard!$AQ$6:$AQ$39,MATCH(16,Scorecard!$AS$6:$AS$39,0)) -> 46.423596 | F21: =INDEX(Scorecard!$AR$6:$AR$39,MATCH(16,Scorecard!$AS$6:$AS$39,0)) -> 48.10414 | G21: =INDEX(Scorecard!$AU$6:$AU$39,MATCH(16,Scorecard!$AS$6:$AS$39,0)) -> Big but hard | H21: =INDEX(Data!$E$6:$E$39,MATCH(16,Scorecard!$AS$6:$AS$39,0)) -> 0.45720986 | I21: =INDEX(Forecast!$J$6:$J$39,MATCH(16,Scorecard!$AS$6:$AS$39,0)) -> 0.7111102 | J21: =INDEX(Pools!$L$6:$L$39,MATCH(16,Scorecard!$AS$6:$AS$39,0)) -> 211.26568 | K21: =INDEX(Pools!$R$6:$R$39,MATCH(16,Scorecard!$AS$6:$AS$39,0)) -> 15.389805 | L21: =INDEX(Scorecard!$AT$6:$AT$39,MATCH(16,Scorecard!$AS$6:$AS$39,0)) -> 0.16962438 | M21: =IFERROR(INDEX(Cases!$F$6:$F$10,MATCH(C21,Cases!$C$6:$C$10,0)),"")
A22: 17 | B22: =INDEX(Scorecard!$A$6:$A$39,MATCH(17,Scorecard!$AS$6:$AS$39,0)) -> Mali | C22: =INDEX(Scorecard!$B$6:$B$39,MATCH(17,Scorecard!$AS$6:$AS$39,0)) -> MLI | D22: =INDEX(Scorecard!$AC$6:$AC$39,MATCH(17,Scorecard!$AS$6:$AS$39,0)) -> 50.112931 | E22: =INDEX(Scorecard!$AQ$6:$AQ$39,MATCH(17,Scorecard!$AS$6:$AS$39,0)) -> 45.048962 | F22: =INDEX(Scorecard!$AR$6:$AR$39,MATCH(17,Scorecard!$AS$6:$AS$39,0)) -> 47.51353 | G22: =INDEX(Scorecard!$AU$6:$AU$39,MATCH(17,Scorecard!$AS$6:$AS$39,0)) -> Big but hard | H22: =INDEX(Data!$E$6:$E$39,MATCH(17,Scorecard!$AS$6:$AS$39,0)) -> 0.48387616 | I22: =INDEX(Forecast!$J$6:$J$39,MATCH(17,Scorecard!$AS$6:$AS$39,0)) -> 0.73259813 | J22: =INDEX(Pools!$L$6:$L$39,MATCH(17,Scorecard!$AS$6:$AS$39,0)) -> 198.02577 | K22: =INDEX(Pools!$R$6:$R$39,MATCH(17,Scorecard!$AS$6:$AS$39,0)) -> 14.008502 | L22: =INDEX(Scorecard!$AT$6:$AT$39,MATCH(17,Scorecard!$AS$6:$AS$39,0)) -> 0.16914497 | M22: =IFERROR(INDEX(Cases!$F$6:$F$10,MATCH(C22,Cases!$C$6:$C$10,0)),"")
A23: 18 | B23: =INDEX(Scorecard!$A$6:$A$39,MATCH(18,Scorecard!$AS$6:$AS$39,0)) -> Sierra Leone | C23: =INDEX(Scorecard!$B$6:$B$39,MATCH(18,Scorecard!$AS$6:$AS$39,0)) -> SLE | D23: =INDEX(Scorecard!$AC$6:$AC$39,MATCH(18,Scorecard!$AS$6:$AS$39,0)) -> 41.233896 | E23: =INDEX(Scorecard!$AQ$6:$AQ$39,MATCH(18,Scorecard!$AS$6:$AS$39,0)) -> 53.356799 | F23: =INDEX(Scorecard!$AR$6:$AR$39,MATCH(18,Scorecard!$AS$6:$AS$39,0)) -> 46.905316 | G23: =INDEX(Scorecard!$AU$6:$AU$39,MATCH(18,Scorecard!$AS$6:$AS$39,0)) -> Deprioritise | H23: =INDEX(Data!$E$6:$E$39,MATCH(18,Scorecard!$AS$6:$AS$39,0)) -> 0.32195726 | I23: =INDEX(Forecast!$J$6:$J$39,MATCH(18,Scorecard!$AS$6:$AS$39,0)) -> 0.58116821 | J23: =INDEX(Pools!$L$6:$L$39,MATCH(18,Scorecard!$AS$6:$AS$39,0)) -> 58.945239 | K23: =INDEX(Pools!$R$6:$R$39,MATCH(18,Scorecard!$AS$6:$AS$39,0)) -> 4.9232272 | L23: =INDEX(Scorecard!$AT$6:$AT$39,MATCH(18,Scorecard!$AS$6:$AS$39,0)) -> 0.14893204 | M23: =IFERROR(INDEX(Cases!$F$6:$F$10,MATCH(C23,Cases!$C$6:$C$10,0)),"")
A24: 19 | B24: =INDEX(Scorecard!$A$6:$A$39,MATCH(19,Scorecard!$AS$6:$AS$39,0)) -> Congo, Rep. | C24: =INDEX(Scorecard!$B$6:$B$39,MATCH(19,Scorecard!$AS$6:$AS$39,0)) -> COG | D24: =INDEX(Scorecard!$AC$6:$AC$39,MATCH(19,Scorecard!$AS$6:$AS$39,0)) -> 36.947665 | E24: =INDEX(Scorecard!$AQ$6:$AQ$39,MATCH(19,Scorecard!$AS$6:$AS$39,0)) -> 59.293913 | F24: =INDEX(Scorecard!$AR$6:$AR$39,MATCH(19,Scorecard!$AS$6:$AS$39,0)) -> 46.80568 | G24: =INDEX(Scorecard!$AU$6:$AU$39,MATCH(19,Scorecard!$AS$6:$AS$39,0)) -> Easy but small | H24: =INDEX(Data!$E$6:$E$39,MATCH(19,Scorecard!$AS$6:$AS$39,0)) -> 0.51592118 | I24: =INDEX(Forecast!$J$6:$J$39,MATCH(19,Scorecard!$AS$6:$AS$39,0)) -> 0.7569571 | J24: =INDEX(Pools!$L$6:$L$39,MATCH(19,Scorecard!$AS$6:$AS$39,0)) -> 77.635606 | K24: =INDEX(Pools!$R$6:$R$39,MATCH(19,Scorecard!$AS$6:$AS$39,0)) -> 5.2956252 | L24: =INDEX(Scorecard!$AT$6:$AT$39,MATCH(19,Scorecard!$AS$6:$AS$39,0)) -> 0.15781991 | M24: =IFERROR(INDEX(Cases!$F$6:$F$10,MATCH(C24,Cases!$C$6:$C$10,0)),"")
A25: 20 | B25: =INDEX(Scorecard!$A$6:$A$39,MATCH(20,Scorecard!$AS$6:$AS$39,0)) -> Nigeria | C25: =INDEX(Scorecard!$B$6:$B$39,MATCH(20,Scorecard!$AS$6:$AS$39,0)) -> NGA | D25: =INDEX(Scorecard!$AC$6:$AC$39,MATCH(20,Scorecard!$AS$6:$AS$39,0)) -> 68.731423 | E25: =INDEX(Scorecard!$AQ$6:$AQ$39,MATCH(20,Scorecard!$AS$6:$AS$39,0)) -> 30.497663 | F25: =INDEX(Scorecard!$AR$6:$AR$39,MATCH(20,Scorecard!$AS$6:$AS$39,0)) -> 45.783706 | G25: =INDEX(Scorecard!$AU$6:$AU$39,MATCH(20,Scorecard!$AS$6:$AS$39,0)) -> Big but hard | H25: =INDEX(Data!$E$6:$E$39,MATCH(20,Scorecard!$AS$6:$AS$39,0)) -> 0.32790752 | I25: =INDEX(Forecast!$J$6:$J$39,MATCH(20,Scorecard!$AS$6:$AS$39,0)) -> 0.58775638 | J25: =INDEX(Pools!$L$6:$L$39,MATCH(20,Scorecard!$AS$6:$AS$39,0)) -> 1320.9712 | K25: =INDEX(Pools!$R$6:$R$39,MATCH(20,Scorecard!$AS$6:$AS$39,0)) -> 109.70977 | L25: =INDEX(Scorecard!$AT$6:$AT$39,MATCH(20,Scorecard!$AS$6:$AS$39,0)) -> 0.18958428 | M25: =IFERROR(INDEX(Cases!$F$6:$F$10,MATCH(C25,Cases!$C$6:$C$10,0)),"")
A26: 21 | B26: =INDEX(Scorecard!$A$6:$A$39,MATCH(21,Scorecard!$AS$6:$AS$39,0)) -> Burkina Faso | C26: =INDEX(Scorecard!$B$6:$B$39,MATCH(21,Scorecard!$AS$6:$AS$39,0)) -> BFA | D26: =INDEX(Scorecard!$AC$6:$AC$39,MATCH(21,Scorecard!$AS$6:$AS$39,0)) -> 46.83604 | E26: =INDEX(Scorecard!$AQ$6:$AQ$39,MATCH(21,Scorecard!$AS$6:$AS$39,0)) -> 38.75993 | F26: =INDEX(Scorecard!$AR$6:$AR$39,MATCH(21,Scorecard!$AS$6:$AS$39,0)) -> 42.607061 | G26: =INDEX(Scorecard!$AU$6:$AU$39,MATCH(21,Scorecard!$AS$6:$AS$39,0)) -> Big but hard | H26: =INDEX(Data!$E$6:$E$39,MATCH(21,Scorecard!$AS$6:$AS$39,0)) -> 0.44157364 | I26: =INDEX(Forecast!$J$6:$J$39,MATCH(21,Scorecard!$AS$6:$AS$39,0)) -> 0.69795622 | J26: =INDEX(Pools!$L$6:$L$39,MATCH(21,Scorecard!$AS$6:$AS$39,0)) -> 174.90816 | K26: =INDEX(Pools!$R$6:$R$39,MATCH(21,Scorecard!$AS$6:$AS$39,0)) -> 12.957196 | L26: =INDEX(Scorecard!$AT$6:$AT$39,MATCH(21,Scorecard!$AS$6:$AS$39,0)) -> 0.17225921 | M26: =IFERROR(INDEX(Cases!$F$6:$F$10,MATCH(C26,Cases!$C$6:$C$10,0)),"")
A27: 22 | B27: =INDEX(Scorecard!$A$6:$A$39,MATCH(22,Scorecard!$AS$6:$AS$39,0)) -> Chad | C27: =INDEX(Scorecard!$B$6:$B$39,MATCH(22,Scorecard!$AS$6:$AS$39,0)) -> TCD | D27: =INDEX(Scorecard!$AC$6:$AC$39,MATCH(22,Scorecard!$AS$6:$AS$39,0)) -> 44.952903 | E27: =INDEX(Scorecard!$AQ$6:$AQ$39,MATCH(22,Scorecard!$AS$6:$AS$39,0)) -> 35.626108 | F27: =INDEX(Scorecard!$AR$6:$AR$39,MATCH(22,Scorecard!$AS$6:$AS$39,0)) -> 40.018708 | G27: =INDEX(Scorecard!$AU$6:$AU$39,MATCH(22,Scorecard!$AS$6:$AS$39,0)) -> Deprioritise | H27: =INDEX(Data!$E$6:$E$39,MATCH(22,Scorecard!$AS$6:$AS$39,0)) -> 0.13335894 | I27: =INDEX(Forecast!$J$6:$J$39,MATCH(22,Scorecard!$AS$6:$AS$39,0)) -> 0.31019278 | J27: =INDEX(Pools!$L$6:$L$39,MATCH(22,Scorecard!$AS$6:$AS$39,0)) -> 51.557008 | K27: =INDEX(Pools!$R$6:$R$39,MATCH(22,Scorecard!$AS$6:$AS$39,0)) -> 5.0736873 | L27: =INDEX(Scorecard!$AT$6:$AT$39,MATCH(22,Scorecard!$AS$6:$AS$39,0)) -> 0.15464262 | M27: =IFERROR(INDEX(Cases!$F$6:$F$10,MATCH(C27,Cases!$C$6:$C$10,0)),"")
A28: 23 | B28: =INDEX(Scorecard!$A$6:$A$39,MATCH(23,Scorecard!$AS$6:$AS$39,0)) -> Ethiopia | C28: =INDEX(Scorecard!$B$6:$B$39,MATCH(23,Scorecard!$AS$6:$AS$39,0)) -> ETH | D28: =INDEX(Scorecard!$AC$6:$AC$39,MATCH(23,Scorecard!$AS$6:$AS$39,0)) -> 58.126283 | E28: =INDEX(Scorecard!$AQ$6:$AQ$39,MATCH(23,Scorecard!$AS$6:$AS$39,0)) -> 26.919982 | F28: =INDEX(Scorecard!$AR$6:$AR$39,MATCH(23,Scorecard!$AS$6:$AS$39,0)) -> 39.557028 | G28: =INDEX(Scorecard!$AU$6:$AU$39,MATCH(23,Scorecard!$AS$6:$AS$39,0)) -> Big but hard | H28: =INDEX(Data!$E$6:$E$39,MATCH(23,Scorecard!$AS$6:$AS$39,0)) -> 0.094548896 | I28: =INDEX(Forecast!$J$6:$J$39,MATCH(23,Scorecard!$AS$6:$AS$39,0)) -> 0.23380419 | J28: =INDEX(Pools!$L$6:$L$39,MATCH(23,Scorecard!$AS$6:$AS$39,0)) -> 103.8991 | K28: =INDEX(Pools!$R$6:$R$39,MATCH(23,Scorecard!$AS$6:$AS$39,0)) -> 10.542931 | L28: =INDEX(Scorecard!$AT$6:$AT$39,MATCH(23,Scorecard!$AS$6:$AS$39,0)) -> 0.17933966 | M28: =IFERROR(INDEX(Cases!$F$6:$F$10,MATCH(C28,Cases!$C$6:$C$10,0)),"")
A29: 24 | B29: =INDEX(Scorecard!$A$6:$A$39,MATCH(24,Scorecard!$AS$6:$AS$39,0)) -> Zimbabwe | C29: =INDEX(Scorecard!$B$6:$B$39,MATCH(24,Scorecard!$AS$6:$AS$39,0)) -> ZWE | D29: =INDEX(Scorecard!$AC$6:$AC$39,MATCH(24,Scorecard!$AS$6:$AS$39,0)) -> 42.640538 | E29: =INDEX(Scorecard!$AQ$6:$AQ$39,MATCH(24,Scorecard!$AS$6:$AS$39,0)) -> 35.856925 | F29: =INDEX(Scorecard!$AR$6:$AR$39,MATCH(24,Scorecard!$AS$6:$AS$39,0)) -> 39.1019 | G29: =INDEX(Scorecard!$AU$6:$AU$39,MATCH(24,Scorecard!$AS$6:$AS$39,0)) -> Deprioritise | H29: =INDEX(Data!$E$6:$E$39,MATCH(24,Scorecard!$AS$6:$AS$39,0)) -> 0.43331737 | I29: =INDEX(Forecast!$J$6:$J$39,MATCH(24,Scorecard!$AS$6:$AS$39,0)) -> 0.6908366 | J29: =INDEX(Pools!$L$6:$L$39,MATCH(24,Scorecard!$AS$6:$AS$39,0)) -> 159.41589 | K29: =INDEX(Pools!$R$6:$R$39,MATCH(24,Scorecard!$AS$6:$AS$39,0)) -> 11.913423 | L29: =INDEX(Scorecard!$AT$6:$AT$39,MATCH(24,Scorecard!$AS$6:$AS$39,0)) -> 0.177662 | M29: =IFERROR(INDEX(Cases!$F$6:$F$10,MATCH(C29,Cases!$C$6:$C$10,0)),"")
A30: 25 | B30: =INDEX(Scorecard!$A$6:$A$39,MATCH(25,Scorecard!$AS$6:$AS$39,0)) -> Niger | C30: =INDEX(Scorecard!$B$6:$B$39,MATCH(25,Scorecard!$AS$6:$AS$39,0)) -> NER | D30: =INDEX(Scorecard!$AC$6:$AC$39,MATCH(25,Scorecard!$AS$6:$AS$39,0)) -> 45.033287 | E30: =INDEX(Scorecard!$AQ$6:$AQ$39,MATCH(25,Scorecard!$AS$6:$AS$39,0)) -> 25.295115 | F30: =INDEX(Scorecard!$AR$6:$AR$39,MATCH(25,Scorecard!$AS$6:$AS$39,0)) -> 33.750884 | G30: =INDEX(Scorecard!$AU$6:$AU$39,MATCH(25,Scorecard!$AS$6:$AS$39,0)) -> Deprioritise | H30: =INDEX(Data!$E$6:$E$39,MATCH(25,Scorecard!$AS$6:$AS$39,0)) -> 0.057003706 | I30: =INDEX(Forecast!$J$6:$J$39,MATCH(25,Scorecard!$AS$6:$AS$39,0)) -> 0.15012976 | J30: =INDEX(Pools!$L$6:$L$39,MATCH(25,Scorecard!$AS$6:$AS$39,0)) -> 16.560831 | K30: =INDEX(Pools!$R$6:$R$39,MATCH(25,Scorecard!$AS$6:$AS$39,0)) -> 1.7295544 | L30: =INDEX(Scorecard!$AT$6:$AT$39,MATCH(25,Scorecard!$AS$6:$AS$39,0)) -> 0.16309859 | M30: =IFERROR(INDEX(Cases!$F$6:$F$10,MATCH(C30,Cases!$C$6:$C$10,0)),"")
A32: Home market for reference:
A33: Kenya mobile money adoption 2024 | D33: =INDEX(Data!$E$6:$E$39,MATCH("KEN",Data!$B$6:$B$39,0)) -> 0.87499411
A34: Candidate markets scored (34 markets with 2024 data; home market and markets under the size screen excluded) | D34: =SUM(Data!AB6:AB39) -> 25

Sheet Inputs
A1: Inputs and assumptions
A2: Blue = input you can change. Tags: [S] sourced, [A] analyst assumption, [E] estimated in Python, [S/A] sourced with analyst adjustment.
A4: Input | B4: Unit | C4: Low | D4: Base | E4: High | F4: Tag | G4: Source or rationale
A5: 1. Timeline and forecast
A6: Base year (latest Findex survey) | B6: year | D6: 2024 | F6: [S] | G6: S1: Global Findex 2025 reports the 2024 survey round.
A7: Target year | B7: year | D7: 2030 | F7: [A] | G7: Planning horizon for the expansion decision.
A8: Years from base to target | B8: years | D8: =D7-D6 -> 6 | F8: calc
A9: Adoption ceiling in forecasts | B9: % of adults | D9: 0.92 | F9: [A] | G9: Just above Kenya's 87.5% (S1). Keeps the logistic curve from passing near-universal use.
A10: Minimum market size to be a candidate | B10: adults | D10: 3000000 | F10: [A] | G10: Below this, a regional platform cannot cover its fixed costs (see Pools column V).
A11: Pooled growth of logit(adoption) | B11: per year | D11: 0.17872706 | F11: [E] | G11: Median of country trends 2014-2024 (analysis/model.py). Back-test: beats country-specific trends (Robustness sheet).
A12: Weight on a country's own trend | B12: 0 to 1 | D12: 0 | F12: [E] | G12: Chosen by back-test: 0 gave the lowest 2024 forecast error. Raise it to give each country its own growth rate.
A13: Floor on growth | B13: per year | D13: 0 | F13: [A]
A14: Cap on growth | B14: per year | D14: 0.5 | F14: [A]
A15: 2. Scenarios
A16: Growth multiplier on adoption trend | B16: x | C16: 0.5 | D16: 1 | E16: 1.5 | F16: [A] | G16: Low halves the trend; High raises it by half. Back-test showed the Base trend over-predicted 2024 by 2.8 points on average.
A17: Revenue per active user in the reference market (Kenya income, mobile-led) | B17: USD per year | C17: 15 | D17: 25 | E17: 32 | F17: [S/A] | G17: S4: Airtel Money East Africa revenue per customer about $24.7. S3: M-Pesa about $32 per active user. Low = price compression; Airtel Money Nigeria is only about $3.3 (S4).
A18: Operator's share of NEW users by 2030 | B18: % | C18: 0.08 | D18: 0.15 | E18: 0.22 | F18: [A] | G18: What a well-funded challenger wins of adults who start using mobile money after 2024. Tested through the break-even share.
A19: Operator's share of EXISTING users | B19: % | C19: 0.015 | D19: 0.03 | E19: 0.05 | F19: [A] | G19: Switching or multi-homing by people who already use mobile money.
A20: Scenario weight for expected NPV | B20: % | C20: 0.25 | D20: 0.5 | E20: 0.25 | F20: [A] | G20: Judgement weights; the Low and High cases are symmetric around Base.
A21: 3. Revenue per user by market
A22: Income elasticity of revenue per user | B22: x | D22: 0.35 | F22: [A] | G22: Revenue per user rises less than proportionally with income (Francophone Africa earns more per customer than its income implies: S4).
A23: Income factor floor | B23: x | D23: 0.5 | F23: [A]
A24: Income factor cap | B24: x | D24: 1.3 | F24: [A]
A25: Elasticity to mobile-led share (mobile money / any account) | B25: x | D25: 1 | F25: [S/A] | G25: Bank-led markets earn far less per mobile money customer: Airtel Money Nigeria about $3.3 against $24.7 in East Africa (S4).
A26: Structure factor floor | B26: x | D26: 0.25 | F26: [A]
A27: Structure factor cap | B27: x | D27: 1 | F27: [A]
A28: 4. Business case for the entrant (USD millions unless stated)
A29: Contribution margin after agent commissions and variable cost | B29: % of revenue | D29: 0.5 | F29: [A] | G29: Mobile money is high-margin once agent commissions are paid; tested in Sensitivity.
A30: Fixed operating cost per year (reference-size market) | B30: $m | D30: 12 | F30: [A] | G30: Team, compliance, technology and brand. Scaled by market size (below).
A31: Acquisition cost per new operator user | B31: $ | D31: 3 | F31: [A] | G31: Agent onboarding and promotions.
A32: Launch investment (licence, platform, agent seeding), reference-size market | B32: $m | D32: 20 | F32: [A] | G32: Spent in 2026, one year before launch. Assumes a build or partnership entry, not an acquisition.
A33: Terminal value multiple on 2035 EBITDA | B33: x | D33: 5 | F33: [A]
A34: Reference market size for cost scaling | B34: adults | D34: 20000000 | F34: [A]
A35: Cost-scaling exponent | B35: x | D35: 0.4 | F35: [A] | G35: Costs rise with market size, but less than proportionally.
A36: Cost scale floor | B36: x | D36: 0.6 | F36: [A]
A37: Cost scale cap | B37: x | D37: 2 | F37: [A]
A38: Discount rate, base (USD) | B38: % | D38: 0.12 | F38: [A]
A39: Premium for weak macro stability (at score 0) | B39: % | D39: 0.04 | F39: [A]
A40: Premium for fragility (at score 0) | B40: % | D40: 0.04 | F40: [A] | G40: Scaled by the World Bank FY26 fragile-situations flag (S5).
A41: Share of target users reached, 2027 (launch year) | B41: % | D41: 0.1 | F41: [A]
A42: Ramp 2028 | B42: % | D42: 0.35 | F42: [A]
A43: Ramp 2029 | B43: % | D43: 0.65 | F43: [A]
A44: Ramp 2030 and after | B44: % | D44: 1 | F44: [A]
A45: 5. Scoring weights (each block sums to 100%)
A46: Attractiveness: Winnable revenue in 2030 (log scale) | B46: weight | D46: 0.35 | F46: [A]
A47: Attractiveness: Growth of the revenue pool 2024 to 2030 | B47: weight | D47: 0.2 | F47: [A]
A48: Attractiveness: Merchant-payment gap to Kenya | B48: weight | D48: 0.15 | F48: [A]
A49: Attractiveness: Remittance intensity (share of GDP) | B49: weight | D49: 0.15 | F49: [A]
A50: Attractiveness: Inclusion gap (gender and income) | B50: weight | D50: 0.15 | F50: [A]
A51: Attractiveness weights total | B51: check | D51: =SUM(D46:D50) -> 1 | F51: calc
A52: Ease: Digital readiness (phones, internet, electricity, urban) | B52: weight | D52: 0.2 | F52: [A]
A53: Ease: Macro stability (inflation, currency, growth) | B53: weight | D53: 0.2 | F53: [A]
A54: Ease: Mobile-led market (mobile money share of accounts) | B54: weight | D54: 0.15 | F54: [A]
A55: Ease: Proximity to Kenya (EAC and corridor markets) | B55: weight | D55: 0.15 | F55: [A]
A56: Ease: Momentum (adoption gain 2017 to 2024) | B56: weight | D56: 0.1 | F56: [A]
A57: Ease: Institutional stability (World Bank FY26 fragile-situations list) | B57: weight | D57: 0.2 | F57: [A]
A58: Ease weights total | B58: check | D58: =SUM(D52:D57) -> 1 | F58: calc
A59: Cap on mobile subscriptions per 100 people | B59: per 100 | D59: 120 | F59: [A]
A60: Cap on remittances (% of GDP) | B60: % | D60: 15 | F60: [A]
A61: Cap on inflation (average 2022 to 2024) | B61: % | D61: 40 | F61: [A]
A62: Cap on currency depreciation (average 2022 to 2024) | B62: % a year | D62: 40 | F62: [A]
A63: Floor on currency depreciation | B63: % a year | D63: -5 | F63: [A]
A64: 6. Home-market anchors (read from Data)
A65: Kenya GDP per capita, PPP (2021 intl $) | B65: $ | D65: =INDEX(Data!$J$6:$J$39,MATCH("KEN",Data!$B$6:$B$39,0)) -> 5841.5987 | F65: [S]
A66: Kenya mobile-led share | B66: ratio | D66: =MIN(1,INDEX(Data!$E$6:$E$39,MATCH("KEN",Data!$B$6:$B$39,0))/INDEX(Data!$F$6:$F$39,MATCH("KEN",Data!$B$6:$B$39,0))) -> 0.97092201 | F66: [S]
A67: Kenya merchant-payment share of adults | B67: % | D67: =INDEX(Data!$H$6:$H$39,MATCH("KEN",Data!$B$6:$B$39,0)) -> 0.55757002 | F67: [S]
A68: 7. Calibration of revenue per user (sourced company figures)
A69: Safaricom M-Pesa revenue, FY to March 2026 | B69: KES bn | D69: 182.73 | F69: [S] | G69: S3: Safaricom FY2026 results as reported by HapaKenya.
A70: Safaricom M-Pesa active customers (group) | B70: million | D70: 43.69 | F70: [S] | G70: S3. Definition (monthly or 30-day) not stated; group figure.
A71: KES per USD (WDI 2024) | B71: KES | D71: 129 | F71: [S] | G71: S2: WDI PA.NUS.FCRF for Kenya, 2024 (approximate; used only for this calibration).
A72: M-Pesa revenue per active customer | B72: USD per year | D72: =D69*1000/D70/D71 -> 32.421873 | F72: calc
A73: Airtel Money East Africa revenue, FY to March 2026 | B73: $m | D73: 1009 | F73: [S] | G73: S4: Airtel Africa FY2026 final results.
A74: Airtel Money East Africa customers | B74: million | D74: 40.9 | F74: [S] | G74: S4
A75: Airtel Money East Africa revenue per customer | B75: USD per year | D75: =D73/D74 -> 24.669927 | F75: calc
A76: Airtel Money Nigeria revenue | B76: $m | D76: 9 | F76: [S] | G76: S4
A77: Airtel Money Nigeria customers | B77: million | D77: 2.7 | F77: [S] | G77: S4
A78: Airtel Money Nigeria revenue per customer | B78: USD per year | D78: =D76/D77 -> 3.3333333 | F78: calc

Sheet Data
A1: Market data: 34 sub-Saharan African markets with Global Findex 2024 results
A2: Sources: S1 Global Findex 2025 (survey 2024); S2 World Development Indicators (updated 8 Oct 2026); S5 World Bank FY26 fragile-situations list. Blank = not available.
D4: Findex (S1) | J4: WDI (S2) | T4: Findex segments (S1) | W4: Judgement / World Bank (S5)
A5: Country | B5: ISO3 | C5: Income group (World Bank) | D5: Adults 2024 | E5: Mobile money account 2024 | F5: Any account 2024 | G5: Financial-institution account 2024 | H5: Digital merchant payment 2024 | I5: Mobile money account 2017 | J5: GDP per capita, PPP (2021 intl $) | K5: Urban population % | L5: Mobile subscriptions per 100 | M5: Internet users % | N5: Electricity access % | O5: Remittances % of GDP | P5: Population growth % a year | Q5: Inflation, average 2022-24 % | R5: Currency depreciation, average 2022-24 % a year | S5: GDP growth, average 2022-24 % | T5: Gender gap in mobile money, pp (men minus women) | U5: Income gap, pp (richest 60% minus poorest 40%) | V5: Rural gap, pp (urban minus rural) | W5: Proximity to Kenya (0-100) [A] | X5: Institutional stability (0-100) [S] | Y5: Own-trend growth of logit(adoption) per year | Z5: Home market | AA5: Meets size screen | AB5: Candidate
A6: Benin | B6: BEN | C6: Lower middle income | D6: 8207504 | E6: 0.44872852 | F6: 0.51843206 | G6: 0.19906178 | H6: 0.067646851 | I6: 0.18093838 | J6: 3901.3259 | K6: 52.545535 | L6: 125.94087 | M6: 33.983799 | N6: 59 | O6: 1.720825 | P6: 2.4617536 | Q6: 1.7501368 | R6: 2.9729476 | S6: 6.68628 | T6: 10.173517 | U6: 16.364479 | V6: 1.7812899 | W6: 20 | X6: 100 | Y6: 0.35001352 | Z6: =IF(B6="KEN",1,0) -> 0 | AA6: =IF(D6>=Inputs!$D$10,1,0) -> 1 | AB6: =IF(AND(Z6=0,AA6=1),1,0) -> 1
A7: Botswana | B7: BWA | C7: Upper middle income | D7: 1679590 | E7: 0.51617816 | F7: 0.61438469 | G7: 0.41604356 | H7: 0.25596427 | I7: 0.24378307 | J7: 18107.614 | K7: 67.462354 | L7: 163.99992 | M7: 57.4595 | N7: 80.2 | O7: 0.66523525 | P7: 1.6353841 | Q7: 6.5171781 | R7: 6.7186259 | S7: 1.9713985 | T7: 4.3509577 | U7: 23.16161 | V7: 1.4630648 | W7: 20 | X7: 100 | Y7: 0.13346244 | Z7: =IF(B7="KEN",1,0) -> 0 | AA7: =IF(D7>=Inputs!$D$10,1,0) -> 0 | AB7: =IF(AND(Z7=0,AA7=1),1,0) -> 0
A8: Burkina Faso | B8: BFA | C8: Low income | D8: 13262560 | E8: 0.44157364 | F8: 0.51427491 | G8: 0.20549892 | H8: 0.12044409 | I8: 0.33022799 | J8: 2548.5025 | K8: 28.335251 | L8: 116.58959 | M8: 28.252701 | N8: 34 | O8: 2.5727498 | P8: 2.2459773 | Q8: 6.4079877 | R8: 2.9775832 | S8: 3.1536549 | T8: 13.167098 | U8: 18.91277 | V8: 20.202327 | W8: 20 | X8: 0 | Y8: 0.26293923 | Z8: =IF(B8="KEN",1,0) -> 0 | AA8: =IF(D8>=Inputs!$D$10,1,0) -> 1 | AB8: =IF(AND(Z8=0,AA8=1),1,0) -> 1
A9: Cameroon | B9: CMR | C9: Lower middle income | D9: 16524096 | E9: 0.55065452 | F9: 0.60873791 | G9: 0.20997299 | H9: 0.20307798 | I9: 0.1513783 | J9: 4916.9335 | K9: 55.403175 | L9: 108.21313 | M9: 46.258801 | N9: 72 | O9: 1.2949265 | P9: 2.6126829 | Q9: 6.0546015 | R9: 2.9775832 | S9: 3.5363567 | T9: 14.60422 | U9: 26.161748 | V9: 23.508297 | W9: 20 | X9: 0 | Y9: 0.41137771 | Z9: =IF(B9="KEN",1,0) -> 0 | AA9: =IF(D9>=Inputs!$D$10,1,0) -> 1 | AB9: =IF(AND(Z9=0,AA9=1),1,0) -> 1
A10: Chad | B10: TCD | C10: Low income | D10: 10289880 | E10: 0.13335894 | F10: 0.2089836 | G10: 0.1500209 | H10: 0.050241056 | I10: 0.1523341 | J10: 2430.733 | K10: 26.931529 | L10: 72.928978 | M10: 12.6269 | N10: 13.4 | P10: 4.9485303 | Q10: 8.5079637 | R10: 2.9775832 | S10: 4.360139 | T10: 3.5387781 | U10: 2.7392581 | V10: 8.4392212 | W10: 20 | X10: 40 | Y10: 0.066901946 | Z10: =IF(B10="KEN",1,0) -> 0 | AA10: =IF(D10>=Inputs!$D$10,1,0) -> 1 | AB10: =IF(AND(Z10=0,AA10=1),1,0) -> 1
A11: Comoros | B11: COM | C11: Lower middle income | D11: 532331 | E11: 0.14093786 | F11: 0.45459397 | G11: 0.40847664 | H11: 0.067846207 | J11: 3556.0384 | K11: 33.539222 | L11: 109.85563 | M11: 32.517502 | N11: 91.7 | O11: 20.844476 | P11: 1.8918279 | Q11: 8.6525657 | R11: 2.9557096 | S11: 2.98038 | T11: 8.5239143 | U11: 5.9612696 | V11: -4.7260982 | W11: 20 | X11: 40 | Z11: =IF(B11="KEN",1,0) -> 0 | AA11: =IF(D11>=Inputs!$D$10,1,0) -> 0 | AB11: =IF(AND(Z11=0,AA11=1),1,0) -> 0
A12: Congo, Dem. Rep. | B12: COD | C12: Low income | D12: 57033055 | E12: 0.35118239 | F12: 0.39214012 | G12: 0.13506865 | H12: 0.074124188 | I12: 0.16096341 | J12: 1601.7093 | K12: 44.74558 | L12: 58.532153 | M12: 19.6735 | N12: 22.5 | O12: 2.6424157 | P12: 3.2425763 | R12: 8.1168694 | S12: 7.9823962 | T12: 13.179323 | U12: 20.056672 | V12: 18.851614 | W12: 100 | X12: 0 | Y12: 0.15043772 | Z12: =IF(B12="KEN",1,0) -> 0 | AA12: =IF(D12>=Inputs!$D$10,1,0) -> 1 | AB12: =IF(AND(Z12=0,AA12=1),1,0) -> 1
A13: Congo, Rep. | B13: COG | C13: Lower middle income | D13: 3655093 | E13: 0.51592118 | F13: 0.55576039 | G13: 0.14720001 | H13: 0.099257358 | I13: 0.062384391 | J13: 6152.5651 | K13: 63.886611 | L13: 95.531932 | M13: 47.251598 | N13: 53 | P13: 2.3982908 | Q13: 3.4788751 | R13: 2.9775832 | S13: 1.8274032 | T13: 8.7040271 | U13: 18.47605 | V13: 14.286252 | W13: 20 | X13: 40 | Y13: 0.41640328 | Z13: =IF(B13="KEN",1,0) -> 0 | AA13: =IF(D13>=Inputs!$D$10,1,0) -> 1 | AB13: =IF(AND(Z13=0,AA13=1),1,0) -> 1
A14: Cote d'Ivoire | B14: CIV | C14: Lower middle income | D14: 18301587 | E14: 0.53381779 | F14: 0.57567627 | G14: 0.1682522 | H14: 0.091596039 | I14: 0.34053173 | J14: 6747.038 | K14: 53.973311 | L14: 183.87599 | M14: 41.432199 | N14: 72.9 | O14: 2.0327233 | P14: 2.436182 | Q14: 4.3512605 | R14: 2.9775832 | S14: 6.3398062 | T14: 8.8148407 | U14: 22.03366 | V14: 17.408349 | W14: 20 | X14: 100 | Y14: 0.11919423 | Z14: =IF(B14="KEN",1,0) -> 0 | AA14: =IF(D14>=Inputs!$D$10,1,0) -> 1 | AB14: =IF(AND(Z14=0,AA14=1),1,0) -> 1
A15: Eswatini | B15: SWZ | C15: Lower middle income | D15: 816208 | E15: 0.50406918 | F15: 0.65116027 | G15: 0.43135622 | H15: 0.18166877 | J15: 10386.215 | K15: 26.249846 | L15: 139.83346 | M15: 63.403099 | N15: 89.3 | O15: 0.68629089 | P15: 0.99591334 | R15: 7.145326 | S15: 2.3167574 | T15: 1.0778075 | U15: 20.380197 | W15: 20 | X15: 100 | Z15: =IF(B15="KEN",1,0) -> 0 | AA15: =IF(D15>=Inputs!$D$10,1,0) -> 0 | AB15: =IF(AND(Z15=0,AA15=1),1,0) -> 0
A16: Ethiopia | B16: ETH | C16: Low income | D16: 78031387 | E16: 0.094548896 | F16: 0.48830277 | G16: 0.48470402 | H16: 0.059108578 | I16: 0.003159289 | J16: 2892.2222 | K16: 23.622284 | L16: 65.082509 | M16: 21.941299 | N16: 56.6 | O16: 4.7667108 | P16: 2.5835041 | Q16: 28.382151 | R16: 21.196837 | S16: 6.5095935 | W16: 60 | X16: 0 | Y16: 0.3291465 | Z16: =IF(B16="KEN",1,0) -> 0 | AA16: =IF(D16>=Inputs!$D$10,1,0) -> 1 | AB16: =IF(AND(Z16=0,AA16=1),1,0) -> 1
A17: Gabon | B17: GAB | C17: Upper middle income | D17: 1573811 | E17: 0.6164155 | F17: 0.68181256 | G17: 0.24831531 | H17: 0.20072601 | I17: 0.43577988 | J17: 18923.662 | K17: 91.863209 | L17: 125.33711 | M17: 68.720901 | N17: 95.1 | P17: 2.1563651 | Q17: 3.0111278 | R17: 2.9775832 | S17: 2.9568634 | T17: 8.2891387 | U17: 14.658932 | V17: 9.5710072 | W17: 20 | X17: 100 | Y17: 0.28795048 | Z17: =IF(B17="KEN",1,0) -> 0 | AA17: =IF(D17>=Inputs!$D$10,1,0) -> 0 | AB17: =IF(AND(Z17=0,AA17=1),1,0) -> 0
A18: Gambia, The | B18: GMB | C18: Low income | D18: 1598990 | E18: 0.19088544 | F18: 0.38160904 | G18: 0.30846912 | H18: 0.031812505 | J18: 3057.6842 | K18: 64.29941 | L18: 126.24377 | M18: 49.494301 | N18: 69 | O18: 21.999043 | P18: 2.2773026 | Q18: 13.349462 | R18: 9.1077921 | S18: 5.6536849 | T18: 2.0183379 | U18: 4.3523799 | V18: 16.752749 | W18: 20 | X18: 100 | Z18: =IF(B18="KEN",1,0) -> 0 | AA18: =IF(D18>=Inputs!$D$10,1,0) -> 0 | AB18: =IF(AND(Z18=0,AA18=1),1,0) -> 0
A19: Ghana | B19: GHA | C19: Lower middle income | D19: 21563813 | E19: 0.78281364 | F19: 0.81243025 | G19: 0.38741103 | H19: 0.27266012 | I19: 0.38947782 | J19: 7072.7988 | K19: 58.365487 | L19: 113.64797 | M19: 72.175697 | N19: 91.9 | O19: 3.634852 | P19: 1.8750001 | Q19: 30.737063 | R19: 29.770975 | S19: 4.2641364 | T19: 5.3116116 | U19: 18.222546 | V19: 9.5075287 | W19: 20 | X19: 100 | Y19: 0.30338907 | Z19: =IF(B19="KEN",1,0) -> 0 | AA19: =IF(D19>=Inputs!$D$10,1,0) -> 1 | AB19: =IF(AND(Z19=0,AA19=1),1,0) -> 1
A20: Guinea | B20: GIN | C20: Low income | D20: 8464230 | E20: 0.2582194 | F20: 0.36048025 | G20: 0.16903357 | H20: 0.084053328 | I20: 0.13780469 | J20: 4016.3419 | K20: 38.071304 | L20: 97.8795 | M20: 33.304699 | N20: 53.8 | O20: 2.4648244 | P20: 2.395958 | Q20: 8.807052 | S20: 4.954727 | T20: 10.359691 | U20: 15.60558 | V20: 16.38904 | W20: 20 | X20: 100 | Y20: 0.2899367 | Z20: =IF(B20="KEN",1,0) -> 0 | AA20: =IF(D20>=Inputs!$D$10,1,0) -> 1 | AB20: =IF(AND(Z20=0,AA20=1),1,0) -> 1
A21: Kenya | B21: KEN | C21: Lower middle income | D21: 34616135 | E21: 0.87499411 | F21: 0.90119917 | G21: 0.45427844 | H21: 0.55757002 | I21: 0.72931681 | J21: 5841.5987 | K21: 31.893783 | L21: 126.47771 | M21: 34.976225 | N21: 77 | O21: 4.152768 | P21: 1.9575143 | Q21: 6.6070159 | R21: 6.8925752 | S21: 5.0800565 | T21: 8.1622887 | U21: 11.89209 | V21: 8.2310026 | W21: 20 | X21: 100 | Y21: 0.13139349 | Z21: =IF(B21="KEN",1,0) -> 1 | AA21: =IF(D21>=Inputs!$D$10,1,0) -> 1 | AB21: =IF(AND(Z21=0,AA21=1),1,0) -> 0
A22: Lesotho | B22: LSO | C22: Lower middle income | D22: 1504222 | E22: 0.53472819 | F22: 0.61571044 | G22: 0.33529203 | H22: 0.15704578 | I22: 0.27641843 | J22: 2697.6274 | K22: 43.678033 | L22: 70.328049 | M22: 51.7966 | N22: 60.6 | O22: 19.89806 | P22: 1.1164489 | Q22: 6.9064892 | R22: 7.1760114 | S22: 3.1023819 | T22: 0.15852105 | V22: 7.9491495 | W22: 20 | X22: 100 | Y22: 0.15774394 | Z22: =IF(B22="KEN",1,0) -> 0 | AA22: =IF(D22>=Inputs!$D$10,1,0) -> 0 | AB22: =IF(AND(Z22=0,AA22=1),1,0) -> 0
A23: Liberia | B23: LBR | C23: Low income | D23: 3295997 | E23: 0.47529254 | F23: 0.52213933 | G23: 0.13883256 | H23: 0.064507532 | I23: 0.20843392 | J23: 1646.0586 | K23: 55.538799 | L23: 32.063889 | M23: 32.233601 | N23: 34.9 | O23: 21.275838 | P23: 2.1572535 | Q23: 8.6341376 | R23: 4.6988152 | S23: 4.5045722 | T23: 10.907886 | U23: 17.702246 | V23: 15.954297 | W23: 20 | X23: 100 | Y23: 0.17738734 | Z23: =IF(B23="KEN",1,0) -> 0 | AA23: =IF(D23>=Inputs!$D$10,1,0) -> 1 | AB23: =IF(AND(Z23=0,AA23=1),1,0) -> 1
A24: Madagascar | B24: MDG | C24: Low income | D24: 18851036 | E24: 0.19355017 | F24: 0.2445014 | G24: 0.094532663 | H24: 0.024181526 | I24: 0.12055303 | J24: 1659.1503 | K24: 32.433989 | L24: 75.456297 | M24: 18.6779 | N24: 42.5 | O24: 2.3092333 | P24: 2.4352476 | Q24: 8.549425 | R24: 5.5617471 | S24: 4.2304128 | T24: 9.6580478 | U24: 16.938854 | V24: 13.941049 | W24: 20 | X24: 100 | Y24: 0.15820575 | Z24: =IF(B24="KEN",1,0) -> 0 | AA24: =IF(D24>=Inputs!$D$10,1,0) -> 1 | AB24: =IF(AND(Z24=0,AA24=1),1,0) -> 1
A25: Malawi | B25: MWI | C25: Low income | D25: 12384937 | E25: 0.47399198 | F25: 0.50369673 | G25: 0.12406691 | H25: 0.10435313 | I25: 0.20302832 | J25: 1634.2466 | K25: 17.268504 | L25: 69.260531 | M25: 18.961599 | N25: 15.6 | O25: 1.976764 | P25: 2.5764147 | Q25: 27.307788 | R25: 18.257951 | S25: 1.513434 | T25: 7.6321638 | U25: 21.022972 | V25: 13.035874 | W25: 60 | X25: 100 | Y25: 0.2933758 | Z25: =IF(B25="KEN",1,0) -> 0 | AA25: =IF(D25>=Inputs!$D$10,1,0) -> 1 | AB25: =IF(AND(Z25=0,AA25=1),1,0) -> 1
A26: Mali | B26: MLI | C26: Low income | D26: 12725942 | E26: 0.48387616 | F26: 0.54745481 | G26: 0.18447528 | H26: 0.10205062 | I26: 0.24397649 | J26: 2917.9325 | K26: 31.607562 | L26: 112.11985 | M26: 36.801498 | N26: 49.5 | O26: 3.994336 | P26: 2.9411508 | Q26: 4.9622257 | R26: 2.9775832 | S26: 4.4945557 | T26: 15.61277 | U26: 18.255951 | V26: 13.030751 | W26: 20 | X26: 0 | Y26: 0.17791196 | Z26: =IF(B26="KEN",1,0) -> 0 | AA26: =IF(D26>=Inputs!$D$10,1,0) -> 1 | AB26: =IF(AND(Z26=0,AA26=1),1,0) -> 1
A27: Mauritius | B27: MUS | C27: Upper middle income | D27: 1070318 | E27: 0.10127067 | F27: 0.89598448 | G27: 0.89517981 | H27: 0.49889579 | I27: 0.056269371 | J27: 27844.896 | K27: 39.016215 | L27: 172.68357 | M27: 73.307935 | N27: 100 | O27: 1.9204279 | P27: -0.2299528 | Q27: 7.1437519 | R27: 3.576774 | S27: 5.9966894 | T27: 4.5491273 | U27: 8.7544094 | V27: 0.97831316 | W27: 20 | X27: 100 | Y27: 0.26039437 | Z27: =IF(B27="KEN",1,0) -> 0 | AA27: =IF(D27>=Inputs!$D$10,1,0) -> 0 | AB27: =IF(AND(Z27=0,AA27=1),1,0) -> 0
A28: Mozambique | B28: MOZ | C28: Low income | D28: 18581790 | E28: 0.45720986 | F28: 0.54385288 | G28: 0.25084035 | H28: 0.18474351 | I28: 0.21866821 | J28: 1500.7076 | K28: 36.433234 | L28: 49.50477 | M28: 20.5273 | N28: 36.9 | O28: 1.1731363 | P28: 2.9199405 | Q28: 7.1616483 | R28: -0.80393477 | S28: 4.0073592 | T28: 17.189939 | U28: 28.504936 | V28: 28.96317 | W28: 60 | X28: 0 | Y28: 0.1542557 | Z28: =IF(B28="KEN",1,0) -> 0 | AA28: =IF(D28>=Inputs!$D$10,1,0) -> 1 | AB28: =IF(AND(Z28=0,AA28=1),1,0) -> 1
A29: Namibia | B29: NAM | C29: Upper middle income | D29: 1858089 | E29: 0.48447358 | F29: 0.72918767 | G29: 0.62697495 | H29: 0.38572264 | I29: 0.4342947 | J29: 10276.369 | K29: 50.408803 | L29: 85.164899 | M29: 64.874603 | N29: 59.3 | O29: 0.70738677 | P29: 2.2371523 | Q29: 5.400085 | R29: 7.17602 | S29: 4.5007408 | T29: 1.2125731 | U29: 21.192866 | V29: 12.141007 | W29: 20 | X29: 100 | Y29: 0.17954216 | Z29: =IF(B29="KEN",1,0) -> 0 | AA29: =IF(D29>=Inputs!$D$10,1,0) -> 0 | AB29: =IF(AND(Z29=0,AA29=1),1,0) -> 0
A30: Niger | B30: NER | C30: Low income | D30: 13873697 | E30: 0.057003706 | F30: 0.14826899 | G30: 0.12666994 | H30: 0.024256929 | I30: 0.087172383 | J30: 1795.6527 | K30: 18.04974 | L30: 60.593986 | M30: 15.5576 | N30: 21.3 | O30: 3.2964746 | P30: 3.2810148 | Q30: 5.666237 | R30: 2.9775832 | S30: 7.7266634 | W30: 20 | X30: 0 | Y30: 0.01529781 | Z30: =IF(B30="KEN",1,0) -> 0 | AA30: =IF(D30>=Inputs!$D$10,1,0) -> 1 | AB30: =IF(AND(Z30=0,AA30=1),1,0) -> 1
A31: Nigeria | B31: NGA | C31: Lower middle income | D31: 133329232 | E31: 0.32790752 | F31: 0.63261351 | G31: 0.59727706 | H31: 0.28389282 | I31: 0.056061652 | J31: 7994.0375 | K31: 62.975568 | L31: 70.761906 | M31: 41.211399 | N31: 62.5 | O31: 8.7713441 | P31: 2.0829778 | Q31: 25.582799 | R31: 43.491915 | S31: 3.9019332 | T31: 15.540632 | U31: 18.118616 | V31: 9.0920021 | W31: 20 | X31: 0 | Y31: 0.27760098 | Z31: =IF(B31="KEN",1,0) -> 0 | AA31: =IF(D31>=Inputs!$D$10,1,0) -> 1 | AB31: =IF(AND(Z31=0,AA31=1),1,0) -> 1
A32: Senegal | B32: SEN | C32: Lower middle income | D32: 11094279 | E32: 0.66912649 | F32: 0.76460926 | G32: 0.48049595 | H32: 0.36972533 | I32: 0.31798091 | J32: 4477.8174 | K32: 55.236817 | L32: 123.89445 | M32: 60.117802 | N32: 82.9 | O32: 10.643413 | P32: 2.320586 | Q32: 5.4802668 | R32: 2.9775832 | S32: 4.8566895 | T32: 8.7454474 | U32: 21.964824 | V32: 10.762933 | W32: 20 | X32: 100 | Y32: 0.31431324 | Z32: =IF(B32="KEN",1,0) -> 0 | AA32: =IF(D32>=Inputs!$D$10,1,0) -> 1 | AB32: =IF(AND(Z32=0,AA32=1),1,0) -> 1
A33: Sierra Leone | B33: SLE | C33: Low income | D33: 5200533 | E33: 0.32195726 | F33: 0.38620521 | G33: 0.15013341 | H33: 0.052292713 | I33: 0.11018614 | J33: 3098.7629 | K33: 45.362682 | L33: 107.882 | M33: 25.105 | N33: 39.2 | O33: 4.602206 | P33: 2.1226891 | Q33: 34.494971 | R33: 35.66732 | S33: 5.1056 | T33: 2.6766051 | U33: 15.98818 | V33: 17.139349 | W33: 20 | X33: 100 | Y33: 0.22223874 | Z33: =IF(B33="KEN",1,0) -> 0 | AA33: =IF(D33>=Inputs!$D$10,1,0) -> 1 | AB33: =IF(AND(Z33=0,AA33=1),1,0) -> 1
A34: South Africa | B34: ZAF | C34: Upper middle income | D34: 46723498 | E34: 0.31623202 | F34: 0.81125966 | G34: 0.78433026 | H34: 0.46924837 | I34: 0.19016846 | J34: 13597.654 | K34: 63.691798 | L34: 179.33633 | M34: 78.357597 | N34: 90.2 | O34: 0.21323329 | P34: 1.2495143 | Q34: 5.825423 | R34: 7.1760114 | S34: 1.1330282 | T34: 15.914167 | U34: 14.539017 | V34: 9.426459 | W34: 20 | X34: 100 | Y34: 0.11795106 | Z34: =IF(B34="KEN",1,0) -> 0 | AA34: =IF(D34>=Inputs!$D$10,1,0) -> 1 | AB34: =IF(AND(Z34=0,AA34=1),1,0) -> 1
A35: Tanzania | B35: TZA | C35: Lower middle income | D35: 38155970 | E35: 0.52853984 | F35: 0.59827525 | G35: 0.21944173 | H35: 0.038577458 | I35: 0.38538031 | J35: 3713.2629 | K35: 36.168446 | L35: 126.55916 | M35: 31.1621 | N35: 52.4 | O35: 1.4176182 | P35: 2.8742667 | Q35: 3.7354839 | R35: 4.0922337 | S35: 5.0539477 | T35: 6.3849677 | U35: 15.232837 | V35: 20.663409 | W35: 100 | X35: 100 | Y35: 0.082005026 | Z35: =IF(B35="KEN",1,0) -> 0 | AA35: =IF(D35>=Inputs!$D$10,1,0) -> 1 | AB35: =IF(AND(Z35=0,AA35=1),1,0) -> 1
A36: Togo | B36: TGO | C36: Low income | D36: 5593530 | E36: 0.47991838 | F36: 0.57432953 | G36: 0.32442027 | H36: 0.13771111 | I36: 0.21457376 | J36: 3351.2499 | K36: 43.814849 | L36: 80.803555 | M36: 39.4832 | N36: 61.1 | P36: 2.1973646 | Q36: 5.4398267 | R36: 2.9775832 | S36: 6.3395268 | T36: 26.293977 | U36: 24.039604 | V36: 4.9774876 | W36: 20 | X36: 100 | Y36: 0.38484391 | Z36: =IF(B36="KEN",1,0) -> 0 | AA36: =IF(D36>=Inputs!$D$10,1,0) -> 1 | AB36: =IF(AND(Z36=0,AA36=1),1,0) -> 1
A37: Uganda | B37: UGA | C37: Low income | D37: 27277834 | E37: 0.67738295 | F37: 0.72827376 | G37: 0.26173324 | H37: 0.11671008 | I37: 0.50581243 | J37: 2879.6701 | K37: 31.27777 | L37: 83.165031 | M37: 8.9498311 | N37: 55.3 | O37: 2.6514081 | P37: 2.7537317 | Q37: 5.2900391 | R37: 1.5453343 | S37: 5.3268585 | T37: 12.903442 | U37: 12.607208 | V37: 16.129261 | W37: 100 | X37: 100 | Y37: 0.12137563 | Z37: =IF(B37="KEN",1,0) -> 0 | AA37: =IF(D37>=Inputs!$D$10,1,0) -> 1 | AB37: =IF(AND(Z37=0,AA37=1),1,0) -> 1
A38: Zambia | B38: ZMB | C38: Low income | D38: 12029200 | E38: 0.69310751 | F38: 0.72702425 | G38: 0.24072373 | H38: 0.19196639 | I38: 0.27842392 | J38: 3708.069 | K38: 45.470384 | L38: 108.70478 | M38: 17.101 | N38: 53.6 | O38: 1.3212312 | P38: 2.8118226 | Q38: 12.287787 | R38: 8.9273555 | S38: 4.7997382 | T38: 7.5237869 | U38: 25.333009 | V38: 5.7597968 | W38: 60 | X38: 100 | Y38: 0.26224857 | Z38: =IF(B38="KEN",1,0) -> 0 | AA38: =IF(D38>=Inputs!$D$10,1,0) -> 1 | AB38: =IF(AND(Z38=0,AA38=1),1,0) -> 1
A39: Zimbabwe | B39: ZWE | C39: Lower middle income | D39: 9588258 | E39: 0.43331737 | F39: 0.49521602 | G39: 0.21566153 | H39: 0.29098485 | I39: 0.48581632 | J39: 5211.8976 | K39: 39.893372 | L39: 94.245175 | M39: 41.642799 | N39: 62 | O39: 8.4531023 | P39: 1.7804823 | Q39: 104.70517 | R39: 120.26093 | S39: 4.3888755 | T39: 7.1863431 | U39: 15.214052 | V39: 14.891015 | W39: 20 | X39: 40 | Y39: 0.090852221 | Z39: =IF(B39="KEN",1,0) -> 0 | AA39: =IF(D39>=Inputs!$D$10,1,0) -> 1 | AB39: =IF(AND(Z39=0,AA39=1),1,0) -> 1

Sheet Forecast
A1: Adoption forecast to 2030
A2: Logistic diffusion: logit(adoption) rises by a common yearly growth rate (Inputs), scaled by the scenario multiplier, capped at the ceiling.
A5: Country | B5: ISO3 | C5: Candidate | D5: Mobile money 2024 | E5: logit(adoption 2024) | F5: Growth of logit per year | G5: Adults 2030 | H5: Users at 2024 penetration, 2030 | I5: Adoption 2030 Low | J5: Adoption 2030 Base | K5: Adoption 2030 High | L5: Users 2030 Low | M5: Users 2030 Base | N5: Users 2030 High | O5: New users vs 2024 penetration, Low | P5: New users Base | Q5: New users High
A6: =Data!A6 -> Benin | B6: =Data!B6 -> BEN | C6: =Data!AB6 -> 1 | D6: =Data!E6 -> 0.44872852 | E6: =LN(MIN(0.995,MAX(0.005,D6))/(1-MIN(0.995,MAX(0.005,D6)))) -> -0.20580932 | F6: =MIN(Inputs!$D$14,MAX(Inputs!$D$13,(1-Inputs!$D$12)*Inputs!$D$11+Inputs!$D$12*IF(Data!Y6="",Inputs!$D$11,Data!Y6))) -> 0.17872706 | G6: =Data!D6*(1+Data!P6/100)^Inputs!$D$8 -> 9496898.8 | H6: =G6*D6 -> 4261529.3 | I6: =MIN(1/(1+EXP(-(E6+F6*Inputs!$C$16*Inputs!$D$8))),MAX(Inputs!$D$9,D6)) -> 0.58184985 | J6: =MIN(1/(1+EXP(-(E6+F6*Inputs!$D$16*Inputs!$D$8))),MAX(Inputs!$D$9,D6)) -> 0.70402795 | K6: =MIN(1/(1+EXP(-(E6+F6*Inputs!$E$16*Inputs!$D$8))),MAX(Inputs!$D$9,D6)) -> 0.80261741 | L6: =G6*I6 -> 5525769.2 | M6: =G6*J6 -> 6686082.2 | N6: =G6*K6 -> 7622376.3 | O6: =MAX(0,L6-H6) -> 1264239.8 | P6: =MAX(0,M6-H6) -> 2424552.9 | Q6: =MAX(0,N6-H6) -> 3360847
A7: =Data!A7 -> Botswana | B7: =Data!B7 -> BWA | C7: =Data!AB7 -> 0 | D7: =Data!E7 -> 0.51617816 | E7: =LN(MIN(0.995,MAX(0.005,D7))/(1-MIN(0.995,MAX(0.005,D7)))) -> 0.064735226 | F7: =MIN(Inputs!$D$14,MAX(Inputs!$D$13,(1-Inputs!$D$12)*Inputs!$D$11+Inputs!$D$12*IF(Data!Y7="",Inputs!$D$11,Data!Y7))) -> 0.17872706 | G7: =Data!D7*(1+Data!P7/100)^Inputs!$D$8 -> 1851283.3 | H7: =G7*D7 -> 955591.99 | I7: =MIN(1/(1+EXP(-(E7+F7*Inputs!$C$16*Inputs!$D$8))),MAX(Inputs!$D$9,D7)) -> 0.64586594 | J7: =MIN(1/(1+EXP(-(E7+F7*Inputs!$D$16*Inputs!$D$8))),MAX(Inputs!$D$9,D7)) -> 0.75714636 | K7: =MIN(1/(1+EXP(-(E7+F7*Inputs!$E$16*Inputs!$D$8))),MAX(Inputs!$D$9,D7)) -> 0.84201248 | L7: =G7*I7 -> 1195680.8 | M7: =G7*J7 -> 1401692.4 | N7: =G7*K7 -> 1558803.6 | O7: =MAX(0,L7-H7) -> 240088.82 | P7: =MAX(0,M7-H7) -> 446100.39 | Q7: =MAX(0,N7-H7) -> 603211.63
A8: =Data!A8 -> Burkina Faso | B8: =Data!B8 -> BFA | C8: =Data!AB8 -> 1 | D8: =Data!E8 -> 0.44157364 | E8: =LN(MIN(0.995,MAX(0.005,D8))/(1-MIN(0.995,MAX(0.005,D8)))) -> -0.23477795 | F8: =MIN(Inputs!$D$14,MAX(Inputs!$D$13,(1-Inputs!$D$12)*Inputs!$D$11+Inputs!$D$12*IF(Data!Y8="",Inputs!$D$11,Data!Y8))) -> 0.17872706 | G8: =Data!D8*(1+Data!P8/100)^Inputs!$D$8 -> 15153214 | H8: =G8*D8 -> 6691259.7 | I8: =MIN(1/(1+EXP(-(E8+F8*Inputs!$C$16*Inputs!$D$8))),MAX(Inputs!$D$9,D8)) -> 0.57478551 | J8: =MIN(1/(1+EXP(-(E8+F8*Inputs!$D$16*Inputs!$D$8))),MAX(Inputs!$D$9,D8)) -> 0.69795622 | K8: =MIN(1/(1+EXP(-(E8+F8*Inputs!$E$16*Inputs!$D$8))),MAX(Inputs!$D$9,D8)) -> 0.79798786 | L8: =G8*I8 -> 8709847.6 | M8: =G8*J8 -> 10576280 | N8: =G8*K8 -> 12092080 | O8: =MAX(0,L8-H8) -> 2018587.9 | P8: =MAX(0,M8-H8) -> 3885020 | Q8: =MAX(0,N8-H8) -> 5400820.8
A9: =Data!A9 -> Cameroon | B9: =Data!B9 -> CMR | C9: =Data!AB9 -> 1 | D9: =Data!E9 -> 0.55065452 | E9: =LN(MIN(0.995,MAX(0.005,D9))/(1-MIN(0.995,MAX(0.005,D9)))) -> 0.20331557 | F9: =MIN(Inputs!$D$14,MAX(Inputs!$D$13,(1-Inputs!$D$12)*Inputs!$D$11+Inputs!$D$12*IF(Data!Y9="",Inputs!$D$11,Data!Y9))) -> 0.17872706 | G9: =Data!D9*(1+Data!P9/100)^Inputs!$D$8 -> 19289633 | H9: =G9*D9 -> 10621924 | I9: =MIN(1/(1+EXP(-(E9+F9*Inputs!$C$16*Inputs!$D$8))),MAX(Inputs!$D$9,D9)) -> 0.6768858 | J9: =MIN(1/(1+EXP(-(E9+F9*Inputs!$D$16*Inputs!$D$8))),MAX(Inputs!$D$9,D9)) -> 0.78171317 | K9: =MIN(1/(1+EXP(-(E9+F9*Inputs!$E$16*Inputs!$D$8))),MAX(Inputs!$D$9,D9)) -> 0.85958642 | L9: =G9*I9 -> 13056879 | M9: =G9*J9 -> 15078960 | N9: =G9*K9 -> 16581107 | O9: =MAX(0,L9-H9) -> 2434955.1 | P9: =MAX(0,M9-H9) -> 4457036.6 | Q9: =MAX(0,N9-H9) -> 5959182.9
A10: =Data!A10 -> Chad | B10: =Data!B10 -> TCD | C10: =Data!AB10 -> 1 | D10: =Data!E10 -> 0.13335894 | E10: =LN(MIN(0.995,MAX(0.005,D10))/(1-MIN(0.995,MAX(0.005,D10)))) -> -1.8715806 | F10: =MIN(Inputs!$D$14,MAX(Inputs!$D$13,(1-Inputs!$D$12)*Inputs!$D$11+Inputs!$D$12*IF(Data!Y10="",Inputs!$D$11,Data!Y10))) -> 0.17872706 | G10: =Data!D10*(1+Data!P10/100)^Inputs!$D$8 -> 13748917 | H10: =G10*D10 -> 1833541 | I10: =MIN(1/(1+EXP(-(E10+F10*Inputs!$C$16*Inputs!$D$8))),MAX(Inputs!$D$9,D10)) -> 0.20826765 | J10: =MIN(1/(1+EXP(-(E10+F10*Inputs!$D$16*Inputs!$D$8))),MAX(Inputs!$D$9,D10)) -> 0.31019278 | K10: =MIN(1/(1+EXP(-(E10+F10*Inputs!$E$16*Inputs!$D$8))),MAX(Inputs!$D$9,D10)) -> 0.43461729 | L10: =G10*I10 -> 2863454.5 | M10: =G10*J10 -> 4264814.6 | N10: =G10*K10 -> 5975516.9 | O10: =MAX(0,L10-H10) -> 1029913.5 | P10: =MAX(0,M10-H10) -> 2431273.6 | Q10: =MAX(0,N10-H10) -> 4141975.9
A11: =Data!A11 -> Comoros | B11: =Data!B11 -> COM | C11: =Data!AB11 -> 0 | D11: =Data!E11 -> 0.14093786 | E11: =LN(MIN(0.995,MAX(0.005,D11))/(1-MIN(0.995,MAX(0.005,D11)))) -> -1.8075221 | F11: =MIN(Inputs!$D$14,MAX(Inputs!$D$13,(1-Inputs!$D$12)*Inputs!$D$11+Inputs!$D$12*IF(Data!Y11="",Inputs!$D$11,Data!Y11))) -> 0.17872706 | G11: =Data!D11*(1+Data!P11/100)^Inputs!$D$8 -> 595686.66 | H11: =G11*D11 -> 83954.806 | I11: =MIN(1/(1+EXP(-(E11+F11*Inputs!$C$16*Inputs!$D$8))),MAX(Inputs!$D$9,D11)) -> 0.21902779 | J11: =MIN(1/(1+EXP(-(E11+F11*Inputs!$D$16*Inputs!$D$8))),MAX(Inputs!$D$9,D11)) -> 0.32406347 | K11: =MIN(1/(1+EXP(-(E11+F11*Inputs!$E$16*Inputs!$D$8))),MAX(Inputs!$D$9,D11)) -> 0.45041883 | L11: =G11*I11 -> 130471.93 | M11: =G11*J11 -> 193040.29 | N11: =G11*K11 -> 268308.49 | O11: =MAX(0,L11-H11) -> 46517.127 | P11: =MAX(0,M11-H11) -> 109085.48 | Q11: =MAX(0,N11-H11) -> 184353.69
A12: =Data!A12 -> Congo, Dem. Rep. | B12: =Data!B12 -> COD | C12: =Data!AB12 -> 1 | D12: =Data!E12 -> 0.35118239 | E12: =LN(MIN(0.995,MAX(0.005,D12))/(1-MIN(0.995,MAX(0.005,D12)))) -> -0.61384594 | F12: =MIN(Inputs!$D$14,MAX(Inputs!$D$13,(1-Inputs!$D$12)*Inputs!$D$11+Inputs!$D$12*IF(Data!Y12="",Inputs!$D$11,Data!Y12))) -> 0.17872706 | G12: =Data!D12*(1+Data!P12/100)^Inputs!$D$8 -> 69068438 | H12: =G12*D12 -> 24255619 | I12: =MIN(1/(1+EXP(-(E12+F12*Inputs!$C$16*Inputs!$D$8))),MAX(Inputs!$D$9,D12)) -> 0.48059357 | J12: =MIN(1/(1+EXP(-(E12+F12*Inputs!$D$16*Inputs!$D$8))),MAX(Inputs!$D$9,D12)) -> 0.61266217 | K12: =MIN(1/(1+EXP(-(E12+F12*Inputs!$E$16*Inputs!$D$8))),MAX(Inputs!$D$9,D12)) -> 0.73001479 | L12: =G12*I12 -> 33193847 | M12: =G12*J12 -> 42315619 | N12: =G12*K12 -> 50420981 | O12: =MAX(0,L12-H12) -> 8938227.9 | P12: =MAX(0,M12-H12) -> 18060000 | Q12: =MAX(0,N12-H12) -> 26165362
A13: =Data!A13 -> Congo, Rep. | B13: =Data!B13 -> COG | C13: =Data!AB13 -> 1 | D13: =Data!E13 -> 0.51592118 | E13: =LN(MIN(0.995,MAX(0.005,D13))/(1-MIN(0.995,MAX(0.005,D13)))) -> 0.063706246 | F13: =MIN(Inputs!$D$14,MAX(Inputs!$D$13,(1-Inputs!$D$12)*Inputs!$D$11+Inputs!$D$12*IF(Data!Y13="",Inputs!$D$11,Data!Y13))) -> 0.17872706 | G13: =Data!D13*(1+Data!P13/100)^Inputs!$D$8 -> 4213613.3 | H13: =G13*D13 -> 2173892.3 | I13: =MIN(1/(1+EXP(-(E13+F13*Inputs!$C$16*Inputs!$D$8))),MAX(Inputs!$D$9,D13)) -> 0.64563055 | J13: =MIN(1/(1+EXP(-(E13+F13*Inputs!$D$16*Inputs!$D$8))),MAX(Inputs!$D$9,D13)) -> 0.7569571 | K13: =MIN(1/(1+EXP(-(E13+F13*Inputs!$E$16*Inputs!$D$8))),MAX(Inputs!$D$9,D13)) -> 0.84187555 | L13: =G13*I13 -> 2720437.5 | M13: =G13*J13 -> 3189524.5 | N13: =G13*K13 -> 3547338 | O13: =MAX(0,L13-H13) -> 546545.15 | P13: =MAX(0,M13-H13) -> 1015632.2 | Q13: =MAX(0,N13-H13) -> 1373445.7
A14: =Data!A14 -> Cote d'Ivoire | B14: =Data!B14 -> CIV | C14: =Data!AB14 -> 1 | D14: =Data!E14 -> 0.53381779 | E14: =LN(MIN(0.995,MAX(0.005,D14))/(1-MIN(0.995,MAX(0.005,D14)))) -> 0.13547799 | F14: =MIN(Inputs!$D$14,MAX(Inputs!$D$13,(1-Inputs!$D$12)*Inputs!$D$11+Inputs!$D$12*IF(Data!Y14="",Inputs!$D$11,Data!Y14))) -> 0.17872706 | G14: =Data!D14*(1+Data!P14/100)^Inputs!$D$8 -> 21145066 | H14: =G14*D14 -> 11287612 | I14: =MIN(1/(1+EXP(-(E14+F14*Inputs!$C$16*Inputs!$D$8))),MAX(Inputs!$D$9,D14)) -> 0.66187458 | J14: =MIN(1/(1+EXP(-(E14+F14*Inputs!$D$16*Inputs!$D$8))),MAX(Inputs!$D$9,D14)) -> 0.7699166 | K14: =MIN(1/(1+EXP(-(E14+F14*Inputs!$E$16*Inputs!$D$8))),MAX(Inputs!$D$9,D14)) -> 0.85119716 | L14: =G14*I14 -> 13995382 | M14: =G14*J14 -> 16279938 | N14: =G14*K14 -> 17998620 | O14: =MAX(0,L14-H14) -> 2707769.3 | P14: =MAX(0,M14-H14) -> 4992325.1 | Q14: =MAX(0,N14-H14) -> 6711007.8
A15: =Data!A15 -> Eswatini | B15: =Data!B15 -> SWZ | C15: =Data!AB15 -> 0 | D15: =Data!E15 -> 0.50406918 | E15: =LN(MIN(0.995,MAX(0.005,D15))/(1-MIN(0.995,MAX(0.005,D15)))) -> 0.016277062 | F15: =MIN(Inputs!$D$14,MAX(Inputs!$D$13,(1-Inputs!$D$12)*Inputs!$D$11+Inputs!$D$12*IF(Data!Y15="",Inputs!$D$11,Data!Y15))) -> 0.17872706 | G15: =Data!D15*(1+Data!P15/100)^Inputs!$D$8 -> 866210.92 | H15: =G15*D15 -> 436630.22 | I15: =MIN(1/(1+EXP(-(E15+F15*Inputs!$C$16*Inputs!$D$8))),MAX(Inputs!$D$9,D15)) -> 0.63470573 | J15: =MIN(1/(1+EXP(-(E15+F15*Inputs!$D$16*Inputs!$D$8))),MAX(Inputs!$D$9,D15)) -> 0.74812543 | K15: =MIN(1/(1+EXP(-(E15+F15*Inputs!$E$16*Inputs!$D$8))),MAX(Inputs!$D$9,D15)) -> 0.83545888 | L15: =G15*I15 -> 549789.04 | M15: =G15*J15 -> 648034.42 | N15: =G15*K15 -> 723683.6 | O15: =MAX(0,L15-H15) -> 113158.81 | P15: =MAX(0,M15-H15) -> 211404.19 | Q15: =MAX(0,N15-H15) -> 287053.38
A16: =Data!A16 -> Ethiopia | B16: =Data!B16 -> ETH | C16: =Data!AB16 -> 1 | D16: =Data!E16 -> 0.094548896 | E16: =LN(MIN(0.995,MAX(0.005,D16))/(1-MIN(0.995,MAX(0.005,D16)))) -> -2.2593162 | F16: =MIN(Inputs!$D$14,MAX(Inputs!$D$13,(1-Inputs!$D$12)*Inputs!$D$11+Inputs!$D$12*IF(Data!Y16="",Inputs!$D$11,Data!Y16))) -> 0.17872706 | G16: =Data!D16*(1+Data!P16/100)^Inputs!$D$8 -> 90935719 | H16: =G16*D16 -> 8597871.9 | I16: =MIN(1/(1+EXP(-(E16+F16*Inputs!$C$16*Inputs!$D$8))),MAX(Inputs!$D$9,D16)) -> 0.1514678 | J16: =MIN(1/(1+EXP(-(E16+F16*Inputs!$D$16*Inputs!$D$8))),MAX(Inputs!$D$9,D16)) -> 0.23380419 | K16: =MIN(1/(1+EXP(-(E16+F16*Inputs!$E$16*Inputs!$D$8))),MAX(Inputs!$D$9,D16)) -> 0.34281545 | L16: =G16*I16 -> 13773833 | M16: =G16*J16 -> 21261152 | N16: =G16*K16 -> 31174170 | O16: =MAX(0,L16-H16) -> 5175961.5 | P16: =MAX(0,M16-H16) -> 12663280 | Q16: =MAX(0,N16-H16) -> 22576298
A17: =Data!A17 -> Gabon | B17: =Data!B17 -> GAB | C17: =Data!AB17 -> 0 | D17: =Data!E17 -> 0.6164155 | E17: =LN(MIN(0.995,MAX(0.005,D17))/(1-MIN(0.995,MAX(0.005,D17)))) -> 0.47436132 | F17: =MIN(Inputs!$D$14,MAX(Inputs!$D$13,(1-Inputs!$D$12)*Inputs!$D$11+Inputs!$D$12*IF(Data!Y17="",Inputs!$D$11,Data!Y17))) -> 0.17872706 | G17: =Data!D17*(1+Data!P17/100)^Inputs!$D$8 -> 1788731.5 | H17: =G17*D17 -> 1102601.9 | I17: =MIN(1/(1+EXP(-(E17+F17*Inputs!$C$16*Inputs!$D$8))),MAX(Inputs!$D$9,D17)) -> 0.7331263 | J17: =MIN(1/(1+EXP(-(E17+F17*Inputs!$D$16*Inputs!$D$8))),MAX(Inputs!$D$9,D17)) -> 0.82444003 | K17: =MIN(1/(1+EXP(-(E17+F17*Inputs!$E$16*Inputs!$D$8))),MAX(Inputs!$D$9,D17)) -> 0.88923049 | L17: =G17*I17 -> 1311366.1 | M17: =G17*J17 -> 1474701.9 | N17: =G17*K17 -> 1590594.6 | O17: =MAX(0,L17-H17) -> 208764.3 | P17: =MAX(0,M17-H17) -> 372100.03 | Q17: =MAX(0,N17-H17) -> 487992.77
... A39: =Data!A39 -> Zimbabwe | B39: =Data!B39 -> ZWE | C39: =Data!AB39 -> 1 | D39: =Data!E39 -> 0.43331737 | E39: =LN(MIN(0.995,MAX(0.005,D39))/(1-MIN(0.995,MAX(0.005,D39)))) -> -0.268329 | F39: =MIN(Inputs!$D$14,MAX(Inputs!$D$13,(1-Inputs!$D$12)*Inputs!$D$11+Inputs!$D$12*IF(Data!Y39="",Inputs!$D$11,Data!Y39))) -> 0.17872706 | G39: =Data!D39*(1+Data!P39/100)^Inputs!$D$8 -> 10659252 | H39: =G39*D39 -> 4618839.1 | I39: =MIN(1/(1+EXP(-(E39+F39*Inputs!$C$16*Inputs!$D$8))),MAX(Inputs!$D$9,D39)) -> 0.56656554 | J39: =MIN(1/(1+EXP(-(E39+F39*Inputs!$D$16*Inputs!$D$8))),MAX(Inputs!$D$9,D39)) -> 0.6908366 | K39: =MIN(1/(1+EXP(-(E39+F39*Inputs!$E$16*Inputs!$D$8))),MAX(Inputs!$D$9,D39)) -> 0.79252522 | L39: =G39*I39 -> 6039165 | M39: =G39*J39 -> 7363801.5 | N39: =G39*K39 -> 8447726.2 | O39: =MAX(0,L39-H39) -> 1420325.9 | P39: =MAX(0,M39-H39) -> 2744962.4 | Q39: =MAX(0,N39-H39) -> 3828887.1

Sheet Pools
A1: Revenue pools and the winnable share, 2030 ($m)
A2: Pool = users x revenue per user. Winnable = the operator's share of existing users plus its share of new users.
A5: Country | B5: ISO3 | C5: Candidate | D5: Income factor | E5: Mobile-led share | F5: Structure factor | G5: Cost scale factor | H5: Revenue per user Low ($) | I5: Revenue per user Base ($) | J5: Revenue per user High ($) | K5: Pool 2030 Low ($m) | L5: Pool 2030 Base ($m) | M5: Pool 2030 High ($m) | N5: Winnable users Low | O5: Winnable users Base | P5: Winnable users High | Q5: Winnable revenue Low ($m) | R5: Winnable revenue Base ($m) | S5: Winnable revenue High ($m) | T5: Pool 2024 at Base revenue per user ($m) | U5: Pool growth per year 2024-30 | V5: Contribution cover of fixed cost (Base)
A6: =Data!A6 -> Benin | B6: =Data!B6 -> BEN | C6: =Data!AB6 -> 1 | D6: =MIN(Inputs!$D$24,MAX(Inputs!$D$23,(Data!J6/Inputs!$D$65)^Inputs!$D$22)) -> 0.86823678 | E6: =MIN(1,Data!E6/Data!F6) -> 0.86554932 | F6: =MIN(Inputs!$D$27,MAX(Inputs!$D$26,(E6/Inputs!$D$66)^Inputs!$D$25)) -> 0.89147152 | G6: =MIN(Inputs!$D$37,MAX(Inputs!$D$36,(Data!D6/Inputs!$D$34)^Inputs!$D$35)) -> 0.70028116 | H6: =Inputs!$C$17*D6*F6 -> 11.610125 | I6: =Inputs!$D$17*D6*F6 -> 19.350209 | J6: =Inputs!$E$17*D6*F6 -> 24.768268 | K6: =Forecast!L6*H6/1000000 -> 64.154874 | L6: =Forecast!M6*I6/1000000 -> 129.37709 | M6: =Forecast!N6*J6/1000000 -> 188.79306 | N6: =Inputs!$C$19*Forecast!H6+Inputs!$C$18*Forecast!O6 -> 165062.13 | O6: =Inputs!$D$19*Forecast!H6+Inputs!$D$18*Forecast!P6 -> 491528.81 | P6: =Inputs!$E$19*Forecast!H6+Inputs!$E$18*Forecast!Q6 -> 952462.8 | Q6: =N6*H6/1000000 -> 1.916392 | R6: =O6*I6/1000000 -> 9.5111853 | S6: =P6*J6/1000000 -> 23.590854 | T6: =Data!D6*Data!E6*I6/1000000 -> 71.265681 | U6: =(L6/T6)^(1/Inputs!$D$8)-1 -> 0.10449263 | V6: =R6*Inputs!$D$29/(Inputs!$D$30*G6) -> 0.56591468
A7: =Data!A7 -> Botswana | B7: =Data!B7 -> BWA | C7: =Data!AB7 -> 0 | D7: =MIN(Inputs!$D$24,MAX(Inputs!$D$23,(Data!J7/Inputs!$D$65)^Inputs!$D$22)) -> 1.3 | E7: =MIN(1,Data!E7/Data!F7) -> 0.84015465 | F7: =MIN(Inputs!$D$27,MAX(Inputs!$D$26,(E7/Inputs!$D$66)^Inputs!$D$25)) -> 0.86531631 | G7: =MIN(Inputs!$D$37,MAX(Inputs!$D$36,(Data!D7/Inputs!$D$34)^Inputs!$D$35)) -> 0.6 | H7: =Inputs!$C$17*D7*F7 -> 16.873668 | I7: =Inputs!$D$17*D7*F7 -> 28.12278 | J7: =Inputs!$E$17*D7*F7 -> 35.997159 | K7: =Forecast!L7*H7/1000000 -> 20.175521 | L7: =Forecast!M7*I7/1000000 -> 39.419487 | M7: =Forecast!N7*J7/1000000 -> 56.112501 | N7: =Inputs!$C$19*Forecast!H7+Inputs!$C$18*Forecast!O7 -> 33540.985 | O7: =Inputs!$D$19*Forecast!H7+Inputs!$D$18*Forecast!P7 -> 95582.819 | P7: =Inputs!$E$19*Forecast!H7+Inputs!$E$18*Forecast!Q7 -> 180486.16 | Q7: =N7*H7/1000000 -> 0.56595946 | R7: =O7*I7/1000000 -> 2.6880546 | S7: =P7*J7/1000000 -> 6.4969889 | T7: =Data!D7*Data!E7*I7/1000000 -> 24.381541 | U7: =(L7/T7)^(1/Inputs!$D$8)-1 -> 0.083365418 | V7: =R7*Inputs!$D$29/(Inputs!$D$30*G7) -> 0.18667046
A8: =Data!A8 -> Burkina Faso | B8: =Data!B8 -> BFA | C8: =Data!AB8 -> 1 | D8: =MIN(Inputs!$D$24,MAX(Inputs!$D$23,(Data!J8/Inputs!$D$65)^Inputs!$D$22)) -> 0.74802079 | E8: =MIN(1,Data!E8/Data!F8) -> 0.85863345 | F8: =MIN(Inputs!$D$27,MAX(Inputs!$D$26,(E8/Inputs!$D$66)^Inputs!$D$25)) -> 0.88434853 | G8: =MIN(Inputs!$D$37,MAX(Inputs!$D$36,(Data!D8/Inputs!$D$34)^Inputs!$D$35)) -> 0.8484748 | H8: =Inputs!$C$17*D8*F8 -> 9.9226663 | I8: =Inputs!$D$17*D8*F8 -> 16.537777 | J8: =Inputs!$E$17*D8*F8 -> 21.168355 | K8: =Forecast!L8*H8/1000000 -> 86.424912 | L8: =Forecast!M8*I8/1000000 -> 174.90816 | M8: =Forecast!N8*J8/1000000 -> 255.96945 | N8: =Inputs!$C$19*Forecast!H8+Inputs!$C$18*Forecast!O8 -> 261855.93 | O8: =Inputs!$D$19*Forecast!H8+Inputs!$D$18*Forecast!P8 -> 783490.79 | P8: =Inputs!$E$19*Forecast!H8+Inputs!$E$18*Forecast!Q8 -> 1522743.6 | Q8: =N8*H8/1000000 -> 2.598309 | R8: =O8*I8/1000000 -> 12.957196 | S8: =P8*J8/1000000 -> 32.233976 | T8: =Data!D8*Data!E8*I8/1000000 -> 96.851787 | U8: =(L8/T8)^(1/Inputs!$D$8)-1 -> 0.10352897 | V8: =R8*Inputs!$D$29/(Inputs!$D$30*G8) -> 0.63629842
A9: =Data!A9 -> Cameroon | B9: =Data!B9 -> CMR | C9: =Data!AB9 -> 1 | D9: =MIN(Inputs!$D$24,MAX(Inputs!$D$23,(Data!J9/Inputs!$D$65)^Inputs!$D$22)) -> 0.94147094 | E9: =MIN(1,Data!E9/Data!F9) -> 0.90458391 | F9: =MIN(Inputs!$D$27,MAX(Inputs!$D$26,(E9/Inputs!$D$66)^Inputs!$D$25)) -> 0.93167515 | G9: =MIN(Inputs!$D$37,MAX(Inputs!$D$36,(Data!D9/Inputs!$D$34)^Inputs!$D$35)) -> 0.92647795 | H9: =Inputs!$C$17*D9*F9 -> 13.157176 | I9: =Inputs!$D$17*D9*F9 -> 21.928627 | J9: =Inputs!$E$17*D9*F9 -> 28.068643 | K9: =Forecast!L9*H9/1000000 -> 171.79165 | L9: =Forecast!M9*I9/1000000 -> 330.66089 | M9: =Forecast!N9*J9/1000000 -> 465.40915 | N9: =Inputs!$C$19*Forecast!H9+Inputs!$C$18*Forecast!O9 -> 354125.26 | O9: =Inputs!$D$19*Forecast!H9+Inputs!$D$18*Forecast!P9 -> 987213.19 | P9: =Inputs!$E$19*Forecast!H9+Inputs!$E$18*Forecast!Q9 -> 1842116.4 | Q9: =N9*H9/1000000 -> 4.6592885 | R9: =O9*I9/1000000 -> 21.64823 | S9: =P9*J9/1000000 -> 51.705708 | T9: =Data!D9*Data!E9*I9/1000000 -> 199.53007 | U9: =(L9/T9)^(1/Inputs!$D$8)-1 -> 0.08783346 | V9: =R9*Inputs!$D$29/(Inputs!$D$30*G9) -> 0.97358991
A10: =Data!A10 -> Chad | B10: =Data!B10 -> TCD | C10: =Data!AB10 -> 1 | D10: =MIN(Inputs!$D$24,MAX(Inputs!$D$23,(Data!J10/Inputs!$D$65)^Inputs!$D$22)) -> 0.73573588 | E10: =MIN(1,Data!E10/Data!F10) -> 0.63813115 | F10: =MIN(Inputs!$D$27,MAX(Inputs!$D$26,(E10/Inputs!$D$66)^Inputs!$D$25)) -> 0.65724244 | G10: =MIN(Inputs!$D$37,MAX(Inputs!$D$36,(Data!D10/Inputs!$D$34)^Inputs!$D$35)) -> 0.76657054 | H10: =Inputs!$C$17*D10*F10 -> 7.2533527 | I10: =Inputs!$D$17*D10*F10 -> 12.088921 | J10: =Inputs!$E$17*D10*F10 -> 15.473819 | K10: =Forecast!L10*H10/1000000 -> 20.769645 | L10: =Forecast!M10*I10/1000000 -> 51.557008 | M10: =Forecast!N10*J10/1000000 -> 92.464067 | N10: =Inputs!$C$19*Forecast!H10+Inputs!$C$18*Forecast!O10 -> 109896.2 | O10: =Inputs!$D$19*Forecast!H10+Inputs!$D$18*Forecast!P10 -> 419697.28 | P10: =Inputs!$E$19*Forecast!H10+Inputs!$E$18*Forecast!Q10 -> 1002911.7 | Q10: =N10*H10/1000000 -> 0.79711587 | R10: =O10*I10/1000000 -> 5.0736873 | S10: =P10*J10/1000000 -> 15.518875 | T10: =Data!D10*Data!E10*I10/1000000 -> 16.588992 | U10: =(L10/T10)^(1/Inputs!$D$8)-1 -> 0.20803064 | V10: =R10*Inputs!$D$29/(Inputs!$D$30*G10) -> 0.27577845
A11: =Data!A11 -> Comoros | B11: =Data!B11 -> COM | C11: =Data!AB11 -> 0 | D11: =MIN(Inputs!$D$24,MAX(Inputs!$D$23,(Data!J11/Inputs!$D$65)^Inputs!$D$22)) -> 0.84052794 | E11: =MIN(1,Data!E11/Data!F11) -> 0.31003021 | F11: =MIN(Inputs!$D$27,MAX(Inputs!$D$26,(E11/Inputs!$D$66)^Inputs!$D$25)) -> 0.31931525 | G11: =MIN(Inputs!$D$37,MAX(Inputs!$D$36,(Data!D11/Inputs!$D$34)^Inputs!$D$35)) -> 0.6 | H11: =Inputs!$C$17*D11*F11 -> 4.0259009 | I11: =Inputs!$D$17*D11*F11 -> 6.7098348 | J11: =Inputs!$E$17*D11*F11 -> 8.5885885 | K11: =Forecast!L11*H11/1000000 -> 0.52526707 | L11: =Forecast!M11*I11/1000000 -> 1.2952684 | M11: =Forecast!N11*J11/1000000 -> 2.3043912 | N11: =Inputs!$C$19*Forecast!H11+Inputs!$C$18*Forecast!O11 -> 4980.6922 | O11: =Inputs!$D$19*Forecast!H11+Inputs!$D$18*Forecast!P11 -> 18881.467 | P11: =Inputs!$E$19*Forecast!H11+Inputs!$E$18*Forecast!Q11 -> 44755.551 | Q11: =N11*H11/1000000 -> 0.020051773 | R11: =O11*I11/1000000 -> 0.12669152 | S11: =P11*J11/1000000 -> 0.38438701 | T11: =Data!D11*Data!E11*I11/1000000 -> 0.50340934 | U11: =(L11/T11)^(1/Inputs!$D$8)-1 -> 0.17059434 | V11: =R11*Inputs!$D$29/(Inputs!$D$30*G11) -> 0.0087980223
A12: =Data!A12 -> Congo, Dem. Rep. | B12: =Data!B12 -> COD | C12: =Data!AB12 -> 1 | D12: =MIN(Inputs!$D$24,MAX(Inputs!$D$23,(Data!J12/Inputs!$D$65)^Inputs!$D$22)) -> 0.63579658 | E12: =MIN(1,Data!E12/Data!F12) -> 0.89555334 | F12: =MIN(Inputs!$D$27,MAX(Inputs!$D$26,(E12/Inputs!$D$66)^Inputs!$D$25)) -> 0.92237412 | G12: =MIN(Inputs!$D$37,MAX(Inputs!$D$36,(Data!D12/Inputs!$D$34)^Inputs!$D$35)) -> 1.5206829 | H12: =Inputs!$C$17*D12*F12 -> 8.7966347 | I12: =Inputs!$D$17*D12*F12 -> 14.661058 | J12: =Inputs!$E$17*D12*F12 -> 18.766154 | K12: =Forecast!L12*H12/1000000 -> 291.99415 | L12: =Forecast!M12*I12/1000000 -> 620.39175 | M12: =Forecast!N12*J12/1000000 -> 946.20791 | N12: =Inputs!$C$19*Forecast!H12+Inputs!$C$18*Forecast!O12 -> 1078892.5 | O12: =Inputs!$D$19*Forecast!H12+Inputs!$D$18*Forecast!P12 -> 3436668.6 | P12: =Inputs!$E$19*Forecast!H12+Inputs!$E$18*Forecast!Q12 -> 6969160.7 | Q12: =N12*H12/1000000 -> 9.4906234 | R12: =O12*I12/1000000 -> 50.385198 | S12: =P12*J12/1000000 -> 130.78434 | T12: =Data!D12*Data!E12*I12/1000000 -> 293.64639 | U12: =(L12/T12)^(1/Inputs!$D$8)-1 -> 0.13276605 | V12: =R12*Inputs!$D$29/(Inputs!$D$30*G12) -> 1.380553
A13: =Data!A13 -> Congo, Rep. | B13: =Data!B13 -> COG | C13: =Data!AB13 -> 1 | D13: =MIN(Inputs!$D$24,MAX(Inputs!$D$23,(Data!J13/Inputs!$D$65)^Inputs!$D$22)) -> 1.0183184 | E13: =MIN(1,Data!E13/Data!F13) -> 0.92831585 | F13: =MIN(Inputs!$D$27,MAX(Inputs!$D$26,(E13/Inputs!$D$66)^Inputs!$D$25)) -> 0.95611784 | G13: =MIN(Inputs!$D$37,MAX(Inputs!$D$36,(Data!D13/Inputs!$D$34)^Inputs!$D$35)) -> 0.6 | H13: =Inputs!$C$17*D13*F13 -> 14.604485 | I13: =Inputs!$D$17*D13*F13 -> 24.340809 | J13: =Inputs!$E$17*D13*F13 -> 31.156235 | K13: =Forecast!L13*H13/1000000 -> 39.730589 | L13: =Forecast!M13*I13/1000000 -> 77.635606 | M13: =Forecast!N13*J13/1000000 -> 110.5217 | N13: =Inputs!$C$19*Forecast!H13+Inputs!$C$18*Forecast!O13 -> 76331.997 | O13: =Inputs!$D$19*Forecast!H13+Inputs!$D$18*Forecast!P13 -> 217561.6 | P13: =Inputs!$E$19*Forecast!H13+Inputs!$E$18*Forecast!Q13 -> 410852.67 | Q13: =N13*H13/1000000 -> 1.1147895 | R13: =O13*I13/1000000 -> 5.2956252 | S13: =P13*J13/1000000 -> 12.800622 | T13: =Data!D13*Data!E13*I13/1000000 -> 45.900434 | U13: =(L13/T13)^(1/Inputs!$D$8)-1 -> 0.091542609 | V13: =R13*Inputs!$D$29/(Inputs!$D$30*G13) -> 0.36775175
A14: =Data!A14 -> Cote d'Ivoire | B14: =Data!B14 -> CIV | C14: =Data!AB14 -> 1 | D14: =MIN(Inputs!$D$24,MAX(Inputs!$D$23,(Data!J14/Inputs!$D$65)^Inputs!$D$22)) -> 1.0517282 | E14: =MIN(1,Data!E14/Data!F14) -> 0.92728816 | F14: =MIN(Inputs!$D$27,MAX(Inputs!$D$26,(E14/Inputs!$D$66)^Inputs!$D$25)) -> 0.95505936 | G14: =MIN(Inputs!$D$37,MAX(Inputs!$D$36,(Data!D14/Inputs!$D$34)^Inputs!$D$35)) -> 0.96512486 | H14: =Inputs!$C$17*D14*F14 -> 15.066942 | I14: =Inputs!$D$17*D14*F14 -> 25.111571 | J14: =Inputs!$E$17*D14*F14 -> 32.142811 | K14: =Forecast!L14*H14/1000000 -> 210.86761 | L14: =Forecast!M14*I14/1000000 -> 408.8148 | M14: =Forecast!N14*J14/1000000 -> 578.52624 | N14: =Inputs!$C$19*Forecast!H14+Inputs!$C$18*Forecast!O14 -> 385935.73 | O14: =Inputs!$D$19*Forecast!H14+Inputs!$D$18*Forecast!P14 -> 1087477.1 | P14: =Inputs!$E$19*Forecast!H14+Inputs!$E$18*Forecast!Q14 -> 2040802.3 | Q14: =N14*H14/1000000 -> 5.8148714 | R14: =O14*I14/1000000 -> 27.308259 | S14: =P14*J14/1000000 -> 65.597123 | T14: =Data!D14*Data!E14*I14/1000000 -> 245.33283 | U14: =(L14/T14)^(1/Inputs!$D$8)-1 -> 0.088834376 | V14: =R14*Inputs!$D$29/(Inputs!$D$30*G14) -> 1.1789605
A15: =Data!A15 -> Eswatini | B15: =Data!B15 -> SWZ | C15: =Data!AB15 -> 0 | D15: =MIN(Inputs!$D$24,MAX(Inputs!$D$23,(Data!J15/Inputs!$D$65)^Inputs!$D$22)) -> 1.2231338 | E15: =MIN(1,Data!E15/Data!F15) -> 0.77410923 | F15: =MIN(Inputs!$D$27,MAX(Inputs!$D$26,(E15/Inputs!$D$66)^Inputs!$D$25)) -> 0.79729291 | G15: =MIN(Inputs!$D$37,MAX(Inputs!$D$36,(Data!D15/Inputs!$D$34)^Inputs!$D$35)) -> 0.6 | H15: =Inputs!$C$17*D15*F15 -> 14.627938 | I15: =Inputs!$D$17*D15*F15 -> 24.379897 | J15: =Inputs!$E$17*D15*F15 -> 31.206268 | K15: =Forecast!L15*H15/1000000 -> 8.04228 | L15: =Forecast!M15*I15/1000000 -> 15.799012 | M15: =Forecast!N15*J15/1000000 -> 22.583464 | N15: =Inputs!$C$19*Forecast!H15+Inputs!$C$18*Forecast!O15 -> 15602.158 | O15: =Inputs!$D$19*Forecast!H15+Inputs!$D$18*Forecast!P15 -> 44809.536 | P15: =Inputs!$E$19*Forecast!H15+Inputs!$E$18*Forecast!Q15 -> 84983.255 | Q15: =N15*H15/1000000 -> 0.22822741 | R15: =O15*I15/1000000 -> 1.0924519 | S15: =P15*J15/1000000 -> 2.6520102 | T15: =Data!D15*Data!E15*I15/1000000 -> 10.030506 | U15: =(L15/T15)^(1/Inputs!$D$8)-1 -> 0.078659851 | V15: =R15*Inputs!$D$29/(Inputs!$D$30*G15) -> 0.075864712
A16: =Data!A16 -> Ethiopia | B16: =Data!B16 -> ETH | C16: =Data!AB16 -> 1 | D16: =MIN(Inputs!$D$24,MAX(Inputs!$D$23,(Data!J16/Inputs!$D$65)^Inputs!$D$22)) -> 0.78188878 | E16: =MIN(1,Data!E16/Data!F16) -> 0.19362761 | F16: =MIN(Inputs!$D$27,MAX(Inputs!$D$26,(E16/Inputs!$D$66)^Inputs!$D$25)) -> 0.25 | G16: =MIN(Inputs!$D$37,MAX(Inputs!$D$36,(Data!D16/Inputs!$D$34)^Inputs!$D$35)) -> 1.7238352 | H16: =Inputs!$C$17*D16*F16 -> 2.9320829 | I16: =Inputs!$D$17*D16*F16 -> 4.8868048 | J16: =Inputs!$E$17*D16*F16 -> 6.2551102 | K16: =Forecast!L16*H16/1000000 -> 40.386021 | L16: =Forecast!M16*I16/1000000 -> 103.8991 | M16: =Forecast!N16*J16/1000000 -> 194.99787 | N16: =Inputs!$C$19*Forecast!H16+Inputs!$C$18*Forecast!O16 -> 543045 | O16: =Inputs!$D$19*Forecast!H16+Inputs!$D$18*Forecast!P16 -> 2157428.2 | P16: =Inputs!$E$19*Forecast!H16+Inputs!$E$18*Forecast!Q16 -> 5396679.2 | Q16: =N16*H16/1000000 -> 1.592253 | R16: =O16*I16/1000000 -> 10.542931 | S16: =P16*J16/1000000 -> 33.756823 | T16: =Data!D16*Data!E16*I16/1000000 -> 36.053779 | U16: =(L16/T16)^(1/Inputs!$D$8)-1 -> 0.19291684 | V16: =R16*Inputs!$D$29/(Inputs!$D$30*G16) -> 0.25483224
A17: =Data!A17 -> Gabon | B17: =Data!B17 -> GAB | C17: =Data!AB17 -> 0 | D17: =MIN(Inputs!$D$24,MAX(Inputs!$D$23,(Data!J17/Inputs!$D$65)^Inputs!$D$22)) -> 1.3 | E17: =MIN(1,Data!E17/Data!F17) -> 0.90408352 | F17: =MIN(Inputs!$D$27,MAX(Inputs!$D$26,(E17/Inputs!$D$66)^Inputs!$D$25)) -> 0.93115977 | G17: =MIN(Inputs!$D$37,MAX(Inputs!$D$36,(Data!D17/Inputs!$D$34)^Inputs!$D$35)) -> 0.6 | H17: =Inputs!$C$17*D17*F17 -> 18.157616 | I17: =Inputs!$D$17*D17*F17 -> 30.262693 | J17: =Inputs!$E$17*D17*F17 -> 38.736247 | K17: =Forecast!L17*H17/1000000 -> 23.811282 | L17: =Forecast!M17*I17/1000000 -> 44.62845 | M17: =Forecast!N17*J17/1000000 -> 61.613665 | N17: =Inputs!$C$19*Forecast!H17+Inputs!$C$18*Forecast!O17 -> 33240.171 | O17: =Inputs!$D$19*Forecast!H17+Inputs!$D$18*Forecast!P17 -> 88893.06 | P17: =Inputs!$E$19*Forecast!H17+Inputs!$E$18*Forecast!Q17 -> 162488.5 | Q17: =N17*H17/1000000 -> 0.60356225 | R17: =O17*I17/1000000 -> 2.6901434 | S17: =P17*J17/1000000 -> 6.2941947 | T17: =Data!D17*Data!E17*I17/1000000 -> 29.358489 | U17: =(L17/T17)^(1/Inputs!$D$8)-1 -> 0.072291881 | V17: =R17*Inputs!$D$29/(Inputs!$D$30*G17) -> 0.18681551
... A39: =Data!A39 -> Zimbabwe | B39: =Data!B39 -> ZWE | C39: =Data!AB39 -> 1 | D39: =MIN(Inputs!$D$24,MAX(Inputs!$D$23,(Data!J39/Inputs!$D$65)^Inputs!$D$22)) -> 0.96086518 | E39: =MIN(1,Data!E39/Data!F39) -> 0.87500677 | F39: =MIN(Inputs!$D$27,MAX(Inputs!$D$26,(E39/Inputs!$D$66)^Inputs!$D$25)) -> 0.90121221 | G39: =MIN(Inputs!$D$37,MAX(Inputs!$D$36,(Data!D39/Inputs!$D$34)^Inputs!$D$35)) -> 0.74521894 | H39: =Inputs!$C$17*D39*F39 -> 12.989151 | I39: =Inputs!$D$17*D39*F39 -> 21.648586 | J39: =Inputs!$E$17*D39*F39 -> 27.71019 | K39: =Forecast!L39*H39/1000000 -> 78.443629 | L39: =Forecast!M39*I39/1000000 -> 159.41589 | M39: =Forecast!N39*J39/1000000 -> 234.0881 | N39: =Inputs!$C$19*Forecast!H39+Inputs!$C$18*Forecast!O39 -> 182908.66 | O39: =Inputs!$D$19*Forecast!H39+Inputs!$D$18*Forecast!P39 -> 550309.53 | P39: =Inputs!$E$19*Forecast!H39+Inputs!$E$18*Forecast!Q39 -> 1073297.1 | Q39: =N39*H39/1000000 -> 2.3758283 | R39: =O39*I39/1000000 -> 11.913423 | S39: =P39*J39/1000000 -> 29.741267 | T39: =Data!D39*Data!E39*I39/1000000 -> 89.944651 | U39: =(L39/T39)^(1/Inputs!$D$8)-1 -> 0.1000845 | V39: =R39*Inputs!$D$29/(Inputs!$D$30*G39) -> 0.66610307

Sheet Scorecard
A1: Scorecard: attractiveness x ease of entry
A2: Scores run 0-100 across candidate markets only (min-max). Priority = square root of attractiveness x ease, which penalises a weak side.
A5: Country | B5: ISO3 | C5: Candidate | D5: Size: ln(winnable revenue 2030) | E5: Pool growth | F5: Merchant gap to Kenya (pp) | G5: Inclusion gap (pp) | H5: Remittances % GDP (capped) | I5: Adoption gain 2017-24 (pp) | J5: Merchant gap (filled) | K5: Inclusion gap (filled) | L5: Remittances (filled) | M5: Momentum (filled) | N5: Mobile subs per 100 (capped) | O5: Internet users % | P5: Electricity % | Q5: Urban % | R5: Inflation (capped) | S5: Depreciation (capped) | T5: GDP growth | U5: Mobile-led share | V5: Proximity | W5: Institutional stability | X5: Score: size | Y5: Score: growth | Z5: Score: merchant gap | AA5: Score: remittances | AB5: Score: inclusion gap | AC5: ATTRACTIVENESS | AD5: Score: mobile subs | AE5: Score: internet | AF5: Score: electricity | AG5: Score: urban | AH5: Digital readiness | AI5: Score: inflation | AJ5: Score: currency | AK5: Score: growth (GDP) | AL5: Macro stability | AM5: Mobile-led | AN5: Proximity | AO5: Momentum | AP5: Institutional stability | AQ5: EASE | AR5: PRIORITY SCORE | AS5: RANK | AT5: Discount rate | AU5: Quadrant
A6: =Data!A6 -> Benin | B6: =Data!B6 -> BEN | C6: =Data!AB6 -> 1 | D6: =LN(MAX(Pools!R6,0.000001)) -> 2.2524685 | E6: =Pools!U6 -> 0.10449263 | F6: =IF(Data!H6="","",MAX(0,(Inputs!$D$67-Data!H6)*100)) -> 48.992317 | G6: =IF(COUNT(Data!T6,Data!U6)=0,"",AVERAGE(Data!T6,Data!U6)) -> 13.268998 | H6: =IF(Data!O6="","",MIN(Inputs!$D$60,Data!O6)) -> 1.720825 | I6: =IF(Data!I6="","",(Data!E6-Data!I6)*100) -> 26.779014 | J6: =IF(F6="",MEDIAN(F$6:F$39),F6) -> 48.992317 | K6: =IF(G6="",MEDIAN(G$6:G$39),G6) -> 13.268998 | L6: =IF(H6="",MEDIAN(H$6:H$39),H6) -> 1.720825 | M6: =IF(I6="",MEDIAN(I$6:I$39),I6) -> 26.779014 | N6: =IF(Data!L6="",MIN(Inputs!$D$59,MEDIAN(Data!$L$6:$L$39)),MIN(Inputs!$D$59,Data!L6)) -> 120 | O6: =IF(Data!M6="",MEDIAN(Data!$M$6:$M$39),Data!M6) -> 33.983799 | P6: =IF(Data!N6="",MEDIAN(Data!$N$6:$N$39),Data!N6) -> 59 | Q6: =IF(Data!K6="",MEDIAN(Data!$K$6:$K$39),Data!K6) -> 52.545535 | R6: =IF(Data!Q6="",MIN(Inputs!$D$61,MEDIAN(Data!$Q$6:$Q$39)),MIN(Inputs!$D$61,Data!Q6)) -> 1.7501368 | S6: =IF(Data!R6="",MAX(Inputs!$D$63,MIN(Inputs!$D$62,MEDIAN(Data!$R$6:$R$39))),MAX(Inputs!$D$63,MIN(Inputs!$D$62,Data!R6))) -> 2.9729476 | T6: =IF(Data!S6="",MEDIAN(Data!$S$6:$S$39),Data!S6) -> 6.68628 | U6: =Pools!E6 -> 0.86554932 | V6: =Data!W6 -> 20 | W6: =Data!X6 -> 100 | X6: =IF($C6=1,100*(D6-_xlfn.MINIFS(D$6:D$39,$C$6:$C$39,1))/(_xlfn.MAXIFS(D$6:D$39,$C$6:$C$39,1)-_xlfn.MINIFS(D$6:D$39,$C$6:$C$39,1)),"") -> 41.075063 | Y6: =IF($C6=1,100*(E6-_xlfn.MINIFS(E$6:E$39,$C$6:$C$39,1))/(_xlfn.MAXIFS(E$6:E$39,$C$6:$C$39,1)-_xlfn.MINIFS(E$6:E$39,$C$6:$C$39,1)),"") -> 35.161961 | Z6: =IF($C6=1,100*(J6-_xlfn.MINIFS(J$6:J$39,$C$6:$C$39,1))/(_xlfn.MAXIFS(J$6:J$39,$C$6:$C$39,1)-_xlfn.MINIFS(J$6:J$39,$C$6:$C$39,1)),"") -> 90.233978 | AA6: =IF($C6=1,100*(L6-_xlfn.MINIFS(L$6:L$39,$C$6:$C$39,1))/(_xlfn.MAXIFS(L$6:L$39,$C$6:$C$39,1)-_xlfn.MINIFS(L$6:L$39,$C$6:$C$39,1)),"") -> 10.195547 | AB6: =IF($C6=1,100*(K6-_xlfn.MINIFS(K$6:K$39,$C$6:$C$39,1))/(_xlfn.MAXIFS(K$6:K$39,$C$6:$C$39,1)-_xlfn.MINIFS(K$6:K$39,$C$6:$C$39,1)),"") -> 45.98731 | AC6: =IF($C6=1,Inputs!$D$46*X6+Inputs!$D$47*Y6+Inputs!$D$48*Z6+Inputs!$D$49*AA6+Inputs!$D$50*AB6,"") -> 43.37119 | AD6: =IF($C6=1,100*(N6-_xlfn.MINIFS(N$6:N$39,$C$6:$C$39,1))/(_xlfn.MAXIFS(N$6:N$39,$C$6:$C$39,1)-_xlfn.MINIFS(N$6:N$39,$C$6:$C$39,1)),"") -> 100 | AE6: =IF($C6=1,100*(O6-_xlfn.MINIFS(O$6:O$39,$C$6:$C$39,1))/(_xlfn.MAXIFS(O$6:O$39,$C$6:$C$39,1)-_xlfn.MINIFS(O$6:O$39,$C$6:$C$39,1)),"") -> 36.067964 | AF6: =IF($C6=1,100*(P6-_xlfn.MINIFS(P$6:P$39,$C$6:$C$39,1))/(_xlfn.MAXIFS(P$6:P$39,$C$6:$C$39,1)-_xlfn.MINIFS(P$6:P$39,$C$6:$C$39,1)),"") -> 58.089172 | AG6: =IF($C6=1,100*(Q6-_xlfn.MINIFS(Q$6:Q$39,$C$6:$C$39,1))/(_xlfn.MAXIFS(Q$6:Q$39,$C$6:$C$39,1)-_xlfn.MINIFS(Q$6:Q$39,$C$6:$C$39,1)),"") -> 75.672381 | AH6: =IF($C6=1,AVERAGE(AD6:AG6),"") -> 67.457379 | AI6: =IF($C6=1,100*(_xlfn.MAXIFS(R$6:R$39,$C$6:$C$39,1)-R6)/(_xlfn.MAXIFS(R$6:R$39,$C$6:$C$39,1)-_xlfn.MINIFS(R$6:R$39,$C$6:$C$39,1)),"") -> 100 | AJ6: =IF($C6=1,100*(_xlfn.MAXIFS(S$6:S$39,$C$6:$C$39,1)-S6)/(_xlfn.MAXIFS(S$6:S$39,$C$6:$C$39,1)-_xlfn.MINIFS(S$6:S$39,$C$6:$C$39,1)),"") -> 90.743828 | AK6: =IF($C6=1,100*(T6-_xlfn.MINIFS(T$6:T$39,$C$6:$C$39,1))/(_xlfn.MAXIFS(T$6:T$39,$C$6:$C$39,1)-_xlfn.MINIFS(T$6:T$39,$C$6:$C$39,1)),"") -> 81.07685 | AL6: =IF($C6=1,AVERAGE(AI6:AK6),"") -> 90.606893 | AM6: =IF($C6=1,100*(U6-_xlfn.MINIFS(U$6:U$39,$C$6:$C$39,1))/(_xlfn.MAXIFS(U$6:U$39,$C$6:$C$39,1)-_xlfn.MINIFS(U$6:U$39,$C$6:$C$39,1)),"") -> 87.27185 | AN6: =IF($C6=1,100*(V6-_xlfn.MINIFS(V$6:V$39,$C$6:$C$39,1))/(_xlfn.MAXIFS(V$6:V$39,$C$6:$C$39,1)-_xlfn.MINIFS(V$6:V$39,$C$6:$C$39,1)),"") -> 0 | AO6: =IF($C6=1,100*(M6-_xlfn.MINIFS(M$6:M$39,$C$6:$C$39,1))/(_xlfn.MAXIFS(M$6:M$39,$C$6:$C$39,1)-_xlfn.MINIFS(M$6:M$39,$C$6:$C$39,1)),"") -> 63.29377 | AP6: =IF($C6=1,W6,"") -> 100 | AQ6: =IF($C6=1,Inputs!$D$52*AH6+Inputs!$D$53*AL6+Inputs!$D$54*AM6+Inputs!$D$55*AN6+Inputs!$D$56*AO6+Inputs!$D$57*AP6,"") -> 71.033009 | AR6: =IF($C6=1,SQRT(AC6*AQ6),"") -> 55.504829 | AS6: =IF($C6=1,COUNTIFS($C$6:$C$39,1,$AR$6:$AR$39,">"&AR6)+1,"") -> 5 | AT6: =IF($C6=1,Inputs!$D$38+Inputs!$D$39*(1-AL6/100)+Inputs!$D$40*(1-AP6/100),"") -> 0.12375724 | AU6: =IF($C6=1,IF(AC6>=MEDIAN(AC$6:AC$39),IF(AQ6>=MEDIAN(AQ$6:AQ$39),"Prioritise","Big but hard"),IF(AQ6>=MEDIAN(AQ$6:AQ$39),"Easy but small","Deprioritise")),"") -> Easy but small
A7: =Data!A7 -> Botswana | B7: =Data!B7 -> BWA | C7: =Data!AB7 -> 0 | D7: =LN(MAX(Pools!R7,0.000001)) -> 0.98881774 | E7: =Pools!U7 -> 0.083365418 | F7: =IF(Data!H7="","",MAX(0,(Inputs!$D$67-Data!H7)*100)) -> 30.160576 | G7: =IF(COUNT(Data!T7,Data!U7)=0,"",AVERAGE(Data!T7,Data!U7)) -> 13.756284 | H7: =IF(Data!O7="","",MIN(Inputs!$D$60,Data!O7)) -> 0.66523525 | I7: =IF(Data!I7="","",(Data!E7-Data!I7)*100) -> 27.239509 | J7: =IF(F7="",MEDIAN(F$6:F$39),F7) -> 30.160576 | K7: =IF(G7="",MEDIAN(G$6:G$39),G7) -> 13.756284 | L7: =IF(H7="",MEDIAN(H$6:H$39),H7) -> 0.66523525 | M7: =IF(I7="",MEDIAN(I$6:I$39),I7) -> 27.239509 | N7: =IF(Data!L7="",MIN(Inputs!$D$59,MEDIAN(Data!$L$6:$L$39)),MIN(Inputs!$D$59,Data!L7)) -> 120 | O7: =IF(Data!M7="",MEDIAN(Data!$M$6:$M$39),Data!M7) -> 57.4595 | P7: =IF(Data!N7="",MEDIAN(Data!$N$6:$N$39),Data!N7) -> 80.2 | Q7: =IF(Data!K7="",MEDIAN(Data!$K$6:$K$39),Data!K7) -> 67.462354 | R7: =IF(Data!Q7="",MIN(Inputs!$D$61,MEDIAN(Data!$Q$6:$Q$39)),MIN(Inputs!$D$61,Data!Q7)) -> 6.5171781 | S7: =IF(Data!R7="",MAX(Inputs!$D$63,MIN(Inputs!$D$62,MEDIAN(Data!$R$6:$R$39))),MAX(Inputs!$D$63,MIN(Inputs!$D$62,Data!R7))) -> 6.7186259 | T7: =IF(Data!S7="",MEDIAN(Data!$S$6:$S$39),Data!S7) -> 1.9713985 | U7: =Pools!E7 -> 0.84015465 | V7: =Data!W7 -> 20 | W7: =Data!X7 -> 100 | X7: =IF($C7=1,100*(D7-_xlfn.MINIFS(D$6:D$39,$C$6:$C$39,1))/(_xlfn.MAXIFS(D$6:D$39,$C$6:$C$39,1)-_xlfn.MINIFS(D$6:D$39,$C$6:$C$39,1)),"") | Y7: =IF($C7=1,100*(E7-_xlfn.MINIFS(E$6:E$39,$C$6:$C$39,1))/(_xlfn.MAXIFS(E$6:E$39,$C$6:$C$39,1)-_xlfn.MINIFS(E$6:E$39,$C$6:$C$39,1)),"") | Z7: =IF($C7=1,100*(J7-_xlfn.MINIFS(J$6:J$39,$C$6:$C$39,1))/(_xlfn.MAXIFS(J$6:J$39,$C$6:$C$39,1)-_xlfn.MINIFS(J$6:J$39,$C$6:$C$39,1)),"") | AA7: =IF($C7=1,100*(L7-_xlfn.MINIFS(L$6:L$39,$C$6:$C$39,1))/(_xlfn.MAXIFS(L$6:L$39,$C$6:$C$39,1)-_xlfn.MINIFS(L$6:L$39,$C$6:$C$39,1)),"") | AB7: =IF($C7=1,100*(K7-_xlfn.MINIFS(K$6:K$39,$C$6:$C$39,1))/(_xlfn.MAXIFS(K$6:K$39,$C$6:$C$39,1)-_xlfn.MINIFS(K$6:K$39,$C$6:$C$39,1)),"") | AC7: =IF($C7=1,Inputs!$D$46*X7+Inputs!$D$47*Y7+Inputs!$D$48*Z7+Inputs!$D$49*AA7+Inputs!$D$50*AB7,"") | AD7: =IF($C7=1,100*(N7-_xlfn.MINIFS(N$6:N$39,$C$6:$C$39,1))/(_xlfn.MAXIFS(N$6:N$39,$C$6:$C$39,1)-_xlfn.MINIFS(N$6:N$39,$C$6:$C$39,1)),"") | AE7: =IF($C7=1,100*(O7-_xlfn.MINIFS(O$6:O$39,$C$6:$C$39,1))/(_xlfn.MAXIFS(O$6:O$39,$C$6:$C$39,1)-_xlfn.MINIFS(O$6:O$39,$C$6:$C$39,1)),"") | AF7: =IF($C7=1,100*(P7-_xlfn.MINIFS(P$6:P$39,$C$6:$C$39,1))/(_xlfn.MAXIFS(P$6:P$39,$C$6:$C$39,1)-_xlfn.MINIFS(P$6:P$39,$C$6:$C$39,1)),"") | AG7: =IF($C7=1,100*(Q7-_xlfn.MINIFS(Q$6:Q$39,$C$6:$C$39,1))/(_xlfn.MAXIFS(Q$6:Q$39,$C$6:$C$39,1)-_xlfn.MINIFS(Q$6:Q$39,$C$6:$C$39,1)),"") | AH7: =IF($C7=1,AVERAGE(AD7:AG7),"") | AI7: =IF($C7=1,100*(_xlfn.MAXIFS(R$6:R$39,$C$6:$C$39,1)-R7)/(_xlfn.MAXIFS(R$6:R$39,$C$6:$C$39,1)-_xlfn.MINIFS(R$6:R$39,$C$6:$C$39,1)),"") | AJ7: =IF($C7=1,100*(_xlfn.MAXIFS(S$6:S$39,$C$6:$C$39,1)-S7)/(_xlfn.MAXIFS(S$6:S$39,$C$6:$C$39,1)-_xlfn.MINIFS(S$6:S$39,$C$6:$C$39,1)),"") | AK7: =IF($C7=1,100*(T7-_xlfn.MINIFS(T$6:T$39,$C$6:$C$39,1))/(_xlfn.MAXIFS(T$6:T$39,$C$6:$C$39,1)-_xlfn.MINIFS(T$6:T$39,$C$6:$C$39,1)),"") | AL7: =IF($C7=1,AVERAGE(AI7:AK7),"") | AM7: =IF($C7=1,100*(U7-_xlfn.MINIFS(U$6:U$39,$C$6:$C$39,1))/(_xlfn.MAXIFS(U$6:U$39,$C$6:$C$39,1)-_xlfn.MINIFS(U$6:U$39,$C$6:$C$39,1)),"") | AN7: =IF($C7=1,100*(V7-_xlfn.MINIFS(V$6:V$39,$C$6:$C$39,1))/(_xlfn.MAXIFS(V$6:V$39,$C$6:$C$39,1)-_xlfn.MINIFS(V$6:V$39,$C$6:$C$39,1)),"") | AO7: =IF($C7=1,100*(M7-_xlfn.MINIFS(M$6:M$39,$C$6:$C$39,1))/(_xlfn.MAXIFS(M$6:M$39,$C$6:$C$39,1)-_xlfn.MINIFS(M$6:M$39,$C$6:$C$39,1)),"") | AP7: =IF($C7=1,W7,"") | AQ7: =IF($C7=1,Inputs!$D$52*AH7+Inputs!$D$53*AL7+Inputs!$D$54*AM7+Inputs!$D$55*AN7+Inputs!$D$56*AO7+Inputs!$D$57*AP7,"") | AR7: =IF($C7=1,SQRT(AC7*AQ7),"") | AS7: =IF($C7=1,COUNTIFS($C$6:$C$39,1,$AR$6:$AR$39,">"&AR7)+1,"") | AT7: =IF($C7=1,Inputs!$D$38+Inputs!$D$39*(1-AL7/100)+Inputs!$D$40*(1-AP7/100),"") | AU7: =IF($C7=1,IF(AC7>=MEDIAN(AC$6:AC$39),IF(AQ7>=MEDIAN(AQ$6:AQ$39),"Prioritise","Big but hard"),IF(AQ7>=MEDIAN(AQ$6:AQ$39),"Easy but small","Deprioritise")),"")
A8: =Data!A8 -> Burkina Faso | B8: =Data!B8 -> BFA | C8: =Data!AB8 -> 1 | D8: =LN(MAX(Pools!R8,0.000001)) -> 2.5616513 | E8: =Pools!U8 -> 0.10352897 | F8: =IF(Data!H8="","",MAX(0,(Inputs!$D$67-Data!H8)*100)) -> 43.712594 | G8: =IF(COUNT(Data!T8,Data!U8)=0,"",AVERAGE(Data!T8,Data!U8)) -> 16.039934 | H8: =IF(Data!O8="","",MIN(Inputs!$D$60,Data!O8)) -> 2.5727498 | I8: =IF(Data!I8="","",(Data!E8-Data!I8)*100) -> 11.134566 | J8: =IF(F8="",MEDIAN(F$6:F$39),F8) -> 43.712594 | K8: =IF(G8="",MEDIAN(G$6:G$39),G8) -> 16.039934 | L8: =IF(H8="",MEDIAN(H$6:H$39),H8) -> 2.5727498 | M8: =IF(I8="",MEDIAN(I$6:I$39),I8) -> 11.134566 | N8: =IF(Data!L8="",MIN(Inputs!$D$59,MEDIAN(Data!$L$6:$L$39)),MIN(Inputs!$D$59,Data!L8)) -> 116.58959 | O8: =IF(Data!M8="",MEDIAN(Data!$M$6:$M$39),Data!M8) -> 28.252701 | P8: =IF(Data!N8="",MEDIAN(Data!$N$6:$N$39),Data!N8) -> 34 | Q8: =IF(Data!K8="",MEDIAN(Data!$K$6:$K$39),Data!K8) -> 28.335251 | R8: =IF(Data!Q8="",MIN(Inputs!$D$61,MEDIAN(Data!$Q$6:$Q$39)),MIN(Inputs!$D$61,Data!Q8)) -> 6.4079877 | S8: =IF(Data!R8="",MAX(Inputs!$D$63,MIN(Inputs!$D$62,MEDIAN(Data!$R$6:$R$39))),MAX(Inputs!$D$63,MIN(Inputs!$D$62,Data!R8))) -> 2.9775832 | T8: =IF(Data!S8="",MEDIAN(Data!$S$6:$S$39),Data!S8) -> 3.1536549 | U8: =Pools!E8 -> 0.85863345 | V8: =Data!W8 -> 20 | W8: =Data!X8 -> 0 | X8: =IF($C8=1,100*(D8-_xlfn.MINIFS(D$6:D$39,$C$6:$C$39,1))/(_xlfn.MAXIFS(D$6:D$39,$C$6:$C$39,1)-_xlfn.MINIFS(D$6:D$39,$C$6:$C$39,1)),"") -> 48.525297 | Y8: =IF($C8=1,100*(E8-_xlfn.MINIFS(E$6:E$39,$C$6:$C$39,1))/(_xlfn.MAXIFS(E$6:E$39,$C$6:$C$39,1)-_xlfn.MINIFS(E$6:E$39,$C$6:$C$39,1)),"") -> 34.589864 | Z8: =IF($C8=1,100*(J8-_xlfn.MINIFS(J$6:J$39,$C$6:$C$39,1))/(_xlfn.MAXIFS(J$6:J$39,$C$6:$C$39,1)-_xlfn.MINIFS(J$6:J$39,$C$6:$C$39,1)),"") -> 78.371213 | AA8: =IF($C8=1,100*(L8-_xlfn.MINIFS(L$6:L$39,$C$6:$C$39,1))/(_xlfn.MAXIFS(L$6:L$39,$C$6:$C$39,1)-_xlfn.MINIFS(L$6:L$39,$C$6:$C$39,1)),"") -> 15.956947 | AB8: =IF($C8=1,100*(K8-_xlfn.MINIFS(K$6:K$39,$C$6:$C$39,1))/(_xlfn.MAXIFS(K$6:K$39,$C$6:$C$39,1)-_xlfn.MINIFS(K$6:K$39,$C$6:$C$39,1)),"") -> 58.566594 | AC8: =IF($C8=1,Inputs!$D$46*X8+Inputs!$D$47*Y8+Inputs!$D$48*Z8+Inputs!$D$49*AA8+Inputs!$D$50*AB8,"") -> 46.83604 | AD8: =IF($C8=1,100*(N8-_xlfn.MINIFS(N$6:N$39,$C$6:$C$39,1))/(_xlfn.MAXIFS(N$6:N$39,$C$6:$C$39,1)-_xlfn.MINIFS(N$6:N$39,$C$6:$C$39,1)),"") -> 96.121722 | AE8: =IF($C8=1,100*(O8-_xlfn.MINIFS(O$6:O$39,$C$6:$C$39,1))/(_xlfn.MAXIFS(O$6:O$39,$C$6:$C$39,1)-_xlfn.MINIFS(O$6:O$39,$C$6:$C$39,1)),"") -> 27.810821 | AF8: =IF($C8=1,100*(P8-_xlfn.MINIFS(P$6:P$39,$C$6:$C$39,1))/(_xlfn.MAXIFS(P$6:P$39,$C$6:$C$39,1)-_xlfn.MINIFS(P$6:P$39,$C$6:$C$39,1)),"") -> 26.242038 | AG8: =IF($C8=1,100*(Q8-_xlfn.MINIFS(Q$6:Q$39,$C$6:$C$39,1))/(_xlfn.MAXIFS(Q$6:Q$39,$C$6:$C$39,1)-_xlfn.MINIFS(Q$6:Q$39,$C$6:$C$39,1)),"") -> 23.739162 | AH8: =IF($C8=1,AVERAGE(AD8:AG8),"") -> 43.478436 | AI8: =IF($C8=1,100*(_xlfn.MAXIFS(R$6:R$39,$C$6:$C$39,1)-R8)/(_xlfn.MAXIFS(R$6:R$39,$C$6:$C$39,1)-_xlfn.MINIFS(R$6:R$39,$C$6:$C$39,1)),"") -> 87.822568 | AJ8: =IF($C8=1,100*(_xlfn.MAXIFS(S$6:S$39,$C$6:$C$39,1)-S8)/(_xlfn.MAXIFS(S$6:S$39,$C$6:$C$39,1)-_xlfn.MINIFS(S$6:S$39,$C$6:$C$39,1)),"") -> 90.732467 | AK8: =IF($C8=1,100*(T8-_xlfn.MINIFS(T$6:T$39,$C$6:$C$39,1))/(_xlfn.MAXIFS(T$6:T$39,$C$6:$C$39,1)-_xlfn.MINIFS(T$6:T$39,$C$6:$C$39,1)),"") -> 29.500922 | AL8: =IF($C8=1,AVERAGE(AI8:AK8),"") -> 69.351986 | AM8: =IF($C8=1,100*(U8-_xlfn.MINIFS(U$6:U$39,$C$6:$C$39,1))/(_xlfn.MAXIFS(U$6:U$39,$C$6:$C$39,1)-_xlfn.MINIFS(U$6:U$39,$C$6:$C$39,1)),"") -> 86.373589 | AN8: =IF($C8=1,100*(V8-_xlfn.MINIFS(V$6:V$39,$C$6:$C$39,1))/(_xlfn.MAXIFS(V$6:V$39,$C$6:$C$39,1)-_xlfn.MINIFS(V$6:V$39,$C$6:$C$39,1)),"") -> 0 | AO8: =IF($C8=1,100*(M8-_xlfn.MINIFS(M$6:M$39,$C$6:$C$39,1))/(_xlfn.MAXIFS(M$6:M$39,$C$6:$C$39,1)-_xlfn.MINIFS(M$6:M$39,$C$6:$C$39,1)),"") -> 32.378071 | AP8: =IF($C8=1,W8,"") -> 0 | AQ8: =IF($C8=1,Inputs!$D$52*AH8+Inputs!$D$53*AL8+Inputs!$D$54*AM8+Inputs!$D$55*AN8+Inputs!$D$56*AO8+Inputs!$D$57*AP8,"") -> 38.75993 | AR8: =IF($C8=1,SQRT(AC8*AQ8),"") -> 42.607061 | AS8: =IF($C8=1,COUNTIFS($C$6:$C$39,1,$AR$6:$AR$39,">"&AR8)+1,"") -> 21 | AT8: =IF($C8=1,Inputs!$D$38+Inputs!$D$39*(1-AL8/100)+Inputs!$D$40*(1-AP8/100),"") -> 0.17225921 | AU8: =IF($C8=1,IF(AC8>=MEDIAN(AC$6:AC$39),IF(AQ8>=MEDIAN(AQ$6:AQ$39),"Prioritise","Big but hard"),IF(AQ8>=MEDIAN(AQ$6:AQ$39),"Easy but small","Deprioritise")),"") -> Big but hard
A9: =Data!A9 -> Cameroon | B9: =Data!B9 -> CMR | C9: =Data!AB9 -> 1 | D9: =LN(MAX(Pools!R9,0.000001)) -> 3.0749237 | E9: =Pools!U9 -> 0.08783346 | F9: =IF(Data!H9="","",MAX(0,(Inputs!$D$67-Data!H9)*100)) -> 35.449204 | G9: =IF(COUNT(Data!T9,Data!U9)=0,"",AVERAGE(Data!T9,Data!U9)) -> 20.382984 | H9: =IF(Data!O9="","",MIN(Inputs!$D$60,Data!O9)) -> 1.2949265 | I9: =IF(Data!I9="","",(Data!E9-Data!I9)*100) -> 39.927622 | J9: =IF(F9="",MEDIAN(F$6:F$39),F9) -> 35.449204 | K9: =IF(G9="",MEDIAN(G$6:G$39),G9) -> 20.382984 | L9: =IF(H9="",MEDIAN(H$6:H$39),H9) -> 1.2949265 | M9: =IF(I9="",MEDIAN(I$6:I$39),I9) -> 39.927622 | N9: =IF(Data!L9="",MIN(Inputs!$D$59,MEDIAN(Data!$L$6:$L$39)),MIN(Inputs!$D$59,Data!L9)) -> 108.21313 | O9: =IF(Data!M9="",MEDIAN(Data!$M$6:$M$39),Data!M9) -> 46.258801 | P9: =IF(Data!N9="",MEDIAN(Data!$N$6:$N$39),Data!N9) -> 72 | Q9: =IF(Data!K9="",MEDIAN(Data!$K$6:$K$39),Data!K9) -> 55.403175 | R9: =IF(Data!Q9="",MIN(Inputs!$D$61,MEDIAN(Data!$Q$6:$Q$39)),MIN(Inputs!$D$61,Data!Q9)) -> 6.0546015 | S9: =IF(Data!R9="",MAX(Inputs!$D$63,MIN(Inputs!$D$62,MEDIAN(Data!$R$6:$R$39))),MAX(Inputs!$D$63,MIN(Inputs!$D$62,Data!R9))) -> 2.9775832 | T9: =IF(Data!S9="",MEDIAN(Data!$S$6:$S$39),Data!S9) -> 3.5363567 | U9: =Pools!E9 -> 0.90458391 | V9: =Data!W9 -> 20 | W9: =Data!X9 -> 0 | X9: =IF($C9=1,100*(D9-_xlfn.MINIFS(D$6:D$39,$C$6:$C$39,1))/(_xlfn.MAXIFS(D$6:D$39,$C$6:$C$39,1)-_xlfn.MINIFS(D$6:D$39,$C$6:$C$39,1)),"") -> 60.893381 | Y9: =IF($C9=1,100*(E9-_xlfn.MINIFS(E$6:E$39,$C$6:$C$39,1))/(_xlfn.MAXIFS(E$6:E$39,$C$6:$C$39,1)-_xlfn.MINIFS(E$6:E$39,$C$6:$C$39,1)),"") -> 25.271946 | Z9: =IF($C9=1,100*(J9-_xlfn.MINIFS(J$6:J$39,$C$6:$C$39,1))/(_xlfn.MAXIFS(J$6:J$39,$C$6:$C$39,1)-_xlfn.MINIFS(J$6:J$39,$C$6:$C$39,1)),"") -> 59.804588 | AA9: =IF($C9=1,100*(L9-_xlfn.MINIFS(L$6:L$39,$C$6:$C$39,1))/(_xlfn.MAXIFS(L$6:L$39,$C$6:$C$39,1)-_xlfn.MINIFS(L$6:L$39,$C$6:$C$39,1)),"") -> 7.3152786 | AB9: =IF($C9=1,100*(K9-_xlfn.MINIFS(K$6:K$39,$C$6:$C$39,1))/(_xlfn.MAXIFS(K$6:K$39,$C$6:$C$39,1)-_xlfn.MINIFS(K$6:K$39,$C$6:$C$39,1)),"") -> 78.282841 | AC9: =IF($C9=1,Inputs!$D$46*X9+Inputs!$D$47*Y9+Inputs!$D$48*Z9+Inputs!$D$49*AA9+Inputs!$D$50*AB9,"") -> 48.177479 | AD9: =IF($C9=1,100*(N9-_xlfn.MINIFS(N$6:N$39,$C$6:$C$39,1))/(_xlfn.MAXIFS(N$6:N$39,$C$6:$C$39,1)-_xlfn.MINIFS(N$6:N$39,$C$6:$C$39,1)),"") -> 86.596098 | AE9: =IF($C9=1,100*(O9-_xlfn.MINIFS(O$6:O$39,$C$6:$C$39,1))/(_xlfn.MAXIFS(O$6:O$39,$C$6:$C$39,1)-_xlfn.MINIFS(O$6:O$39,$C$6:$C$39,1)),"") -> 53.753307 | AF9: =IF($C9=1,100*(P9-_xlfn.MINIFS(P$6:P$39,$C$6:$C$39,1))/(_xlfn.MAXIFS(P$6:P$39,$C$6:$C$39,1)-_xlfn.MINIFS(P$6:P$39,$C$6:$C$39,1)),"") -> 74.649682 | AG9: =IF($C9=1,100*(Q9-_xlfn.MINIFS(Q$6:Q$39,$C$6:$C$39,1))/(_xlfn.MAXIFS(Q$6:Q$39,$C$6:$C$39,1)-_xlfn.MINIFS(Q$6:Q$39,$C$6:$C$39,1)),"") -> 81.802272 | AH9: =IF($C9=1,AVERAGE(AD9:AG9),"") -> 74.20034 | AI9: =IF($C9=1,100*(_xlfn.MAXIFS(R$6:R$39,$C$6:$C$39,1)-R9)/(_xlfn.MAXIFS(R$6:R$39,$C$6:$C$39,1)-_xlfn.MINIFS(R$6:R$39,$C$6:$C$39,1)),"") -> 88.746457 | AJ9: =IF($C9=1,100*(_xlfn.MAXIFS(S$6:S$39,$C$6:$C$39,1)-S9)/(_xlfn.MAXIFS(S$6:S$39,$C$6:$C$39,1)-_xlfn.MINIFS(S$6:S$39,$C$6:$C$39,1)),"") -> 90.732467 | AK9: =IF($C9=1,100*(T9-_xlfn.MINIFS(T$6:T$39,$C$6:$C$39,1))/(_xlfn.MAXIFS(T$6:T$39,$C$6:$C$39,1)-_xlfn.MINIFS(T$6:T$39,$C$6:$C$39,1)),"") -> 35.088324 | AL9: =IF($C9=1,AVERAGE(AI9:AK9),"") -> 71.522416 | AM9: =IF($C9=1,100*(U9-_xlfn.MINIFS(U$6:U$39,$C$6:$C$39,1))/(_xlfn.MAXIFS(U$6:U$39,$C$6:$C$39,1)-_xlfn.MINIFS(U$6:U$39,$C$6:$C$39,1)),"") -> 92.341816 | AN9: =IF($C9=1,100*(V9-_xlfn.MINIFS(V$6:V$39,$C$6:$C$39,1))/(_xlfn.MAXIFS(V$6:V$39,$C$6:$C$39,1)-_xlfn.MINIFS(V$6:V$39,$C$6:$C$39,1)),"") -> 0 | AO9: =IF($C9=1,100*(M9-_xlfn.MINIFS(M$6:M$39,$C$6:$C$39,1))/(_xlfn.MAXIFS(M$6:M$39,$C$6:$C$39,1)-_xlfn.MINIFS(M$6:M$39,$C$6:$C$39,1)),"") -> 89.277325 | AP9: =IF($C9=1,W9,"") -> 0 | AQ9: =IF($C9=1,Inputs!$D$52*AH9+Inputs!$D$53*AL9+Inputs!$D$54*AM9+Inputs!$D$55*AN9+Inputs!$D$56*AO9+Inputs!$D$57*AP9,"") -> 51.923556 | AR9: =IF($C9=1,SQRT(AC9*AQ9),"") -> 50.015458 | AS9: =IF($C9=1,COUNTIFS($C$6:$C$39,1,$AR$6:$AR$39,">"&AR9)+1,"") -> 14 | AT9: =IF($C9=1,Inputs!$D$38+Inputs!$D$39*(1-AL9/100)+Inputs!$D$40*(1-AP9/100),"") -> 0.17139103 | AU9: =IF($C9=1,IF(AC9>=MEDIAN(AC$6:AC$39),IF(AQ9>=MEDIAN(AQ$6:AQ$39),"Prioritise","Big but hard"),IF(AQ9>=MEDIAN(AQ$6:AQ$39),"Easy but small","Deprioritise")),"") -> Big but hard
A10: =Data!A10 -> Chad | B10: =Data!B10 -> TCD | C10: =Data!AB10 -> 1 | D10: =LN(MAX(Pools!R10,0.000001)) -> 1.6240678 | E10: =Pools!U10 -> 0.20803064 | F10: =IF(Data!H10="","",MAX(0,(Inputs!$D$67-Data!H10)*100)) -> 50.732897 | G10: =IF(COUNT(Data!T10,Data!U10)=0,"",AVERAGE(Data!T10,Data!U10)) -> 3.1390181 | H10: =IF(Data!O10="","",MIN(Inputs!$D$60,Data!O10)) | I10: =IF(Data!I10="","",(Data!E10-Data!I10)*100) -> -1.8975153 | J10: =IF(F10="",MEDIAN(F$6:F$39),F10) -> 50.732897 | K10: =IF(G10="",MEDIAN(G$6:G$39),G10) -> 3.1390181 | L10: =IF(H10="",MEDIAN(H$6:H$39),H10) -> 2.6075828 | M10: =IF(I10="",MEDIAN(I$6:I$39),I10) -> -1.8975153 | N10: =IF(Data!L10="",MIN(Inputs!$D$59,MEDIAN(Data!$L$6:$L$39)),MIN(Inputs!$D$59,Data!L10)) -> 72.928978 | O10: =IF(Data!M10="",MEDIAN(Data!$M$6:$M$39),Data!M10) -> 12.6269 | P10: =IF(Data!N10="",MEDIAN(Data!$N$6:$N$39),Data!N10) -> 13.4 | Q10: =IF(Data!K10="",MEDIAN(Data!$K$6:$K$39),Data!K10) -> 26.931529 | R10: =IF(Data!Q10="",MIN(Inputs!$D$61,MEDIAN(Data!$Q$6:$Q$39)),MIN(Inputs!$D$61,Data!Q10)) -> 8.5079637 | S10: =IF(Data!R10="",MAX(Inputs!$D$63,MIN(Inputs!$D$62,MEDIAN(Data!$R$6:$R$39))),MAX(Inputs!$D$63,MIN(Inputs!$D$62,Data!R10))) -> 2.9775832 | T10: =IF(Data!S10="",MEDIAN(Data!$S$6:$S$39),Data!S10) -> 4.360139 | U10: =Pools!E10 -> 0.63813115 | V10: =Data!W10 -> 20 | W10: =Data!X10 -> 40 | X10: =IF($C10=1,100*(D10-_xlfn.MINIFS(D$6:D$39,$C$6:$C$39,1))/(_xlfn.MAXIFS(D$6:D$39,$C$6:$C$39,1)-_xlfn.MINIFS(D$6:D$39,$C$6:$C$39,1)),"") -> 25.932786 | Y10: =IF($C10=1,100*(E10-_xlfn.MINIFS(E$6:E$39,$C$6:$C$39,1))/(_xlfn.MAXIFS(E$6:E$39,$C$6:$C$39,1)-_xlfn.MINIFS(E$6:E$39,$C$6:$C$39,1)),"") -> 96.629151 | Z10: =IF($C10=1,100*(J10-_xlfn.MINIFS(J$6:J$39,$C$6:$C$39,1))/(_xlfn.MAXIFS(J$6:J$39,$C$6:$C$39,1)-_xlfn.MINIFS(J$6:J$39,$C$6:$C$39,1)),"") -> 94.144805 | AA10: =IF($C10=1,100*(L10-_xlfn.MINIFS(L$6:L$39,$C$6:$C$39,1))/(_xlfn.MAXIFS(L$6:L$39,$C$6:$C$39,1)-_xlfn.MINIFS(L$6:L$39,$C$6:$C$39,1)),"") -> 16.192516 | AB10: =IF($C10=1,100*(K10-_xlfn.MINIFS(K$6:K$39,$C$6:$C$39,1))/(_xlfn.MAXIFS(K$6:K$39,$C$6:$C$39,1)-_xlfn.MINIFS(K$6:K$39,$C$6:$C$39,1)),"") -> 0 | AC10: =IF($C10=1,Inputs!$D$46*X10+Inputs!$D$47*Y10+Inputs!$D$48*Z10+Inputs!$D$49*AA10+Inputs!$D$50*AB10,"") -> 44.952903 | AD10: =IF($C10=1,100*(N10-_xlfn.MINIFS(N$6:N$39,$C$6:$C$39,1))/(_xlfn.MAXIFS(N$6:N$39,$C$6:$C$39,1)-_xlfn.MINIFS(N$6:N$39,$C$6:$C$39,1)),"") -> 46.47134 | AE10: =IF($C10=1,100*(O10-_xlfn.MINIFS(O$6:O$39,$C$6:$C$39,1))/(_xlfn.MAXIFS(O$6:O$39,$C$6:$C$39,1)-_xlfn.MINIFS(O$6:O$39,$C$6:$C$39,1)),"") -> 5.297777 | AF10: =IF($C10=1,100*(P10-_xlfn.MINIFS(P$6:P$39,$C$6:$C$39,1))/(_xlfn.MAXIFS(P$6:P$39,$C$6:$C$39,1)-_xlfn.MINIFS(P$6:P$39,$C$6:$C$39,1)),"") -> 0 | AG10: =IF($C10=1,100*(Q10-_xlfn.MINIFS(Q$6:Q$39,$C$6:$C$39,1))/(_xlfn.MAXIFS(Q$6:Q$39,$C$6:$C$39,1)-_xlfn.MINIFS(Q$6:Q$39,$C$6:$C$39,1)),"") -> 20.728052 | AH10: =IF($C10=1,AVERAGE(AD10:AG10),"") -> 18.124292 | AI10: =IF($C10=1,100*(_xlfn.MAXIFS(R$6:R$39,$C$6:$C$39,1)-R10)/(_xlfn.MAXIFS(R$6:R$39,$C$6:$C$39,1)-_xlfn.MINIFS(R$6:R$39,$C$6:$C$39,1)),"") -> 82.332415 | AJ10: =IF($C10=1,100*(_xlfn.MAXIFS(S$6:S$39,$C$6:$C$39,1)-S10)/(_xlfn.MAXIFS(S$6:S$39,$C$6:$C$39,1)-_xlfn.MINIFS(S$6:S$39,$C$6:$C$39,1)),"") -> 90.732467 | AK10: =IF($C10=1,100*(T10-_xlfn.MINIFS(T$6:T$39,$C$6:$C$39,1))/(_xlfn.MAXIFS(T$6:T$39,$C$6:$C$39,1)-_xlfn.MINIFS(T$6:T$39,$C$6:$C$39,1)),"") -> 47.115453 | AL10: =IF($C10=1,AVERAGE(AI10:AK10),"") -> 73.393445 | AM10: =IF($C10=1,100*(U10-_xlfn.MINIFS(U$6:U$39,$C$6:$C$39,1))/(_xlfn.MAXIFS(U$6:U$39,$C$6:$C$39,1)-_xlfn.MINIFS(U$6:U$39,$C$6:$C$39,1)),"") -> 57.733878 | AN10: =IF($C10=1,100*(V10-_xlfn.MINIFS(V$6:V$39,$C$6:$C$39,1))/(_xlfn.MAXIFS(V$6:V$39,$C$6:$C$39,1)-_xlfn.MINIFS(V$6:V$39,$C$6:$C$39,1)),"") -> 0 | AO10: =IF($C10=1,100*(M10-_xlfn.MINIFS(M$6:M$39,$C$6:$C$39,1))/(_xlfn.MAXIFS(M$6:M$39,$C$6:$C$39,1)-_xlfn.MINIFS(M$6:M$39,$C$6:$C$39,1)),"") -> 6.624789 | AP10: =IF($C10=1,W10,"") -> 40 | AQ10: =IF($C10=1,Inputs!$D$52*AH10+Inputs!$D$53*AL10+Inputs!$D$54*AM10+Inputs!$D$55*AN10+Inputs!$D$56*AO10+Inputs!$D$57*AP10,"") -> 35.626108 | AR10: =IF($C10=1,SQRT(AC10*AQ10),"") -> 40.018708 | AS10: =IF($C10=1,COUNTIFS($C$6:$C$39,1,$AR$6:$AR$39,">"&AR10)+1,"") -> 22 | AT10: =IF($C10=1,Inputs!$D$38+Inputs!$D$39*(1-AL10/100)+Inputs!$D$40*(1-AP10/100),"") -> 0.15464262 | AU10: =IF($C10=1,IF(AC10>=MEDIAN(AC$6:AC$39),IF(AQ10>=MEDIAN(AQ$6:AQ$39),"Prioritise","Big but hard"),IF(AQ10>=MEDIAN(AQ$6:AQ$39),"Easy but small","Deprioritise")),"") -> Deprioritise
A11: =Data!A11 -> Comoros | B11: =Data!B11 -> COM | C11: =Data!AB11 -> 0 | D11: =LN(MAX(Pools!R11,0.000001)) -> -2.0660001 | E11: =Pools!U11 -> 0.17059434 | F11: =IF(Data!H11="","",MAX(0,(Inputs!$D$67-Data!H11)*100)) -> 48.972382 | G11: =IF(COUNT(Data!T11,Data!U11)=0,"",AVERAGE(Data!T11,Data!U11)) -> 7.2425919 | H11: =IF(Data!O11="","",MIN(Inputs!$D$60,Data!O11)) -> 15 | I11: =IF(Data!I11="","",(Data!E11-Data!I11)*100) | J11: =IF(F11="",MEDIAN(F$6:F$39),F11) -> 48.972382 | K11: =IF(G11="",MEDIAN(G$6:G$39),G11) -> 7.2425919 | L11: =IF(H11="",MEDIAN(H$6:H$39),H11) -> 15 | M11: =IF(I11="",MEDIAN(I$6:I$39),I11) -> 19.328605 | N11: =IF(Data!L11="",MIN(Inputs!$D$59,MEDIAN(Data!$L$6:$L$39)),MIN(Inputs!$D$59,Data!L11)) -> 109.85563 | O11: =IF(Data!M11="",MEDIAN(Data!$M$6:$M$39),Data!M11) -> 32.517502 | P11: =IF(Data!N11="",MEDIAN(Data!$N$6:$N$39),Data!N11) -> 91.7 | Q11: =IF(Data!K11="",MEDIAN(Data!$K$6:$K$39),Data!K11) -> 33.539222 | R11: =IF(Data!Q11="",MIN(Inputs!$D$61,MEDIAN(Data!$Q$6:$Q$39)),MIN(Inputs!$D$61,Data!Q11)) -> 8.6525657 | S11: =IF(Data!R11="",MAX(Inputs!$D$63,MIN(Inputs!$D$62,MEDIAN(Data!$R$6:$R$39))),MAX(Inputs!$D$63,MIN(Inputs!$D$62,Data!R11))) -> 2.9557096 | T11: =IF(Data!S11="",MEDIAN(Data!$S$6:$S$39),Data!S11) -> 2.98038 | U11: =Pools!E11 -> 0.31003021 | V11: =Data!W11 -> 20 | W11: =Data!X11 -> 40 | X11: =IF($C11=1,100*(D11-_xlfn.MINIFS(D$6:D$39,$C$6:$C$39,1))/(_xlfn.MAXIFS(D$6:D$39,$C$6:$C$39,1)-_xlfn.MINIFS(D$6:D$39,$C$6:$C$39,1)),"") | Y11: =IF($C11=1,100*(E11-_xlfn.MINIFS(E$6:E$39,$C$6:$C$39,1))/(_xlfn.MAXIFS(E$6:E$39,$C$6:$C$39,1)-_xlfn.MINIFS(E$6:E$39,$C$6:$C$39,1)),"") | Z11: =IF($C11=1,100*(J11-_xlfn.MINIFS(J$6:J$39,$C$6:$C$39,1))/(_xlfn.MAXIFS(J$6:J$39,$C$6:$C$39,1)-_xlfn.MINIFS(J$6:J$39,$C$6:$C$39,1)),"") | AA11: =IF($C11=1,100*(L11-_xlfn.MINIFS(L$6:L$39,$C$6:$C$39,1))/(_xlfn.MAXIFS(L$6:L$39,$C$6:$C$39,1)-_xlfn.MINIFS(L$6:L$39,$C$6:$C$39,1)),"") | AB11: =IF($C11=1,100*(K11-_xlfn.MINIFS(K$6:K$39,$C$6:$C$39,1))/(_xlfn.MAXIFS(K$6:K$39,$C$6:$C$39,1)-_xlfn.MINIFS(K$6:K$39,$C$6:$C$39,1)),"") | AC11: =IF($C11=1,Inputs!$D$46*X11+Inputs!$D$47*Y11+Inputs!$D$48*Z11+Inputs!$D$49*AA11+Inputs!$D$50*AB11,"") | AD11: =IF($C11=1,100*(N11-_xlfn.MINIFS(N$6:N$39,$C$6:$C$39,1))/(_xlfn.MAXIFS(N$6:N$39,$C$6:$C$39,1)-_xlfn.MINIFS(N$6:N$39,$C$6:$C$39,1)),"") | AE11: =IF($C11=1,100*(O11-_xlfn.MINIFS(O$6:O$39,$C$6:$C$39,1))/(_xlfn.MAXIFS(O$6:O$39,$C$6:$C$39,1)-_xlfn.MINIFS(O$6:O$39,$C$6:$C$39,1)),"") | AF11: =IF($C11=1,100*(P11-_xlfn.MINIFS(P$6:P$39,$C$6:$C$39,1))/(_xlfn.MAXIFS(P$6:P$39,$C$6:$C$39,1)-_xlfn.MINIFS(P$6:P$39,$C$6:$C$39,1)),"") | AG11: =IF($C11=1,100*(Q11-_xlfn.MINIFS(Q$6:Q$39,$C$6:$C$39,1))/(_xlfn.MAXIFS(Q$6:Q$39,$C$6:$C$39,1)-_xlfn.MINIFS(Q$6:Q$39,$C$6:$C$39,1)),"") | AH11: =IF($C11=1,AVERAGE(AD11:AG11),"") | AI11: =IF($C11=1,100*(_xlfn.MAXIFS(R$6:R$39,$C$6:$C$39,1)-R11)/(_xlfn.MAXIFS(R$6:R$39,$C$6:$C$39,1)-_xlfn.MINIFS(R$6:R$39,$C$6:$C$39,1)),"") | AJ11: =IF($C11=1,100*(_xlfn.MAXIFS(S$6:S$39,$C$6:$C$39,1)-S11)/(_xlfn.MAXIFS(S$6:S$39,$C$6:$C$39,1)-_xlfn.MINIFS(S$6:S$39,$C$6:$C$39,1)),"") | AK11: =IF($C11=1,100*(T11-_xlfn.MINIFS(T$6:T$39,$C$6:$C$39,1))/(_xlfn.MAXIFS(T$6:T$39,$C$6:$C$39,1)-_xlfn.MINIFS(T$6:T$39,$C$6:$C$39,1)),"") | AL11: =IF($C11=1,AVERAGE(AI11:AK11),"") | AM11: =IF($C11=1,100*(U11-_xlfn.MINIFS(U$6:U$39,$C$6:$C$39,1))/(_xlfn.MAXIFS(U$6:U$39,$C$6:$C$39,1)-_xlfn.MINIFS(U$6:U$39,$C$6:$C$39,1)),"") | AN11: =IF($C11=1,100*(V11-_xlfn.MINIFS(V$6:V$39,$C$6:$C$39,1))/(_xlfn.MAXIFS(V$6:V$39,$C$6:$C$39,1)-_xlfn.MINIFS(V$6:V$39,$C$6:$C$39,1)),"") | AO11: =IF($C11=1,100*(M11-_xlfn.MINIFS(M$6:M$39,$C$6:$C$39,1))/(_xlfn.MAXIFS(M$6:M$39,$C$6:$C$39,1)-_xlfn.MINIFS(M$6:M$39,$C$6:$C$39,1)),"") | AP11: =IF($C11=1,W11,"") | AQ11: =IF($C11=1,Inputs!$D$52*AH11+Inputs!$D$53*AL11+Inputs!$D$54*AM11+Inputs!$D$55*AN11+Inputs!$D$56*AO11+Inputs!$D$57*AP11,"") | AR11: =IF($C11=1,SQRT(AC11*AQ11),"") | AS11: =IF($C11=1,COUNTIFS($C$6:$C$39,1,$AR$6:$AR$39,">"&AR11)+1,"") | AT11: =IF($C11=1,Inputs!$D$38+Inputs!$D$39*(1-AL11/100)+Inputs!$D$40*(1-AP11/100),"") | AU11: =IF($C11=1,IF(AC11>=MEDIAN(AC$6:AC$39),IF(AQ11>=MEDIAN(AQ$6:AQ$39),"Prioritise","Big but hard"),IF(AQ11>=MEDIAN(AQ$6:AQ$39),"Easy but small","Deprioritise")),"")
A12: =Data!A12 -> Congo, Dem. Rep. | B12: =Data!B12 -> COD | C12: =Data!AB12 -> 1 | D12: =LN(MAX(Pools!R12,0.000001)) -> 3.9196974 | E12: =Pools!U12 -> 0.13276605 | F12: =IF(Data!H12="","",MAX(0,(Inputs!$D$67-Data!H12)*100)) -> 48.344584 | G12: =IF(COUNT(Data!T12,Data!U12)=0,"",AVERAGE(Data!T12,Data!U12)) -> 16.617998 | H12: =IF(Data!O12="","",MIN(Inputs!$D$60,Data!O12)) -> 2.6424157 | I12: =IF(Data!I12="","",(Data!E12-Data!I12)*100) -> 19.021898 | J12: =IF(F12="",MEDIAN(F$6:F$39),F12) -> 48.344584 | K12: =IF(G12="",MEDIAN(G$6:G$39),G12) -> 16.617998 | L12: =IF(H12="",MEDIAN(H$6:H$39),H12) -> 2.6424157 | M12: =IF(I12="",MEDIAN(I$6:I$39),I12) -> 19.021898 | N12: =IF(Data!L12="",MIN(Inputs!$D$59,MEDIAN(Data!$L$6:$L$39)),MIN(Inputs!$D$59,Data!L12)) -> 58.532153 | O12: =IF(Data!M12="",MEDIAN(Data!$M$6:$M$39),Data!M12) -> 19.6735 | P12: =IF(Data!N12="",MEDIAN(Data!$N$6:$N$39),Data!N12) -> 22.5 | Q12: =IF(Data!K12="",MEDIAN(Data!$K$6:$K$39),Data!K12) -> 44.74558 | R12: =IF(Data!Q12="",MIN(Inputs!$D$61,MEDIAN(Data!$Q$6:$Q$39)),MIN(Inputs!$D$61,Data!Q12)) -> 6.7567525 | S12: =IF(Data!R12="",MAX(Inputs!$D$63,MIN(Inputs!$D$62,MEDIAN(Data!$R$6:$R$39))),MAX(Inputs!$D$63,MIN(Inputs!$D$62,Data!R12))) -> 8.1168694 | T12: =IF(Data!S12="",MEDIAN(Data!$S$6:$S$39),Data!S12) -> 7.9823962 | U12: =Pools!E12 -> 0.89555334 | V12: =Data!W12 -> 100 | W12: =Data!X12 -> 0 | X12: =IF($C12=1,100*(D12-_xlfn.MINIFS(D$6:D$39,$C$6:$C$39,1))/(_xlfn.MAXIFS(D$6:D$39,$C$6:$C$39,1)-_xlfn.MINIFS(D$6:D$39,$C$6:$C$39,1)),"") -> 81.249499 | Y12: =IF($C12=1,100*(E12-_xlfn.MINIFS(E$6:E$39,$C$6:$C$39,1))/(_xlfn.MAXIFS(E$6:E$39,$C$6:$C$39,1)-_xlfn.MINIFS(E$6:E$39,$C$6:$C$39,1)),"") -> 51.946979 | Z12: =IF($C12=1,100*(J12-_xlfn.MINIFS(J$6:J$39,$C$6:$C$39,1))/(_xlfn.MAXIFS(J$6:J$39,$C$6:$C$39,1)-_xlfn.MINIFS(J$6:J$39,$C$6:$C$39,1)),"") -> 88.778616 | AA12: =IF($C12=1,100*(L12-_xlfn.MINIFS(L$6:L$39,$C$6:$C$39,1))/(_xlfn.MAXIFS(L$6:L$39,$C$6:$C$39,1)-_xlfn.MINIFS(L$6:L$39,$C$6:$C$39,1)),"") -> 16.428084 | AB12: =IF($C12=1,100*(K12-_xlfn.MINIFS(K$6:K$39,$C$6:$C$39,1))/(_xlfn.MAXIFS(K$6:K$39,$C$6:$C$39,1)-_xlfn.MINIFS(K$6:K$39,$C$6:$C$39,1)),"") -> 61.190843 | AC12: =IF($C12=1,Inputs!$D$46*X12+Inputs!$D$47*Y12+Inputs!$D$48*Z12+Inputs!$D$49*AA12+Inputs!$D$50*AB12,"") -> 63.786352 | AD12: =IF($C12=1,100*(N12-_xlfn.MINIFS(N$6:N$39,$C$6:$C$39,1))/(_xlfn.MAXIFS(N$6:N$39,$C$6:$C$39,1)-_xlfn.MINIFS(N$6:N$39,$C$6:$C$39,1)),"") -> 30.099426 | AE12: =IF($C12=1,100*(O12-_xlfn.MINIFS(O$6:O$39,$C$6:$C$39,1))/(_xlfn.MAXIFS(O$6:O$39,$C$6:$C$39,1)-_xlfn.MINIFS(O$6:O$39,$C$6:$C$39,1)),"") -> 15.450244 | AF12: =IF($C12=1,100*(P12-_xlfn.MINIFS(P$6:P$39,$C$6:$C$39,1))/(_xlfn.MAXIFS(P$6:P$39,$C$6:$C$39,1)-_xlfn.MINIFS(P$6:P$39,$C$6:$C$39,1)),"") -> 11.592357 | AG12: =IF($C12=1,100*(Q12-_xlfn.MINIFS(Q$6:Q$39,$C$6:$C$39,1))/(_xlfn.MAXIFS(Q$6:Q$39,$C$6:$C$39,1)-_xlfn.MINIFS(Q$6:Q$39,$C$6:$C$39,1)),"") -> 58.940781 | AH12: =IF($C12=1,AVERAGE(AD12:AG12),"") -> 29.020702 | AI12: =IF($C12=1,100*(_xlfn.MAXIFS(R$6:R$39,$C$6:$C$39,1)-R12)/(_xlfn.MAXIFS(R$6:R$39,$C$6:$C$39,1)-_xlfn.MINIFS(R$6:R$39,$C$6:$C$39,1)),"") -> 86.910762 | AJ12: =IF($C12=1,100*(_xlfn.MAXIFS(S$6:S$39,$C$6:$C$39,1)-S12)/(_xlfn.MAXIFS(S$6:S$39,$C$6:$C$39,1)-_xlfn.MINIFS(S$6:S$39,$C$6:$C$39,1)),"") -> 78.137392 | AK12: =IF($C12=1,100*(T12-_xlfn.MINIFS(T$6:T$39,$C$6:$C$39,1))/(_xlfn.MAXIFS(T$6:T$39,$C$6:$C$39,1)-_xlfn.MINIFS(T$6:T$39,$C$6:$C$39,1)),"") -> 100 | AL12: =IF($C12=1,AVERAGE(AI12:AK12),"") -> 88.349385 | AM12: =IF($C12=1,100*(U12-_xlfn.MINIFS(U$6:U$39,$C$6:$C$39,1))/(_xlfn.MAXIFS(U$6:U$39,$C$6:$C$39,1)-_xlfn.MINIFS(U$6:U$39,$C$6:$C$39,1)),"") -> 91.168889 | AN12: =IF($C12=1,100*(V12-_xlfn.MINIFS(V$6:V$39,$C$6:$C$39,1))/(_xlfn.MAXIFS(V$6:V$39,$C$6:$C$39,1)-_xlfn.MINIFS(V$6:V$39,$C$6:$C$39,1)),"") -> 100 | AO12: =IF($C12=1,100*(M12-_xlfn.MINIFS(M$6:M$39,$C$6:$C$39,1))/(_xlfn.MAXIFS(M$6:M$39,$C$6:$C$39,1)-_xlfn.MINIFS(M$6:M$39,$C$6:$C$39,1)),"") -> 47.964584 | AP12: =IF($C12=1,W12,"") -> 0 | AQ12: =IF($C12=1,Inputs!$D$52*AH12+Inputs!$D$53*AL12+Inputs!$D$54*AM12+Inputs!$D$55*AN12+Inputs!$D$56*AO12+Inputs!$D$57*AP12,"") -> 56.945809 | AR12: =IF($C12=1,SQRT(AC12*AQ12),"") -> 60.269108 | AS12: =IF($C12=1,COUNTIFS($C$6:$C$39,1,$AR$6:$AR$39,">"&AR12)+1,"") -> 4 | AT12: =IF($C12=1,Inputs!$D$38+Inputs!$D$39*(1-AL12/100)+Inputs!$D$40*(1-AP12/100),"") -> 0.16466025 | AU12: =IF($C12=1,IF(AC12>=MEDIAN(AC$6:AC$39),IF(AQ12>=MEDIAN(AQ$6:AQ$39),"Prioritise","Big but hard"),IF(AQ12>=MEDIAN(AQ$6:AQ$39),"Easy but small","Deprioritise")),"") -> Big but hard
A13: =Data!A13 -> Congo, Rep. | B13: =Data!B13 -> COG | C13: =Data!AB13 -> 1 | D13: =LN(MAX(Pools!R13,0.000001)) -> 1.666881 | E13: =Pools!U13 -> 0.091542609 | F13: =IF(Data!H13="","",MAX(0,(Inputs!$D$67-Data!H13)*100)) -> 45.831267 | G13: =IF(COUNT(Data!T13,Data!U13)=0,"",AVERAGE(Data!T13,Data!U13)) -> 13.590038 | H13: =IF(Data!O13="","",MIN(Inputs!$D$60,Data!O13)) | I13: =IF(Data!I13="","",(Data!E13-Data!I13)*100) -> 45.353679 | J13: =IF(F13="",MEDIAN(F$6:F$39),F13) -> 45.831267 | K13: =IF(G13="",MEDIAN(G$6:G$39),G13) -> 13.590038 | L13: =IF(H13="",MEDIAN(H$6:H$39),H13) -> 2.6075828 | M13: =IF(I13="",MEDIAN(I$6:I$39),I13) -> 45.353679 | N13: =IF(Data!L13="",MIN(Inputs!$D$59,MEDIAN(Data!$L$6:$L$39)),MIN(Inputs!$D$59,Data!L13)) -> 95.531932 | O13: =IF(Data!M13="",MEDIAN(Data!$M$6:$M$39),Data!M13) -> 47.251598 | P13: =IF(Data!N13="",MEDIAN(Data!$N$6:$N$39),Data!N13) -> 53 | Q13: =IF(Data!K13="",MEDIAN(Data!$K$6:$K$39),Data!K13) -> 63.886611 | R13: =IF(Data!Q13="",MIN(Inputs!$D$61,MEDIAN(Data!$Q$6:$Q$39)),MIN(Inputs!$D$61,Data!Q13)) -> 3.4788751 | S13: =IF(Data!R13="",MAX(Inputs!$D$63,MIN(Inputs!$D$62,MEDIAN(Data!$R$6:$R$39))),MAX(Inputs!$D$63,MIN(Inputs!$D$62,Data!R13))) -> 2.9775832 | T13: =IF(Data!S13="",MEDIAN(Data!$S$6:$S$39),Data!S13) -> 1.8274032 | U13: =Pools!E13 -> 0.92831585 | V13: =Data!W13 -> 20 | W13: =Data!X13 -> 40 | X13: =IF($C13=1,100*(D13-_xlfn.MINIFS(D$6:D$39,$C$6:$C$39,1))/(_xlfn.MAXIFS(D$6:D$39,$C$6:$C$39,1)-_xlfn.MINIFS(D$6:D$39,$C$6:$C$39,1)),"") -> 26.964436 | Y13: =IF($C13=1,100*(E13-_xlfn.MINIFS(E$6:E$39,$C$6:$C$39,1))/(_xlfn.MAXIFS(E$6:E$39,$C$6:$C$39,1)-_xlfn.MINIFS(E$6:E$39,$C$6:$C$39,1)),"") -> 27.473948 | Z13: =IF($C13=1,100*(J13-_xlfn.MINIFS(J$6:J$39,$C$6:$C$39,1))/(_xlfn.MAXIFS(J$6:J$39,$C$6:$C$39,1)-_xlfn.MINIFS(J$6:J$39,$C$6:$C$39,1)),"") -> 83.13156 | AA13: =IF($C13=1,100*(L13-_xlfn.MINIFS(L$6:L$39,$C$6:$C$39,1))/(_xlfn.MAXIFS(L$6:L$39,$C$6:$C$39,1)-_xlfn.MINIFS(L$6:L$39,$C$6:$C$39,1)),"") -> 16.192516 | AB13: =IF($C13=1,100*(K13-_xlfn.MINIFS(K$6:K$39,$C$6:$C$39,1))/(_xlfn.MAXIFS(K$6:K$39,$C$6:$C$39,1)-_xlfn.MINIFS(K$6:K$39,$C$6:$C$39,1)),"") -> 47.444744 | AC13: =IF($C13=1,Inputs!$D$46*X13+Inputs!$D$47*Y13+Inputs!$D$48*Z13+Inputs!$D$49*AA13+Inputs!$D$50*AB13,"") -> 36.947665 | AD13: =IF($C13=1,100*(N13-_xlfn.MINIFS(N$6:N$39,$C$6:$C$39,1))/(_xlfn.MAXIFS(N$6:N$39,$C$6:$C$39,1)-_xlfn.MINIFS(N$6:N$39,$C$6:$C$39,1)),"") -> 72.175176 | AE13: =IF($C13=1,100*(O13-_xlfn.MINIFS(O$6:O$39,$C$6:$C$39,1))/(_xlfn.MAXIFS(O$6:O$39,$C$6:$C$39,1)-_xlfn.MINIFS(O$6:O$39,$C$6:$C$39,1)),"") -> 55.183691 | AF13: =IF($C13=1,100*(P13-_xlfn.MINIFS(P$6:P$39,$C$6:$C$39,1))/(_xlfn.MAXIFS(P$6:P$39,$C$6:$C$39,1)-_xlfn.MINIFS(P$6:P$39,$C$6:$C$39,1)),"") -> 50.44586 | AG13: =IF($C13=1,100*(Q13-_xlfn.MINIFS(Q$6:Q$39,$C$6:$C$39,1))/(_xlfn.MAXIFS(Q$6:Q$39,$C$6:$C$39,1)-_xlfn.MINIFS(Q$6:Q$39,$C$6:$C$39,1)),"") -> 100 | AH13: =IF($C13=1,AVERAGE(AD13:AG13),"") -> 69.451182 | AI13: =IF($C13=1,100*(_xlfn.MAXIFS(R$6:R$39,$C$6:$C$39,1)-R13)/(_xlfn.MAXIFS(R$6:R$39,$C$6:$C$39,1)-_xlfn.MINIFS(R$6:R$39,$C$6:$C$39,1)),"") -> 95.480407 | AJ13: =IF($C13=1,100*(_xlfn.MAXIFS(S$6:S$39,$C$6:$C$39,1)-S13)/(_xlfn.MAXIFS(S$6:S$39,$C$6:$C$39,1)-_xlfn.MINIFS(S$6:S$39,$C$6:$C$39,1)),"") -> 90.732467 | AK13: =IF($C13=1,100*(T13-_xlfn.MINIFS(T$6:T$39,$C$6:$C$39,1))/(_xlfn.MAXIFS(T$6:T$39,$C$6:$C$39,1)-_xlfn.MINIFS(T$6:T$39,$C$6:$C$39,1)),"") -> 10.137796 | AL13: =IF($C13=1,AVERAGE(AI13:AK13),"") -> 65.450223 | AM13: =IF($C13=1,100*(U13-_xlfn.MINIFS(U$6:U$39,$C$6:$C$39,1))/(_xlfn.MAXIFS(U$6:U$39,$C$6:$C$39,1)-_xlfn.MINIFS(U$6:U$39,$C$6:$C$39,1)),"") -> 95.424214 | AN13: =IF($C13=1,100*(V13-_xlfn.MINIFS(V$6:V$39,$C$6:$C$39,1))/(_xlfn.MAXIFS(V$6:V$39,$C$6:$C$39,1)-_xlfn.MINIFS(V$6:V$39,$C$6:$C$39,1)),"") -> 0 | AO13: =IF($C13=1,100*(M13-_xlfn.MINIFS(M$6:M$39,$C$6:$C$39,1))/(_xlfn.MAXIFS(M$6:M$39,$C$6:$C$39,1)-_xlfn.MINIFS(M$6:M$39,$C$6:$C$39,1)),"") -> 100 | AP13: =IF($C13=1,W13,"") -> 40 | AQ13: =IF($C13=1,Inputs!$D$52*AH13+Inputs!$D$53*AL13+Inputs!$D$54*AM13+Inputs!$D$55*AN13+Inputs!$D$56*AO13+Inputs!$D$57*AP13,"") -> 59.293913 | AR13: =IF($C13=1,SQRT(AC13*AQ13),"") -> 46.80568 | AS13: =IF($C13=1,COUNTIFS($C$6:$C$39,1,$AR$6:$AR$39,">"&AR13)+1,"") -> 19 | AT13: =IF($C13=1,Inputs!$D$38+Inputs!$D$39*(1-AL13/100)+Inputs!$D$40*(1-AP13/100),"") -> 0.15781991 | AU13: =IF($C13=1,IF(AC13>=MEDIAN(AC$6:AC$39),IF(AQ13>=MEDIAN(AQ$6:AQ$39),"Prioritise","Big but hard"),IF(AQ13>=MEDIAN(AQ$6:AQ$39),"Easy but small","Deprioritise")),"") -> Easy but small
A14: =Data!A14 -> Cote d'Ivoire | B14: =Data!B14 -> CIV | C14: =Data!AB14 -> 1 | D14: =LN(MAX(Pools!R14,0.000001)) -> 3.3071892 | E14: =Pools!U14 -> 0.088834376 | F14: =IF(Data!H14="","",MAX(0,(Inputs!$D$67-Data!H14)*100)) -> 46.597399 | G14: =IF(COUNT(Data!T14,Data!U14)=0,"",AVERAGE(Data!T14,Data!U14)) -> 15.424251 | H14: =IF(Data!O14="","",MIN(Inputs!$D$60,Data!O14)) -> 2.0327233 | I14: =IF(Data!I14="","",(Data!E14-Data!I14)*100) -> 19.328605 | J14: =IF(F14="",MEDIAN(F$6:F$39),F14) -> 46.597399 | K14: =IF(G14="",MEDIAN(G$6:G$39),G14) -> 15.424251 | L14: =IF(H14="",MEDIAN(H$6:H$39),H14) -> 2.0327233 | M14: =IF(I14="",MEDIAN(I$6:I$39),I14) -> 19.328605 | N14: =IF(Data!L14="",MIN(Inputs!$D$59,MEDIAN(Data!$L$6:$L$39)),MIN(Inputs!$D$59,Data!L14)) -> 120 | O14: =IF(Data!M14="",MEDIAN(Data!$M$6:$M$39),Data!M14) -> 41.432199 | P14: =IF(Data!N14="",MEDIAN(Data!$N$6:$N$39),Data!N14) -> 72.9 | Q14: =IF(Data!K14="",MEDIAN(Data!$K$6:$K$39),Data!K14) -> 53.973311 | R14: =IF(Data!Q14="",MIN(Inputs!$D$61,MEDIAN(Data!$Q$6:$Q$39)),MIN(Inputs!$D$61,Data!Q14)) -> 4.3512605 | S14: =IF(Data!R14="",MAX(Inputs!$D$63,MIN(Inputs!$D$62,MEDIAN(Data!$R$6:$R$39))),MAX(Inputs!$D$63,MIN(Inputs!$D$62,Data!R14))) -> 2.9775832 | T14: =IF(Data!S14="",MEDIAN(Data!$S$6:$S$39),Data!S14) -> 6.3398062 | U14: =Pools!E14 -> 0.92728816 | V14: =Data!W14 -> 20 | W14: =Data!X14 -> 100 | X14: =IF($C14=1,100*(D14-_xlfn.MINIFS(D$6:D$39,$C$6:$C$39,1))/(_xlfn.MAXIFS(D$6:D$39,$C$6:$C$39,1)-_xlfn.MINIFS(D$6:D$39,$C$6:$C$39,1)),"") -> 66.490174 | Y14: =IF($C14=1,100*(E14-_xlfn.MINIFS(E$6:E$39,$C$6:$C$39,1))/(_xlfn.MAXIFS(E$6:E$39,$C$6:$C$39,1)-_xlfn.MINIFS(E$6:E$39,$C$6:$C$39,1)),"") -> 25.866158 | Z14: =IF($C14=1,100*(J14-_xlfn.MINIFS(J$6:J$39,$C$6:$C$39,1))/(_xlfn.MAXIFS(J$6:J$39,$C$6:$C$39,1)-_xlfn.MINIFS(J$6:J$39,$C$6:$C$39,1)),"") -> 84.852946 | AA14: =IF($C14=1,100*(L14-_xlfn.MINIFS(L$6:L$39,$C$6:$C$39,1))/(_xlfn.MAXIFS(L$6:L$39,$C$6:$C$39,1)-_xlfn.MINIFS(L$6:L$39,$C$6:$C$39,1)),"") -> 12.304854 | AB14: =IF($C14=1,100*(K14-_xlfn.MINIFS(K$6:K$39,$C$6:$C$39,1))/(_xlfn.MAXIFS(K$6:K$39,$C$6:$C$39,1)-_xlfn.MINIFS(K$6:K$39,$C$6:$C$39,1)),"") -> 55.771561 | AC14: =IF($C14=1,Inputs!$D$46*X14+Inputs!$D$47*Y14+Inputs!$D$48*Z14+Inputs!$D$49*AA14+Inputs!$D$50*AB14,"") -> 51.384197 | AD14: =IF($C14=1,100*(N14-_xlfn.MINIFS(N$6:N$39,$C$6:$C$39,1))/(_xlfn.MAXIFS(N$6:N$39,$C$6:$C$39,1)-_xlfn.MINIFS(N$6:N$39,$C$6:$C$39,1)),"") -> 100 | AE14: =IF($C14=1,100*(O14-_xlfn.MINIFS(O$6:O$39,$C$6:$C$39,1))/(_xlfn.MAXIFS(O$6:O$39,$C$6:$C$39,1)-_xlfn.MINIFS(O$6:O$39,$C$6:$C$39,1)),"") -> 46.799328 | AF14: =IF($C14=1,100*(P14-_xlfn.MINIFS(P$6:P$39,$C$6:$C$39,1))/(_xlfn.MAXIFS(P$6:P$39,$C$6:$C$39,1)-_xlfn.MINIFS(P$6:P$39,$C$6:$C$39,1)),"") -> 75.796178 | AG14: =IF($C14=1,100*(Q14-_xlfn.MINIFS(Q$6:Q$39,$C$6:$C$39,1))/(_xlfn.MAXIFS(Q$6:Q$39,$C$6:$C$39,1)-_xlfn.MINIFS(Q$6:Q$39,$C$6:$C$39,1)),"") -> 78.735088 | AH14: =IF($C14=1,AVERAGE(AD14:AG14),"") -> 75.332648 | AI14: =IF($C14=1,100*(_xlfn.MAXIFS(R$6:R$39,$C$6:$C$39,1)-R14)/(_xlfn.MAXIFS(R$6:R$39,$C$6:$C$39,1)-_xlfn.MINIFS(R$6:R$39,$C$6:$C$39,1)),"") -> 93.199652 | AJ14: =IF($C14=1,100*(_xlfn.MAXIFS(S$6:S$39,$C$6:$C$39,1)-S14)/(_xlfn.MAXIFS(S$6:S$39,$C$6:$C$39,1)-_xlfn.MINIFS(S$6:S$39,$C$6:$C$39,1)),"") -> 90.732467 | AK14: =IF($C14=1,100*(T14-_xlfn.MINIFS(T$6:T$39,$C$6:$C$39,1))/(_xlfn.MAXIFS(T$6:T$39,$C$6:$C$39,1)-_xlfn.MINIFS(T$6:T$39,$C$6:$C$39,1)),"") -> 76.018371 | AL14: =IF($C14=1,AVERAGE(AI14:AK14),"") -> 86.650164 | AM14: =IF($C14=1,100*(U14-_xlfn.MINIFS(U$6:U$39,$C$6:$C$39,1))/(_xlfn.MAXIFS(U$6:U$39,$C$6:$C$39,1)-_xlfn.MINIFS(U$6:U$39,$C$6:$C$39,1)),"") -> 95.290734 | AN14: =IF($C14=1,100*(V14-_xlfn.MINIFS(V$6:V$39,$C$6:$C$39,1))/(_xlfn.MAXIFS(V$6:V$39,$C$6:$C$39,1)-_xlfn.MINIFS(V$6:V$39,$C$6:$C$39,1)),"") -> 0 | AO14: =IF($C14=1,100*(M14-_xlfn.MINIFS(M$6:M$39,$C$6:$C$39,1))/(_xlfn.MAXIFS(M$6:M$39,$C$6:$C$39,1)-_xlfn.MINIFS(M$6:M$39,$C$6:$C$39,1)),"") -> 48.570681 | AP14: =IF($C14=1,W14,"") -> 100 | AQ14: =IF($C14=1,Inputs!$D$52*AH14+Inputs!$D$53*AL14+Inputs!$D$54*AM14+Inputs!$D$55*AN14+Inputs!$D$56*AO14+Inputs!$D$57*AP14,"") -> 71.547241 | AR14: =IF($C14=1,SQRT(AC14*AQ14),"") -> 60.633303 | AS14: =IF($C14=1,COUNTIFS($C$6:$C$39,1,$AR$6:$AR$39,">"&AR14)+1,"") -> 2 | AT14: =IF($C14=1,Inputs!$D$38+Inputs!$D$39*(1-AL14/100)+Inputs!$D$40*(1-AP14/100),"") -> 0.12533993 | AU14: =IF($C14=1,IF(AC14>=MEDIAN(AC$6:AC$39),IF(AQ14>=MEDIAN(AQ$6:AQ$39),"Prioritise","Big but hard"),IF(AQ14>=MEDIAN(AQ$6:AQ$39),"Easy but small","Deprioritise")),"") -> Prioritise
A15: =Data!A15 -> Eswatini | B15: =Data!B15 -> SWZ | C15: =Data!AB15 -> 0 | D15: =LN(MAX(Pools!R15,0.000001)) -> 0.088424575 | E15: =Pools!U15 -> 0.078659851 | F15: =IF(Data!H15="","",MAX(0,(Inputs!$D$67-Data!H15)*100)) -> 37.590125 | G15: =IF(COUNT(Data!T15,Data!U15)=0,"",AVERAGE(Data!T15,Data!U15)) -> 10.729002 | H15: =IF(Data!O15="","",MIN(Inputs!$D$60,Data!O15)) -> 0.68629089 | I15: =IF(Data!I15="","",(Data!E15-Data!I15)*100) | J15: =IF(F15="",MEDIAN(F$6:F$39),F15) -> 37.590125 | K15: =IF(G15="",MEDIAN(G$6:G$39),G15) -> 10.729002 | L15: =IF(H15="",MEDIAN(H$6:H$39),H15) -> 0.68629089 | M15: =IF(I15="",MEDIAN(I$6:I$39),I15) -> 19.328605 | N15: =IF(Data!L15="",MIN(Inputs!$D$59,MEDIAN(Data!$L$6:$L$39)),MIN(Inputs!$D$59,Data!L15)) -> 120 | O15: =IF(Data!M15="",MEDIAN(Data!$M$6:$M$39),Data!M15) -> 63.403099 | P15: =IF(Data!N15="",MEDIAN(Data!$N$6:$N$39),Data!N15) -> 89.3 | Q15: =IF(Data!K15="",MEDIAN(Data!$K$6:$K$39),Data!K15) -> 26.249846 | R15: =IF(Data!Q15="",MIN(Inputs!$D$61,MEDIAN(Data!$Q$6:$Q$39)),MIN(Inputs!$D$61,Data!Q15)) -> 6.7567525 | S15: =IF(Data!R15="",MAX(Inputs!$D$63,MIN(Inputs!$D$62,MEDIAN(Data!$R$6:$R$39))),MAX(Inputs!$D$63,MIN(Inputs!$D$62,Data!R15))) -> 7.145326 | T15: =IF(Data!S15="",MEDIAN(Data!$S$6:$S$39),Data!S15) -> 2.3167574 | U15: =Pools!E15 -> 0.77410923 | V15: =Data!W15 -> 20 | W15: =Data!X15 -> 100 | X15: =IF($C15=1,100*(D15-_xlfn.MINIFS(D$6:D$39,$C$6:$C$39,1))/(_xlfn.MAXIFS(D$6:D$39,$C$6:$C$39,1)-_xlfn.MINIFS(D$6:D$39,$C$6:$C$39,1)),"") | Y15: =IF($C15=1,100*(E15-_xlfn.MINIFS(E$6:E$39,$C$6:$C$39,1))/(_xlfn.MAXIFS(E$6:E$39,$C$6:$C$39,1)-_xlfn.MINIFS(E$6:E$39,$C$6:$C$39,1)),"") | Z15: =IF($C15=1,100*(J15-_xlfn.MINIFS(J$6:J$39,$C$6:$C$39,1))/(_xlfn.MAXIFS(J$6:J$39,$C$6:$C$39,1)-_xlfn.MINIFS(J$6:J$39,$C$6:$C$39,1)),"") | AA15: =IF($C15=1,100*(L15-_xlfn.MINIFS(L$6:L$39,$C$6:$C$39,1))/(_xlfn.MAXIFS(L$6:L$39,$C$6:$C$39,1)-_xlfn.MINIFS(L$6:L$39,$C$6:$C$39,1)),"") | AB15: =IF($C15=1,100*(K15-_xlfn.MINIFS(K$6:K$39,$C$6:$C$39,1))/(_xlfn.MAXIFS(K$6:K$39,$C$6:$C$39,1)-_xlfn.MINIFS(K$6:K$39,$C$6:$C$39,1)),"") | AC15: =IF($C15=1,Inputs!$D$46*X15+Inputs!$D$47*Y15+Inputs!$D$48*Z15+Inputs!$D$49*AA15+Inputs!$D$50*AB15,"") | AD15: =IF($C15=1,100*(N15-_xlfn.MINIFS(N$6:N$39,$C$6:$C$39,1))/(_xlfn.MAXIFS(N$6:N$39,$C$6:$C$39,1)-_xlfn.MINIFS(N$6:N$39,$C$6:$C$39,1)),"") | AE15: =IF($C15=1,100*(O15-_xlfn.MINIFS(O$6:O$39,$C$6:$C$39,1))/(_xlfn.MAXIFS(O$6:O$39,$C$6:$C$39,1)-_xlfn.MINIFS(O$6:O$39,$C$6:$C$39,1)),"") | AF15: =IF($C15=1,100*(P15-_xlfn.MINIFS(P$6:P$39,$C$6:$C$39,1))/(_xlfn.MAXIFS(P$6:P$39,$C$6:$C$39,1)-_xlfn.MINIFS(P$6:P$39,$C$6:$C$39,1)),"") | AG15: =IF($C15=1,100*(Q15-_xlfn.MINIFS(Q$6:Q$39,$C$6:$C$39,1))/(_xlfn.MAXIFS(Q$6:Q$39,$C$6:$C$39,1)-_xlfn.MINIFS(Q$6:Q$39,$C$6:$C$39,1)),"") | AH15: =IF($C15=1,AVERAGE(AD15:AG15),"") | AI15: =IF($C15=1,100*(_xlfn.MAXIFS(R$6:R$39,$C$6:$C$39,1)-R15)/(_xlfn.MAXIFS(R$6:R$39,$C$6:$C$39,1)-_xlfn.MINIFS(R$6:R$39,$C$6:$C$39,1)),"") | AJ15: =IF($C15=1,100*(_xlfn.MAXIFS(S$6:S$39,$C$6:$C$39,1)-S15)/(_xlfn.MAXIFS(S$6:S$39,$C$6:$C$39,1)-_xlfn.MINIFS(S$6:S$39,$C$6:$C$39,1)),"") | AK15: =IF($C15=1,100*(T15-_xlfn.MINIFS(T$6:T$39,$C$6:$C$39,1))/(_xlfn.MAXIFS(T$6:T$39,$C$6:$C$39,1)-_xlfn.MINIFS(T$6:T$39,$C$6:$C$39,1)),"") | AL15: =IF($C15=1,AVERAGE(AI15:AK15),"") | AM15: =IF($C15=1,100*(U15-_xlfn.MINIFS(U$6:U$39,$C$6:$C$39,1))/(_xlfn.MAXIFS(U$6:U$39,$C$6:$C$39,1)-_xlfn.MINIFS(U$6:U$39,$C$6:$C$39,1)),"") | AN15: =IF($C15=1,100*(V15-_xlfn.MINIFS(V$6:V$39,$C$6:$C$39,1))/(_xlfn.MAXIFS(V$6:V$39,$C$6:$C$39,1)-_xlfn.MINIFS(V$6:V$39,$C$6:$C$39,1)),"") | AO15: =IF($C15=1,100*(M15-_xlfn.MINIFS(M$6:M$39,$C$6:$C$39,1))/(_xlfn.MAXIFS(M$6:M$39,$C$6:$C$39,1)-_xlfn.MINIFS(M$6:M$39,$C$6:$C$39,1)),"") | AP15: =IF($C15=1,W15,"") | AQ15: =IF($C15=1,Inputs!$D$52*AH15+Inputs!$D$53*AL15+Inputs!$D$54*AM15+Inputs!$D$55*AN15+Inputs!$D$56*AO15+Inputs!$D$57*AP15,"") | AR15: =IF($C15=1,SQRT(AC15*AQ15),"") | AS15: =IF($C15=1,COUNTIFS($C$6:$C$39,1,$AR$6:$AR$39,">"&AR15)+1,"") | AT15: =IF($C15=1,Inputs!$D$38+Inputs!$D$39*(1-AL15/100)+Inputs!$D$40*(1-AP15/100),"") | AU15: =IF($C15=1,IF(AC15>=MEDIAN(AC$6:AC$39),IF(AQ15>=MEDIAN(AQ$6:AQ$39),"Prioritise","Big but hard"),IF(AQ15>=MEDIAN(AQ$6:AQ$39),"Easy but small","Deprioritise")),"")
A16: =Data!A16 -> Ethiopia | B16: =Data!B16 -> ETH | C16: =Data!AB16 -> 1 | D16: =LN(MAX(Pools!R16,0.000001)) -> 2.3554556 | E16: =Pools!U16 -> 0.19291684 | F16: =IF(Data!H16="","",MAX(0,(Inputs!$D$67-Data!H16)*100)) -> 49.846145 | G16: =IF(COUNT(Data!T16,Data!U16)=0,"",AVERAGE(Data!T16,Data!U16)) | H16: =IF(Data!O16="","",MIN(Inputs!$D$60,Data!O16)) -> 4.7667108 | I16: =IF(Data!I16="","",(Data!E16-Data!I16)*100) -> 9.1389607 | J16: =IF(F16="",MEDIAN(F$6:F$39),F16) -> 49.846145 | K16: =IF(G16="",MEDIAN(G$6:G$39),G16) -> 13.283725 | L16: =IF(H16="",MEDIAN(H$6:H$39),H16) -> 4.7667108 | M16: =IF(I16="",MEDIAN(I$6:I$39),I16) -> 9.1389607 | N16: =IF(Data!L16="",MIN(Inputs!$D$59,MEDIAN(Data!$L$6:$L$39)),MIN(Inputs!$D$59,Data!L16)) -> 65.082509 | O16: =IF(Data!M16="",MEDIAN(Data!$M$6:$M$39),Data!M16) -> 21.941299 | P16: =IF(Data!N16="",MEDIAN(Data!$N$6:$N$39),Data!N16) -> 56.6 | Q16: =IF(Data!K16="",MEDIAN(Data!$K$6:$K$39),Data!K16) -> 23.622284 | R16: =IF(Data!Q16="",MIN(Inputs!$D$61,MEDIAN(Data!$Q$6:$Q$39)),MIN(Inputs!$D$61,Data!Q16)) -> 28.382151 | S16: =IF(Data!R16="",MAX(Inputs!$D$63,MIN(Inputs!$D$62,MEDIAN(Data!$R$6:$R$39))),MAX(Inputs!$D$63,MIN(Inputs!$D$62,Data!R16))) -> 21.196837 | T16: =IF(Data!S16="",MEDIAN(Data!$S$6:$S$39),Data!S16) -> 6.5095935 | U16: =Pools!E16 -> 0.19362761 | V16: =Data!W16 -> 60 | W16: =Data!X16 -> 0 | X16: =IF($C16=1,100*(D16-_xlfn.MINIFS(D$6:D$39,$C$6:$C$39,1))/(_xlfn.MAXIFS(D$6:D$39,$C$6:$C$39,1)-_xlfn.MINIFS(D$6:D$39,$C$6:$C$39,1)),"") -> 43.556694 | Y16: =IF($C16=1,100*(E16-_xlfn.MINIFS(E$6:E$39,$C$6:$C$39,1))/(_xlfn.MAXIFS(E$6:E$39,$C$6:$C$39,1)-_xlfn.MINIFS(E$6:E$39,$C$6:$C$39,1)),"") -> 87.65657 | Z16: =IF($C16=1,100*(J16-_xlfn.MINIFS(J$6:J$39,$C$6:$C$39,1))/(_xlfn.MAXIFS(J$6:J$39,$C$6:$C$39,1)-_xlfn.MINIFS(J$6:J$39,$C$6:$C$39,1)),"") -> 92.152403 | AA16: =IF($C16=1,100*(L16-_xlfn.MINIFS(L$6:L$39,$C$6:$C$39,1))/(_xlfn.MAXIFS(L$6:L$39,$C$6:$C$39,1)-_xlfn.MINIFS(L$6:L$39,$C$6:$C$39,1)),"") -> 30.794275 | AB16: =IF($C16=1,100*(K16-_xlfn.MINIFS(K$6:K$39,$C$6:$C$39,1))/(_xlfn.MAXIFS(K$6:K$39,$C$6:$C$39,1)-_xlfn.MINIFS(K$6:K$39,$C$6:$C$39,1)),"") -> 46.054164 | AC16: =IF($C16=1,Inputs!$D$46*X16+Inputs!$D$47*Y16+Inputs!$D$48*Z16+Inputs!$D$49*AA16+Inputs!$D$50*AB16,"") -> 58.126283 | AD16: =IF($C16=1,100*(N16-_xlfn.MINIFS(N$6:N$39,$C$6:$C$39,1))/(_xlfn.MAXIFS(N$6:N$39,$C$6:$C$39,1)-_xlfn.MINIFS(N$6:N$39,$C$6:$C$39,1)),"") -> 37.54842 | AE16: =IF($C16=1,100*(O16-_xlfn.MINIFS(O$6:O$39,$C$6:$C$39,1))/(_xlfn.MAXIFS(O$6:O$39,$C$6:$C$39,1)-_xlfn.MINIFS(O$6:O$39,$C$6:$C$39,1)),"") -> 18.7176 | AF16: =IF($C16=1,100*(P16-_xlfn.MINIFS(P$6:P$39,$C$6:$C$39,1))/(_xlfn.MAXIFS(P$6:P$39,$C$6:$C$39,1)-_xlfn.MINIFS(P$6:P$39,$C$6:$C$39,1)),"") -> 55.031847 | AG16: =IF($C16=1,100*(Q16-_xlfn.MINIFS(Q$6:Q$39,$C$6:$C$39,1))/(_xlfn.MAXIFS(Q$6:Q$39,$C$6:$C$39,1)-_xlfn.MINIFS(Q$6:Q$39,$C$6:$C$39,1)),"") -> 13.629426 | AH16: =IF($C16=1,AVERAGE(AD16:AG16),"") -> 31.231823 | AI16: =IF($C16=1,100*(_xlfn.MAXIFS(R$6:R$39,$C$6:$C$39,1)-R16)/(_xlfn.MAXIFS(R$6:R$39,$C$6:$C$39,1)-_xlfn.MINIFS(R$6:R$39,$C$6:$C$39,1)),"") -> 30.37357 | AJ16: =IF($C16=1,100*(_xlfn.MAXIFS(S$6:S$39,$C$6:$C$39,1)-S16)/(_xlfn.MAXIFS(S$6:S$39,$C$6:$C$39,1)-_xlfn.MINIFS(S$6:S$39,$C$6:$C$39,1)),"") -> 46.081741 | AK16: =IF($C16=1,100*(T16-_xlfn.MINIFS(T$6:T$39,$C$6:$C$39,1))/(_xlfn.MAXIFS(T$6:T$39,$C$6:$C$39,1)-_xlfn.MINIFS(T$6:T$39,$C$6:$C$39,1)),"") -> 78.497245 | AL16: =IF($C16=1,AVERAGE(AI16:AK16),"") -> 51.650852 | AM16: =IF($C16=1,100*(U16-_xlfn.MINIFS(U$6:U$39,$C$6:$C$39,1))/(_xlfn.MAXIFS(U$6:U$39,$C$6:$C$39,1)-_xlfn.MINIFS(U$6:U$39,$C$6:$C$39,1)),"") -> 0 | AN16: =IF($C16=1,100*(V16-_xlfn.MINIFS(V$6:V$39,$C$6:$C$39,1))/(_xlfn.MAXIFS(V$6:V$39,$C$6:$C$39,1)-_xlfn.MINIFS(V$6:V$39,$C$6:$C$39,1)),"") -> 50 | AO16: =IF($C16=1,100*(M16-_xlfn.MINIFS(M$6:M$39,$C$6:$C$39,1))/(_xlfn.MAXIFS(M$6:M$39,$C$6:$C$39,1)-_xlfn.MINIFS(M$6:M$39,$C$6:$C$39,1)),"") -> 28.434466 | AP16: =IF($C16=1,W16,"") -> 0 | AQ16: =IF($C16=1,Inputs!$D$52*AH16+Inputs!$D$53*AL16+Inputs!$D$54*AM16+Inputs!$D$55*AN16+Inputs!$D$56*AO16+Inputs!$D$57*AP16,"") -> 26.919982 | AR16: =IF($C16=1,SQRT(AC16*AQ16),"") -> 39.557028 | AS16: =IF($C16=1,COUNTIFS($C$6:$C$39,1,$AR$6:$AR$39,">"&AR16)+1,"") -> 23 | AT16: =IF($C16=1,Inputs!$D$38+Inputs!$D$39*(1-AL16/100)+Inputs!$D$40*(1-AP16/100),"") -> 0.17933966 | AU16: =IF($C16=1,IF(AC16>=MEDIAN(AC$6:AC$39),IF(AQ16>=MEDIAN(AQ$6:AQ$39),"Prioritise","Big but hard"),IF(AQ16>=MEDIAN(AQ$6:AQ$39),"Easy but small","Deprioritise")),"") -> Big but hard
A17: =Data!A17 -> Gabon | B17: =Data!B17 -> GAB | C17: =Data!AB17 -> 0 | D17: =LN(MAX(Pools!R17,0.000001)) -> 0.98959449 | E17: =Pools!U17 -> 0.072291881 | F17: =IF(Data!H17="","",MAX(0,(Inputs!$D$67-Data!H17)*100)) -> 35.684401 | G17: =IF(COUNT(Data!T17,Data!U17)=0,"",AVERAGE(Data!T17,Data!U17)) -> 11.474035 | H17: =IF(Data!O17="","",MIN(Inputs!$D$60,Data!O17)) | I17: =IF(Data!I17="","",(Data!E17-Data!I17)*100) -> 18.063562 | J17: =IF(F17="",MEDIAN(F$6:F$39),F17) -> 35.684401 | K17: =IF(G17="",MEDIAN(G$6:G$39),G17) -> 11.474035 | L17: =IF(H17="",MEDIAN(H$6:H$39),H17) -> 2.6075828 | M17: =IF(I17="",MEDIAN(I$6:I$39),I17) -> 18.063562 | N17: =IF(Data!L17="",MIN(Inputs!$D$59,MEDIAN(Data!$L$6:$L$39)),MIN(Inputs!$D$59,Data!L17)) -> 120 | O17: =IF(Data!M17="",MEDIAN(Data!$M$6:$M$39),Data!M17) -> 68.720901 | P17: =IF(Data!N17="",MEDIAN(Data!$N$6:$N$39),Data!N17) -> 95.1 | Q17: =IF(Data!K17="",MEDIAN(Data!$K$6:$K$39),Data!K17) -> 91.863209 | R17: =IF(Data!Q17="",MIN(Inputs!$D$61,MEDIAN(Data!$Q$6:$Q$39)),MIN(Inputs!$D$61,Data!Q17)) -> 3.0111278 | S17: =IF(Data!R17="",MAX(Inputs!$D$63,MIN(Inputs!$D$62,MEDIAN(Data!$R$6:$R$39))),MAX(Inputs!$D$63,MIN(Inputs!$D$62,Data!R17))) -> 2.9775832 | T17: =IF(Data!S17="",MEDIAN(Data!$S$6:$S$39),Data!S17) -> 2.9568634 | U17: =Pools!E17 -> 0.90408352 | V17: =Data!W17 -> 20 | W17: =Data!X17 -> 100 | X17: =IF($C17=1,100*(D17-_xlfn.MINIFS(D$6:D$39,$C$6:$C$39,1))/(_xlfn.MAXIFS(D$6:D$39,$C$6:$C$39,1)-_xlfn.MINIFS(D$6:D$39,$C$6:$C$39,1)),"") | Y17: =IF($C17=1,100*(E17-_xlfn.MINIFS(E$6:E$39,$C$6:$C$39,1))/(_xlfn.MAXIFS(E$6:E$39,$C$6:$C$39,1)-_xlfn.MINIFS(E$6:E$39,$C$6:$C$39,1)),"") | Z17: =IF($C17=1,100*(J17-_xlfn.MINIFS(J$6:J$39,$C$6:$C$39,1))/(_xlfn.MAXIFS(J$6:J$39,$C$6:$C$39,1)-_xlfn.MINIFS(J$6:J$39,$C$6:$C$39,1)),"") | AA17: =IF($C17=1,100*(L17-_xlfn.MINIFS(L$6:L$39,$C$6:$C$39,1))/(_xlfn.MAXIFS(L$6:L$39,$C$6:$C$39,1)-_xlfn.MINIFS(L$6:L$39,$C$6:$C$39,1)),"") | AB17: =IF($C17=1,100*(K17-_xlfn.MINIFS(K$6:K$39,$C$6:$C$39,1))/(_xlfn.MAXIFS(K$6:K$39,$C$6:$C$39,1)-_xlfn.MINIFS(K$6:K$39,$C$6:$C$39,1)),"") | AC17: =IF($C17=1,Inputs!$D$46*X17+Inputs!$D$47*Y17+Inputs!$D$48*Z17+Inputs!$D$49*AA17+Inputs!$D$50*AB17,"") | AD17: =IF($C17=1,100*(N17-_xlfn.MINIFS(N$6:N$39,$C$6:$C$39,1))/(_xlfn.MAXIFS(N$6:N$39,$C$6:$C$39,1)-_xlfn.MINIFS(N$6:N$39,$C$6:$C$39,1)),"") | AE17: =IF($C17=1,100*(O17-_xlfn.MINIFS(O$6:O$39,$C$6:$C$39,1))/(_xlfn.MAXIFS(O$6:O$39,$C$6:$C$39,1)-_xlfn.MINIFS(O$6:O$39,$C$6:$C$39,1)),"") | AF17: =IF($C17=1,100*(P17-_xlfn.MINIFS(P$6:P$39,$C$6:$C$39,1))/(_xlfn.MAXIFS(P$6:P$39,$C$6:$C$39,1)-_xlfn.MINIFS(P$6:P$39,$C$6:$C$39,1)),"") | AG17: =IF($C17=1,100*(Q17-_xlfn.MINIFS(Q$6:Q$39,$C$6:$C$39,1))/(_xlfn.MAXIFS(Q$6:Q$39,$C$6:$C$39,1)-_xlfn.MINIFS(Q$6:Q$39,$C$6:$C$39,1)),"") | AH17: =IF($C17=1,AVERAGE(AD17:AG17),"") | AI17: =IF($C17=1,100*(_xlfn.MAXIFS(R$6:R$39,$C$6:$C$39,1)-R17)/(_xlfn.MAXIFS(R$6:R$39,$C$6:$C$39,1)-_xlfn.MINIFS(R$6:R$39,$C$6:$C$39,1)),"") | AJ17: =IF($C17=1,100*(_xlfn.MAXIFS(S$6:S$39,$C$6:$C$39,1)-S17)/(_xlfn.MAXIFS(S$6:S$39,$C$6:$C$39,1)-_xlfn.MINIFS(S$6:S$39,$C$6:$C$39,1)),"") | AK17: =IF($C17=1,100*(T17-_xlfn.MINIFS(T$6:T$39,$C$6:$C$39,1))/(_xlfn.MAXIFS(T$6:T$39,$C$6:$C$39,1)-_xlfn.MINIFS(T$6:T$39,$C$6:$C$39,1)),"") | AL17: =IF($C17=1,AVERAGE(AI17:AK17),"") | AM17: =IF($C17=1,100*(U17-_xlfn.MINIFS(U$6:U$39,$C$6:$C$39,1))/(_xlfn.MAXIFS(U$6:U$39,$C$6:$C$39,1)-_xlfn.MINIFS(U$6:U$39,$C$6:$C$39,1)),"") | AN17: =IF($C17=1,100*(V17-_xlfn.MINIFS(V$6:V$39,$C$6:$C$39,1))/(_xlfn.MAXIFS(V$6:V$39,$C$6:$C$39,1)-_xlfn.MINIFS(V$6:V$39,$C$6:$C$39,1)),"") | AO17: =IF($C17=1,100*(M17-_xlfn.MINIFS(M$6:M$39,$C$6:$C$39,1))/(_xlfn.MAXIFS(M$6:M$39,$C$6:$C$39,1)-_xlfn.MINIFS(M$6:M$39,$C$6:$C$39,1)),"") | AP17: =IF($C17=1,W17,"") | AQ17: =IF($C17=1,Inputs!$D$52*AH17+Inputs!$D$53*AL17+Inputs!$D$54*AM17+Inputs!$D$55*AN17+Inputs!$D$56*AO17+Inputs!$D$57*AP17,"") | AR17: =IF($C17=1,SQRT(AC17*AQ17),"") | AS17: =IF($C17=1,COUNTIFS($C$6:$C$39,1,$AR$6:$AR$39,">"&AR17)+1,"") | AT17: =IF($C17=1,Inputs!$D$38+Inputs!$D$39*(1-AL17/100)+Inputs!$D$40*(1-AP17/100),"") | AU17: =IF($C17=1,IF(AC17>=MEDIAN(AC$6:AC$39),IF(AQ17>=MEDIAN(AQ$6:AQ$39),"Prioritise","Big but hard"),IF(AQ17>=MEDIAN(AQ$6:AQ$39),"Easy but small","Deprioritise")),"")
... A39: =Data!A39 -> Zimbabwe | B39: =Data!B39 -> ZWE | C39: =Data!AB39 -> 1 | D39: =LN(MAX(Pools!R39,0.000001)) -> 2.4776658 | E39: =Pools!U39 -> 0.1000845 | F39: =IF(Data!H39="","",MAX(0,(Inputs!$D$67-Data!H39)*100)) -> 26.658517 | G39: =IF(COUNT(Data!T39,Data!U39)=0,"",AVERAGE(Data!T39,Data!U39)) -> 11.200197 | H39: =IF(Data!O39="","",MIN(Inputs!$D$60,Data!O39)) -> 8.4531023 | I39: =IF(Data!I39="","",(Data!E39-Data!I39)*100) -> -5.2498953 | J39: =IF(F39="",MEDIAN(F$6:F$39),F39) -> 26.658517 | K39: =IF(G39="",MEDIAN(G$6:G$39),G39) -> 11.200197 | L39: =IF(H39="",MEDIAN(H$6:H$39),H39) -> 8.4531023 | M39: =IF(I39="",MEDIAN(I$6:I$39),I39) -> -5.2498953 | N39: =IF(Data!L39="",MIN(Inputs!$D$59,MEDIAN(Data!$L$6:$L$39)),MIN(Inputs!$D$59,Data!L39)) -> 94.245175 | O39: =IF(Data!M39="",MEDIAN(Data!$M$6:$M$39),Data!M39) -> 41.642799 | P39: =IF(Data!N39="",MEDIAN(Data!$N$6:$N$39),Data!N39) -> 62 | Q39: =IF(Data!K39="",MEDIAN(Data!$K$6:$K$39),Data!K39) -> 39.893372 | R39: =IF(Data!Q39="",MIN(Inputs!$D$61,MEDIAN(Data!$Q$6:$Q$39)),MIN(Inputs!$D$61,Data!Q39)) -> 40 | S39: =IF(Data!R39="",MAX(Inputs!$D$63,MIN(Inputs!$D$62,MEDIAN(Data!$R$6:$R$39))),MAX(Inputs!$D$63,MIN(Inputs!$D$62,Data!R39))) -> 40 | T39: =IF(Data!S39="",MEDIAN(Data!$S$6:$S$39),Data!S39) -> 4.3888755 | U39: =Pools!E39 -> 0.87500677 | V39: =Data!W39 -> 20 | W39: =Data!X39 -> 40 | X39: =IF($C39=1,100*(D39-_xlfn.MINIFS(D$6:D$39,$C$6:$C$39,1))/(_xlfn.MAXIFS(D$6:D$39,$C$6:$C$39,1)-_xlfn.MINIFS(D$6:D$39,$C$6:$C$39,1)),"") -> 46.501536 | Y39: =IF($C39=1,100*(E39-_xlfn.MINIFS(E$6:E$39,$C$6:$C$39,1))/(_xlfn.MAXIFS(E$6:E$39,$C$6:$C$39,1)-_xlfn.MINIFS(E$6:E$39,$C$6:$C$39,1)),"") -> 32.544993 | Z39: =IF($C39=1,100*(J39-_xlfn.MINIFS(J$6:J$39,$C$6:$C$39,1))/(_xlfn.MAXIFS(J$6:J$39,$C$6:$C$39,1)-_xlfn.MINIFS(J$6:J$39,$C$6:$C$39,1)),"") -> 40.053201 | AA39: =IF($C39=1,100*(L39-_xlfn.MINIFS(L$6:L$39,$C$6:$C$39,1))/(_xlfn.MAXIFS(L$6:L$39,$C$6:$C$39,1)-_xlfn.MINIFS(L$6:L$39,$C$6:$C$39,1)),"") -> 55.724616 | AB39: =IF($C39=1,100*(K39-_xlfn.MINIFS(K$6:K$39,$C$6:$C$39,1))/(_xlfn.MAXIFS(K$6:K$39,$C$6:$C$39,1)-_xlfn.MINIFS(K$6:K$39,$C$6:$C$39,1)),"") -> 36.595527 | AC39: =IF($C39=1,Inputs!$D$46*X39+Inputs!$D$47*Y39+Inputs!$D$48*Z39+Inputs!$D$49*AA39+Inputs!$D$50*AB39,"") -> 42.640538 | AD39: =IF($C39=1,100*(N39-_xlfn.MINIFS(N$6:N$39,$C$6:$C$39,1))/(_xlfn.MAXIFS(N$6:N$39,$C$6:$C$39,1)-_xlfn.MINIFS(N$6:N$39,$C$6:$C$39,1)),"") -> 70.71189 | AE39: =IF($C39=1,100*(O39-_xlfn.MINIFS(O$6:O$39,$C$6:$C$39,1))/(_xlfn.MAXIFS(O$6:O$39,$C$6:$C$39,1)-_xlfn.MINIFS(O$6:O$39,$C$6:$C$39,1)),"") -> 47.102752 | AF39: =IF($C39=1,100*(P39-_xlfn.MINIFS(P$6:P$39,$C$6:$C$39,1))/(_xlfn.MAXIFS(P$6:P$39,$C$6:$C$39,1)-_xlfn.MINIFS(P$6:P$39,$C$6:$C$39,1)),"") -> 61.910828 | AG39: =IF($C39=1,100*(Q39-_xlfn.MINIFS(Q$6:Q$39,$C$6:$C$39,1))/(_xlfn.MAXIFS(Q$6:Q$39,$C$6:$C$39,1)-_xlfn.MINIFS(Q$6:Q$39,$C$6:$C$39,1)),"") -> 48.532361 | AH39: =IF($C39=1,AVERAGE(AD39:AG39),"") -> 57.064458 | AI39: =IF($C39=1,100*(_xlfn.MAXIFS(R$6:R$39,$C$6:$C$39,1)-R39)/(_xlfn.MAXIFS(R$6:R$39,$C$6:$C$39,1)-_xlfn.MINIFS(R$6:R$39,$C$6:$C$39,1)),"") -> 0 | AJ39: =IF($C39=1,100*(_xlfn.MAXIFS(S$6:S$39,$C$6:$C$39,1)-S39)/(_xlfn.MAXIFS(S$6:S$39,$C$6:$C$39,1)-_xlfn.MINIFS(S$6:S$39,$C$6:$C$39,1)),"") -> 0 | AK39: =IF($C39=1,100*(T39-_xlfn.MINIFS(T$6:T$39,$C$6:$C$39,1))/(_xlfn.MAXIFS(T$6:T$39,$C$6:$C$39,1)-_xlfn.MINIFS(T$6:T$39,$C$6:$C$39,1)),"") -> 47.535003 | AL39: =IF($C39=1,AVERAGE(AI39:AK39),"") -> 15.845001 | AM39: =IF($C39=1,100*(U39-_xlfn.MINIFS(U$6:U$39,$C$6:$C$39,1))/(_xlfn.MAXIFS(U$6:U$39,$C$6:$C$39,1)-_xlfn.MINIFS(U$6:U$39,$C$6:$C$39,1)),"") -> 88.50022 | AN39: =IF($C39=1,100*(V39-_xlfn.MINIFS(V$6:V$39,$C$6:$C$39,1))/(_xlfn.MAXIFS(V$6:V$39,$C$6:$C$39,1)-_xlfn.MINIFS(V$6:V$39,$C$6:$C$39,1)),"") -> 0 | AO39: =IF($C39=1,100*(M39-_xlfn.MINIFS(M$6:M$39,$C$6:$C$39,1))/(_xlfn.MAXIFS(M$6:M$39,$C$6:$C$39,1)-_xlfn.MINIFS(M$6:M$39,$C$6:$C$39,1)),"") -> 0 | AP39: =IF($C39=1,W39,"") -> 40 | AQ39: =IF($C39=1,Inputs!$D$52*AH39+Inputs!$D$53*AL39+Inputs!$D$54*AM39+Inputs!$D$55*AN39+Inputs!$D$56*AO39+Inputs!$D$57*AP39,"") -> 35.856925 | AR39: =IF($C39=1,SQRT(AC39*AQ39),"") -> 39.1019 | AS39: =IF($C39=1,COUNTIFS($C$6:$C$39,1,$AR$6:$AR$39,">"&AR39)+1,"") -> 24 | AT39: =IF($C39=1,Inputs!$D$38+Inputs!$D$39*(1-AL39/100)+Inputs!$D$40*(1-AP39/100),"") -> 0.177662 | AU39: =IF($C39=1,IF(AC39>=MEDIAN(AC$6:AC$39),IF(AQ39>=MEDIAN(AQ$6:AQ$39),"Prioritise","Big but hard"),IF(AQ39>=MEDIAN(AQ$6:AQ$39),"Easy but small","Deprioritise")),"") -> Deprioritise

Sheet Cases
A1: Business case for the top five markets: three scenarios each (USD millions)
A2: Each block rebuilds the case for one market and scenario. The top five are picked live by rank from the Scorecard. NPV at 2026; launch spend in 2026, first revenue 2027.
A5: Rank | B5: Market | C5: ISO3 | D5: Priority score | E5: NPV Low | F5: NPV Base | G5: NPV High | H5: Expected NPV | I5: Peak funding, Base | J5: Payback year, Base | K5: Operator users 2030, Base | L5: Operator revenue 2030, Base | M5: Operator EBITDA 2030, Base | N5: Break-even multiple of share assumption | O5: Break-even share of NEW users | P5: Discount rate
A6: 1 | B6: =$B$59 -> Tanzania | C6: =C59 -> TZA | D6: =INDEX(Scorecard!$AR$6:$AR$39,$B$58) -> 65.680662 | E6: =B48 -> -102.08844 | F6: =B88 -> 13.478933 | G6: =B128 -> 194.47359 | H6: =Inputs!$C$20*E6+Inputs!$D$20*F6+Inputs!$E$20*G6 -> 29.835753 | I6: =B89 -> 56.236653 | J6: =B90 -> 2035 | K6: =G76 -> 2329052 | L6: =G77 -> 45.210565 | M6: =G81 -> 4.0637661 | N6: =B95 -> 0.90767136 | O6: =IF(ISNUMBER(N6),N6*Inputs!$D$18,"n/a") -> 0.1361507 | P6: =$B$67 -> 0.12799263
A7: 2 | B7: =$B$179 -> Cote d'Ivoire | C7: =C179 -> CIV | D7: =INDEX(Scorecard!$AR$6:$AR$39,$B$178) -> 60.633303 | E7: =B168 -> -80.890126 | F7: =B208 -> -10.323053 | G7: =B248 -> 99.301836 | H7: =Inputs!$C$20*E7+Inputs!$D$20*F7+Inputs!$E$20*G7 -> -0.55859887 | I7: =B209 -> 43.586782 | J7: =B210 -> none | K7: =G196 -> 1087477.1 | L7: =G197 -> 27.308259 | M7: =G201 -> 0.68005652 | N7: =B215 -> 1.1153893 | O7: =IF(ISNUMBER(N7),N7*Inputs!$D$18,"n/a") -> 0.1673084 | P7: =$B$187 -> 0.12533993
A8: 3 | B8: =$B$299 -> Uganda | C8: =C299 -> UGA | D8: =INDEX(Scorecard!$AR$6:$AR$39,$B$298) -> 60.529385 | E8: =B288 -> -96.115655 | F8: =B328 -> -29.90096 | G8: =B368 -> 65.192713 | H8: =Inputs!$C$20*E8+Inputs!$D$20*F8+Inputs!$E$20*G8 -> -22.681215 | I8: =B329 -> 53.850893 | J8: =B330 -> none | K8: =G316 -> 1531268.9 | L8: =G317 -> 28.630609 | M8: =G321 -> -1.1683684 | N8: =B335 -> 1.3463574 | O8: =IF(ISNUMBER(N8),N8*Inputs!$D$18,"n/a") -> 0.20195361 | P8: =$B$307 -> 0.12717103
A9: 4 | B9: =$B$419 -> Congo, Dem. Rep. | C9: =C419 -> COD | D9: =INDEX(Scorecard!$AR$6:$AR$39,$B$418) -> 60.269108 | E9: =B408 -> -111.57089 | F9: =B448 -> 2.1813478 | G9: =B488 -> 208.78313 | H9: =Inputs!$C$20*E9+Inputs!$D$20*F9+Inputs!$E$20*G9 -> 25.393734 | I9: =B449 -> 69.537657 | J9: =B450 -> 2035 | K9: =G436 -> 3436668.6 | L9: =G437 -> 50.385198 | M9: =G441 -> 2.2807219 | N9: =B455 -> 0.98424469 | O9: =IF(ISNUMBER(N9),N9*Inputs!$D$18,"n/a") -> 0.1476367 | P9: =$B$427 -> 0.16466025
A10: 5 | B10: =$B$539 -> Benin | C10: =C539 -> BEN | D10: =INDEX(Scorecard!$AR$6:$AR$39,$B$538) -> 55.504829 | E10: =B528 -> -66.507508 | F10: =B568 -> -40.6569 | G10: =B608 -> 2.4786814 | H10: =Inputs!$C$20*E10+Inputs!$D$20*F10+Inputs!$E$20*G10 -> -36.335657 | I10: =B569 -> 50.297752 | J10: =B570 -> none | K10: =G556 -> 491528.81 | L10: =G557 -> 9.5111853 | M10: =G561 -> -4.291414 | N10: =B575 -> 2.2628918 | O10: =IF(ISNUMBER(N10),N10*Inputs!$D$18,"n/a") -> 0.33943377 | P10: =$B$547 -> 0.12375724
A12: How to read: NPV is at 2026 in $m. 'Break-even multiple' is the multiple of the Base share assumption at which NPV = 0 (below 1.0 = positive at the assumed share). 'Break-even share of NEW users' restates it as a share of adults who start using mobile money after 2024.
A13: Expected NPV weights Low, Base and High by the scenario weights on Inputs. Costs scale with market size (Inputs section 4).
A18: Rank 1 | Low scenario | row index in market list | B18: =MATCH(1,Scorecard!$AS$6:$AS$39,0) -> 30
A19: Market | B19: =INDEX(Scorecard!$A$6:$A$39,$B$18) -> Tanzania | C19: =INDEX(Scorecard!$B$6:$B$39,$B$18) -> TZA
A20: Adults 2024 | B20: =INDEX(Data!$D$6:$D$39,$B$18) -> 38155970
A21: Population growth % a year | B21: =INDEX(Data!$P$6:$P$39,$B$18) -> 2.8742667
A22: Mobile money adoption 2024 | B22: =INDEX(Data!$E$6:$E$39,$B$18) -> 0.52853984
A23: logit(adoption 2024) | B23: =INDEX(Forecast!$E$6:$E$39,$B$18) -> 0.11428357
A24: Growth of logit per year x scenario multiplier | B24: =INDEX(Forecast!$F$6:$F$39,$B$18)*Inputs!$C$16 -> 0.089363531
A25: Revenue per user ($ a year) | B25: =INDEX(Pools!$H$6:$H$39,$B$18) -> 11.646944
A26: Cost scale factor | B26: =INDEX(Pools!$G$6:$G$39,$B$18) -> 1.2948307
A27: Discount rate | B27: =INDEX(Scorecard!$AT$6:$AT$39,$B$18) -> 0.12799263
A28: Share of existing users won | B28: =Inputs!$C$19 -> 0.015
A29: Share of new users won | B29: =Inputs!$C$18 -> 0.08
A30: Year | C30: 2026 | D30: 2027 | E30: 2028 | F30: 2029 | G30: 2030 | H30: 2031 | I30: 2032 | J30: 2033 | K30: 2034 | L30: 2035
A31: Adults | D31: =$B$20*(1+$B$21/100)^(D30-2024) -> 41541556 | E31: =$B$20*(1+$B$21/100)^(E30-2024) -> 42735571 | F31: =$B$20*(1+$B$21/100)^(F30-2024) -> 43963905 | G31: =$B$20*(1+$B$21/100)^(G30-2024) -> 45227545 | H31: =$B$20*(1+$B$21/100)^(H30-2024) -> 46527505 | I31: =$B$20*(1+$B$21/100)^(I30-2024) -> 47864830 | J31: =$B$20*(1+$B$21/100)^(J30-2024) -> 49240593 | K31: =$B$20*(1+$B$21/100)^(K30-2024) -> 50655899 | L31: =$B$20*(1+$B$21/100)^(L30-2024) -> 52111884
A32: Mobile money adoption | D32: =MIN(1/(1+EXP(-($B$23+$B$24*(D30-2024)))),MAX(Inputs!$D$9,$B$22)) -> 0.59444559 | E32: =MIN(1/(1+EXP(-($B$23+$B$24*(E30-2024)))),MAX(Inputs!$D$9,$B$22)) -> 0.61579496 | F32: =MIN(1/(1+EXP(-($B$23+$B$24*(F30-2024)))),MAX(Inputs!$D$9,$B$22)) -> 0.6367073 | G32: =MIN(1/(1+EXP(-($B$23+$B$24*(G30-2024)))),MAX(Inputs!$D$9,$B$22)) -> 0.65711519 | H32: =MIN(1/(1+EXP(-($B$23+$B$24*(H30-2024)))),MAX(Inputs!$D$9,$B$22)) -> 0.67695831 | I32: =MIN(1/(1+EXP(-($B$23+$B$24*(I30-2024)))),MAX(Inputs!$D$9,$B$22)) -> 0.69618402 | J32: =MIN(1/(1+EXP(-($B$23+$B$24*(J30-2024)))),MAX(Inputs!$D$9,$B$22)) -> 0.71474766 | K32: =MIN(1/(1+EXP(-($B$23+$B$24*(K30-2024)))),MAX(Inputs!$D$9,$B$22)) -> 0.73261267 | L32: =MIN(1/(1+EXP(-($B$23+$B$24*(L30-2024)))),MAX(Inputs!$D$9,$B$22)) -> 0.74975056
A33: Existing users at 2024 penetration | D33: =D31*$B$22 -> 21956367 | E33: =E31*$B$22 -> 22587452 | F33: =F31*$B$22 -> 23236675 | G33: =G31*$B$22 -> 23904559 | H33: =H31*$B$22 -> 24591640 | I33: =I31*$B$22 -> 25298469 | J33: =J31*$B$22 -> 26025615 | K33: =K31*$B$22 -> 26773660 | L33: =L31*$B$22 -> 27543207
A34: New users above 2024 penetration | D34: =MAX(0,D31*D32-D33) -> 2737827.7 | E34: =MAX(0,E31*E32-E33) -> 3728897.6 | F34: =MAX(0,F31*F32-F33) -> 4755464.3 | G34: =MAX(0,G31*G32-G33) -> 5815147.4 | H34: =MAX(0,H31*H32-H33) -> 6905541.1 | I34: =MAX(0,I31*I32-I33) -> 8024260.1 | J34: =MAX(0,J31*J32-J33) -> 9168983.4 | K34: =MAX(0,K31*K32-K33) -> 10337493 | L34: =MAX(0,L31*L32-L33) -> 11527708
A35: Ramp (share of target reached) | D35: =Inputs!$D$41 -> 0.1 | E35: =Inputs!$D$42 -> 0.35 | F35: =Inputs!$D$43 -> 0.65 | G35: =Inputs!$D$44 -> 1 | H35: =Inputs!$D$44 -> 1 | I35: =Inputs!$D$44 -> 1 | J35: =Inputs!$D$44 -> 1 | K35: =Inputs!$D$44 -> 1 | L35: =Inputs!$D$44 -> 1
A36: Operator users | C36: 0 | D36: =D35*($B$28*D33+$B$29*D34) -> 54837.172 | E36: =E35*($B$28*E33+$B$29*E34) -> 222993.25 | F36: =F35*($B$28*F33+$B$29*F34) -> 473841.73 | G36: =G35*($B$28*G33+$B$29*G34) -> 823780.18 | H36: =H35*($B$28*H33+$B$29*H34) -> 921317.89 | I36: =I35*($B$28*I33+$B$29*I34) -> 1021417.9 | J36: =J35*($B$28*J33+$B$29*J34) -> 1123902.9 | K36: =K35*($B$28*K33+$B$29*K34) -> 1228604.3 | L36: =L35*($B$28*L33+$B$29*L34) -> 1335364.7
A37: Operator revenue ($m) | D37: =D36*$B$25/1000000 -> 0.63868549 | E37: =E36*$B$25/1000000 -> 2.59719 | F37: =F36*$B$25/1000000 -> 5.5188082 | G37: =G36*$B$25/1000000 -> 9.5945218 | H37: =H36*$B$25/1000000 -> 10.730538 | I37: =I36*$B$25/1000000 -> 11.896397 | J37: =J36*$B$25/1000000 -> 13.090034 | K37: =K36*$B$25/1000000 -> 14.309486 | L37: =L36*$B$25/1000000 -> 15.552919
A38: Acquisition cost ($m) | D38: =Inputs!$D$31*MAX(0,D36-C36)/1000000 -> 0.16451152 | E38: =Inputs!$D$31*MAX(0,E36-D36)/1000000 -> 0.50446825 | F38: =Inputs!$D$31*MAX(0,F36-E36)/1000000 -> 0.75254541 | G38: =Inputs!$D$31*MAX(0,G36-F36)/1000000 -> 1.0498154 | H38: =Inputs!$D$31*MAX(0,H36-G36)/1000000 -> 0.29261312 | I38: =Inputs!$D$31*MAX(0,I36-H36)/1000000 -> 0.30029989 | J38: =Inputs!$D$31*MAX(0,J36-I36)/1000000 -> 0.30745513 | K38: =Inputs!$D$31*MAX(0,K36-J36)/1000000 -> 0.31410433 | L38: =Inputs!$D$31*MAX(0,L36-K36)/1000000 -> 0.32028118
A39: Fixed operating cost ($m) | D39: =Inputs!$D$30*$B$26 -> 15.537969 | E39: =Inputs!$D$30*$B$26 -> 15.537969 | F39: =Inputs!$D$30*$B$26 -> 15.537969 | G39: =Inputs!$D$30*$B$26 -> 15.537969 | H39: =Inputs!$D$30*$B$26 -> 15.537969 | I39: =Inputs!$D$30*$B$26 -> 15.537969 | J39: =Inputs!$D$30*$B$26 -> 15.537969 | K39: =Inputs!$D$30*$B$26 -> 15.537969 | L39: =Inputs!$D$30*$B$26 -> 15.537969
A40: Margin on revenue less acquisition cost ($m) | D40: =D37*Inputs!$D$29-D38 -> 0.15483123 | E40: =E37*Inputs!$D$29-E38 -> 0.79412675 | F40: =F37*Inputs!$D$29-F38 -> 2.0068587 | G40: =G37*Inputs!$D$29-G38 -> 3.7474456 | H40: =H37*Inputs!$D$29-H38 -> 5.0726559 | I40: =I37*Inputs!$D$29-I38 -> 5.6478985 | J40: =J37*Inputs!$D$29-J38 -> 6.237562 | K40: =K37*Inputs!$D$29-K38 -> 6.8406388 | L40: =L37*Inputs!$D$29-L38 -> 7.4561781
A41: EBITDA ($m) | D41: =D40-D39 -> -15.383138 | E41: =E40-E39 -> -14.743842 | F41: =F40-F39 -> -13.53111 | G41: =G40-G39 -> -11.790523 | H41: =H40-H39 -> -10.465313 | I41: =I40-I39 -> -9.8900704 | J41: =J40-J39 -> -9.3004068 | K41: =K40-K39 -> -8.6973301 | L41: =L40-L39 -> -8.0817908
A42: Discount factor | D42: =1/(1+$B$27)^(D30-2026) -> 0.88653061 | E42: =1/(1+$B$27)^(E30-2026) -> 0.78593653 | F42: =1/(1+$B$27)^(F30-2026) -> 0.69675679 | G42: =1/(1+$B$27)^(G30-2026) -> 0.61769623 | H42: =1/(1+$B$27)^(H30-2026) -> 0.54760661 | I42: =1/(1+$B$27)^(I30-2026) -> 0.48547003 | J42: =1/(1+$B$27)^(J30-2026) -> 0.43038404 | K42: =1/(1+$B$27)^(K30-2026) -> 0.38154863 | L42: =1/(1+$B$27)^(L30-2026) -> 0.33825454
A43: PV of EBITDA ($m) | D43: =D41*D42 -> -13.637622 | E43: =E41*E42 -> -11.587724 | F43: =F41*F42 -> -9.4278929 | G43: =G41*G42 -> -7.2829618 | H43: =H41*H42 -> -5.7308746 | I43: =I41*I42 -> -4.8013327 | J43: =J41*J42 -> -4.0027467 | K43: =K41*K42 -> -3.3184544 | L43: =L41*L42 -> -2.7337024
A44: Cumulative cash incl. launch spend ($m) | C44: =-B47 -> -25.896615 | D44: =C44+D41 -> -41.279752 | E44: =D44+E41 -> -56.023595 | F44: =E44+F41 -> -69.554705 | G44: =F44+G41 -> -81.345228 | H44: =G44+H41 -> -91.810541 | I44: =H44+I41 -> -101.70061 | J44: =I44+J41 -> -111.00102 | K44: =J44+K41 -> -119.69835 | L44: =K44+L41 -> -127.78014
A45: Payback marker | D45: =IF(D44>=0,D30,"") | E45: =IF(E44>=0,E30,"") | F45: =IF(F44>=0,F30,"") | G45: =IF(G44>=0,G30,"") | H45: =IF(H44>=0,H30,"") | I45: =IF(I44>=0,I30,"") | J45: =IF(J44>=0,J30,"") | K45: =IF(K44>=0,K30,"") | L45: =IF(L44>=0,L30,"")
A47: Launch investment ($m) | B47: =Inputs!$D$32*$B$26 -> 25.896615
A48: NPV ($m) | B48: =-B47+SUM(D43:L43)+Inputs!$D$33*L41*L42 -> -102.08844
A49: Peak funding need ($m) | B49: =-MIN(C44:L44) -> 127.78014
A50: Payback year | B50: =IF(COUNT(C45:L45)=0,"none",MIN(C45:L45)) -> none
A51: PV of revenue incl. terminal value ($m) | B51: =SUMPRODUCT(D37:L37,D42:L42)+Inputs!$D$33*L37*L42 -> 66.689244
A52: PV of acquisition cost incl. terminal value ($m) | B52: =SUMPRODUCT(D38:L38,D42:L42)+Inputs!$D$33*L38*L42 -> 2.9233453
A53: PV of launch spend and fixed cost incl. terminal value ($m) | B53: =B47+Inputs!$D$30*$B$26*(SUM(D42:L42)+Inputs!$D$33*L42) -> 132.50972
A54: Closed-form NPV = margin x PV revenue - PV acquisition - PV fixed ($m) | B54: =Inputs!$D$29*B51-B52-B53 -> -102.08844
A55: Break-even multiple of the share assumption | B55: =IF(Inputs!$D$29*B51-B52>0,B53/(Inputs!$D$29*B51-B52),"n/a") -> 4.3558236
A56: Closed-form gap (should be 0) | B56: =ABS(B54-B48) -> 0
A58: Rank 1 | Base scenario | row index in market list | B58: =MATCH(1,Scorecard!$AS$6:$AS$39,0) -> 30
A59: Market | B59: =INDEX(Scorecard!$A$6:$A$39,$B$58) -> Tanzania | C59: =INDEX(Scorecard!$B$6:$B$39,$B$58) -> TZA
A60: Adults 2024 | B60: =INDEX(Data!$D$6:$D$39,$B$58) -> 38155970
A61: Population growth % a year | B61: =INDEX(Data!$P$6:$P$39,$B$58) -> 2.8742667
A62: Mobile money adoption 2024 | B62: =INDEX(Data!$E$6:$E$39,$B$58) -> 0.52853984
A63: logit(adoption 2024) | B63: =INDEX(Forecast!$E$6:$E$39,$B$58) -> 0.11428357
A64: Growth of logit per year x scenario multiplier | B64: =INDEX(Forecast!$F$6:$F$39,$B$58)*Inputs!$D$16 -> 0.17872706
A65: Revenue per user ($ a year) | B65: =INDEX(Pools!$I$6:$I$39,$B$58) -> 19.411574
A66: Cost scale factor | B66: =INDEX(Pools!$G$6:$G$39,$B$58) -> 1.2948307
A67: Discount rate | B67: =INDEX(Scorecard!$AT$6:$AT$39,$B$58) -> 0.12799263
A68: Share of existing users won | B68: =Inputs!$D$19 -> 0.03
A69: Share of new users won | B69: =Inputs!$D$18 -> 0.15
A70: Year | C70: 2026 | D70: 2027 | E70: 2028 | F70: 2029 | G70: 2030 | H70: 2031 | I70: 2032 | J70: 2033 | K70: 2034 | L70: 2035
A71: Adults | D71: =$B$60*(1+$B$61/100)^(D70-2024) -> 41541556 | E71: =$B$60*(1+$B$61/100)^(E70-2024) -> 42735571 | F71: =$B$60*(1+$B$61/100)^(F70-2024) -> 43963905 | G71: =$B$60*(1+$B$61/100)^(G70-2024) -> 45227545 | H71: =$B$60*(1+$B$61/100)^(H70-2024) -> 46527505 | I71: =$B$60*(1+$B$61/100)^(I70-2024) -> 47864830 | J71: =$B$60*(1+$B$61/100)^(J70-2024) -> 49240593 | K71: =$B$60*(1+$B$61/100)^(K70-2024) -> 50655899 | L71: =$B$60*(1+$B$61/100)^(L70-2024) -> 52111884
A72: Mobile money adoption | D72: =MIN(1/(1+EXP(-($B$63+$B$64*(D70-2024)))),MAX(Inputs!$D$9,$B$62)) -> 0.65711519 | E72: =MIN(1/(1+EXP(-($B$63+$B$64*(E70-2024)))),MAX(Inputs!$D$9,$B$62)) -> 0.69618402 | F72: =MIN(1/(1+EXP(-($B$63+$B$64*(F70-2024)))),MAX(Inputs!$D$9,$B$62)) -> 0.73261267 | G72: =MIN(1/(1+EXP(-($B$63+$B$64*(G70-2024)))),MAX(Inputs!$D$9,$B$62)) -> 0.76614066 | H72: =MIN(1/(1+EXP(-($B$63+$B$64*(H70-2024)))),MAX(Inputs!$D$9,$B$62)) -> 0.79663156 | I72: =MIN(1/(1+EXP(-($B$63+$B$64*(I70-2024)))),MAX(Inputs!$D$9,$B$62)) -> 0.82405996 | J72: =MIN(1/(1+EXP(-($B$63+$B$64*(J70-2024)))),MAX(Inputs!$D$9,$B$62)) -> 0.84849263 | K72: =MIN(1/(1+EXP(-($B$63+$B$64*(K70-2024)))),MAX(Inputs!$D$9,$B$62)) -> 0.87006733 | L72: =MIN(1/(1+EXP(-($B$63+$B$64*(L70-2024)))),MAX(Inputs!$D$9,$B$62)) -> 0.8889718
A73: Existing users at 2024 penetration | D73: =D71*$B$62 -> 21956367 | E73: =E71*$B$62 -> 22587452 | F73: =F71*$B$62 -> 23236675 | G73: =G71*$B$62 -> 23904559 | H73: =H71*$B$62 -> 24591640 | I73: =I71*$B$62 -> 25298469 | J73: =J71*$B$62 -> 26025615 | K73: =K71*$B$62 -> 26773660 | L73: =L71*$B$62 -> 27543207
A74: New users above 2024 penetration | D74: =MAX(0,D71*D72-D73) -> 5341220 | E74: =MAX(0,E71*E72-E73) -> 7164369.7 | F74: =MAX(0,F71*F72-F73) -> 8971838.8 | G74: =MAX(0,G71*G72-G73) -> 10746102 | H74: =MAX(0,H71*H72-H73) -> 12473639 | I74: =MAX(0,I71*I72-I73) -> 14145021 | J74: =MAX(0,J71*J72-J73) -> 15754665 | K74: =MAX(0,K71*K72-K73) -> 17300382 | L74: =MAX(0,L71*L72-L73) -> 18782789
A75: Ramp (share of target reached) | D75: =Inputs!$D$41 -> 0.1 | E75: =Inputs!$D$42 -> 0.35 | F75: =Inputs!$D$43 -> 0.65 | G75: =Inputs!$D$44 -> 1 | H75: =Inputs!$D$44 -> 1 | I75: =Inputs!$D$44 -> 1 | J75: =Inputs!$D$44 -> 1 | K75: =Inputs!$D$44 -> 1 | L75: =Inputs!$D$44 -> 1
A76: Operator users | C76: 0 | D76: =D75*($B$68*D73+$B$69*D74) -> 145987.4 | E76: =E75*($B$68*E73+$B$69*E74) -> 613297.65 | F76: =F75*($B$68*F73+$B$69*F74) -> 1327869.4 | G76: =G75*($B$68*G73+$B$69*G74) -> 2329052 | H76: =H75*($B$68*H73+$B$69*H74) -> 2608795.1 | I76: =I75*($B$68*I73+$B$69*I74) -> 2880707.2 | J76: =J75*($B$68*J73+$B$69*J74) -> 3143968.2 | K76: =K75*($B$68*K73+$B$69*K74) -> 3398267.1 | L76: =L75*($B$68*L73+$B$69*L74) -> 3643714.5
A77: Operator revenue ($m) | D77: =D76*$B$65/1000000 -> 2.8338452 | E77: =E76*$B$65/1000000 -> 11.905073 | F77: =F76*$B$65/1000000 -> 25.776036 | G77: =G76*$B$65/1000000 -> 45.210565 | H77: =H76*$B$65/1000000 -> 50.640818 | I77: =I76*$B$65/1000000 -> 55.91906 | J77: =J76*$B$65/1000000 -> 61.029371 | K77: =K76*$B$65/1000000 -> 65.965713 | L77: =L76*$B$65/1000000 -> 70.730232
A78: Acquisition cost ($m) | D78: =Inputs!$D$31*MAX(0,D76-C76)/1000000 -> 0.43796221 | E78: =Inputs!$D$31*MAX(0,E76-D76)/1000000 -> 1.4019308 | F78: =Inputs!$D$31*MAX(0,F76-E76)/1000000 -> 2.1437154 | G78: =Inputs!$D$31*MAX(0,G76-F76)/1000000 -> 3.0035478 | H78: =Inputs!$D$31*MAX(0,H76-G76)/1000000 -> 0.83922913 | I78: =Inputs!$D$31*MAX(0,I76-H76)/1000000 -> 0.81573625 | J78: =Inputs!$D$31*MAX(0,J76-I76)/1000000 -> 0.78978315 | K78: =Inputs!$D$31*MAX(0,K76-J76)/1000000 -> 0.76289667 | L78: =Inputs!$D$31*MAX(0,L76-K76)/1000000 -> 0.73634214
A79: Fixed operating cost ($m) | D79: =Inputs!$D$30*$B$66 -> 15.537969 | E79: =Inputs!$D$30*$B$66 -> 15.537969 | F79: =Inputs!$D$30*$B$66 -> 15.537969 | G79: =Inputs!$D$30*$B$66 -> 15.537969 | H79: =Inputs!$D$30*$B$66 -> 15.537969 | I79: =Inputs!$D$30*$B$66 -> 15.537969 | J79: =Inputs!$D$30*$B$66 -> 15.537969 | K79: =Inputs!$D$30*$B$66 -> 15.537969 | L79: =Inputs!$D$30*$B$66 -> 15.537969
A80: Margin on revenue less acquisition cost ($m) | D80: =D77*Inputs!$D$29-D78 -> 0.9789604 | E80: =E77*Inputs!$D$29-E78 -> 4.5506055 | F80: =F77*Inputs!$D$29-F78 -> 10.744302 | G80: =G77*Inputs!$D$29-G78 -> 19.601735 | H80: =H77*Inputs!$D$29-H78 -> 24.48118 | I80: =I77*Inputs!$D$29-I78 -> 27.143794 | J80: =J77*Inputs!$D$29-J78 -> 29.724902 | K80: =K77*Inputs!$D$29-K78 -> 32.21996 | L80: =L77*Inputs!$D$29-L78 -> 34.628774
A81: EBITDA ($m) | D81: =D80-D79 -> -14.559008 | E81: =E80-E79 -> -10.987363 | F81: =F80-F79 -> -4.7936664 | G81: =G80-G79 -> 4.0637661 | H81: =H80-H79 -> 8.9432111 | I81: =I80-I79 -> 11.605825 | J81: =J80-J79 -> 14.186933 | K81: =K80-K79 -> 16.681991 | L81: =L80-L79 -> 19.090805
A82: Discount factor | D82: =1/(1+$B$67)^(D70-2026) -> 0.88653061 | E82: =1/(1+$B$67)^(E70-2026) -> 0.78593653 | F82: =1/(1+$B$67)^(F70-2026) -> 0.69675679 | G82: =1/(1+$B$67)^(G70-2026) -> 0.61769623 | H82: =1/(1+$B$67)^(H70-2026) -> 0.54760661 | I82: =1/(1+$B$67)^(I70-2026) -> 0.48547003 | J82: =1/(1+$B$67)^(J70-2026) -> 0.43038404 | K82: =1/(1+$B$67)^(K70-2026) -> 0.38154863 | L82: =1/(1+$B$67)^(L70-2026) -> 0.33825454
A83: PV of EBITDA ($m) | D83: =D81*D82 -> -12.907007 | E83: =E81*E82 -> -8.6353702 | F83: =F81*F82 -> -3.3400196 | G83: =G81*G82 -> 2.510173 | H83: =H81*H82 -> 4.8973615 | I83: =I81*I82 -> 5.63428 | J83: =J81*J82 -> 6.1058297 | K83: =K81*K82 -> 6.3649907 | L83: =L81*L82 -> 6.4575515
A84: Cumulative cash incl. launch spend ($m) | C84: =-B87 -> -25.896615 | D84: =C84+D81 -> -40.455623 | E84: =D84+E81 -> -51.442987 | F84: =E84+F81 -> -56.236653 | G84: =F84+G81 -> -52.172887 | H84: =G84+H81 -> -43.229676 | I84: =H84+I81 -> -31.623851 | J84: =I84+J81 -> -17.436918 | K84: =J84+K81 -> -0.75492711 | L84: =K84+L81 -> 18.335878
A85: Payback marker | D85: =IF(D84>=0,D70,"") | E85: =IF(E84>=0,E70,"") | F85: =IF(F84>=0,F70,"") | G85: =IF(G84>=0,G70,"") | H85: =IF(H84>=0,H70,"") | I85: =IF(I84>=0,I70,"") | J85: =IF(J84>=0,J70,"") | K85: =IF(K84>=0,K70,"") | L85: =IF(L84>=0,L70,"") -> 2035
A87: Launch investment ($m) | B87: =Inputs!$D$32*$B$66 -> 25.896615
A88: NPV ($m) | B88: =-B87+SUM(D83:L83)+Inputs!$D$33*L81*L82 -> 13.478933
A89: Peak funding need ($m) | B89: =-MIN(C84:L84) -> 56.236653
A90: Payback year | B90: =IF(COUNT(C85:L85)=0,"none",MIN(C85:L85)) -> 2035
A91: PV of revenue incl. terminal value ($m) | B91: =SUMPRODUCT(D77:L77,D82:L82)+Inputs!$D$33*L77*L82 -> 307.61735
A92: PV of acquisition cost incl. terminal value ($m) | B92: =SUMPRODUCT(D78:L78,D82:L82)+Inputs!$D$33*L78*L82 -> 7.8200255
A93: PV of launch spend and fixed cost incl. terminal value ($m) | B93: =B87+Inputs!$D$30*$B$66*(SUM(D82:L82)+Inputs!$D$33*L82) -> 132.50972
A94: Closed-form NPV = margin x PV revenue - PV acquisition - PV fixed ($m) | B94: =Inputs!$D$29*B91-B92-B93 -> 13.478933
A95: Break-even multiple of the share assumption | B95: =IF(Inputs!$D$29*B91-B92>0,B93/(Inputs!$D$29*B91-B92),"n/a") -> 0.90767136
A96: Closed-form gap (should be 0) | B96: =ABS(B94-B88) -> 0
A98: Rank 1 | High scenario | row index in market list | B98: =MATCH(1,Scorecard!$AS$6:$AS$39,0) -> 30
A99: Market | B99: =INDEX(Scorecard!$A$6:$A$39,$B$98) -> Tanzania | C99: =INDEX(Scorecard!$B$6:$B$39,$B$98) -> TZA
A100: Adults 2024 | B100: =INDEX(Data!$D$6:$D$39,$B$98) -> 38155970
A101: Population growth % a year | B101: =INDEX(Data!$P$6:$P$39,$B$98) -> 2.8742667
A102: Mobile money adoption 2024 | B102: =INDEX(Data!$E$6:$E$39,$B$98) -> 0.52853984
A103: logit(adoption 2024) | B103: =INDEX(Forecast!$E$6:$E$39,$B$98) -> 0.11428357
A104: Growth of logit per year x scenario multiplier | B104: =INDEX(Forecast!$F$6:$F$39,$B$98)*Inputs!$E$16 -> 0.26809059
A105: Revenue per user ($ a year) | B105: =INDEX(Pools!$J$6:$J$39,$B$98) -> 24.846814
A106: Cost scale factor | B106: =INDEX(Pools!$G$6:$G$39,$B$98) -> 1.2948307
A107: Discount rate | B107: =INDEX(Scorecard!$AT$6:$AT$39,$B$98) -> 0.12799263
A108: Share of existing users won | B108: =Inputs!$E$19 -> 0.05
A109: Share of new users won | B109: =Inputs!$E$18 -> 0.22
A110: Year | C110: 2026 | D110: 2027 | E110: 2028 | F110: 2029 | G110: 2030 | H110: 2031 | I110: 2032 | J110: 2033 | K110: 2034 | L110: 2035
A111: Adults | D111: =$B$100*(1+$B$101/100)^(D110-2024) -> 41541556 | E111: =$B$100*(1+$B$101/100)^(E110-2024) -> 42735571 | F111: =$B$100*(1+$B$101/100)^(F110-2024) -> 43963905 | G111: =$B$100*(1+$B$101/100)^(G110-2024) -> 45227545 | H111: =$B$100*(1+$B$101/100)^(H110-2024) -> 46527505 | I111: =$B$100*(1+$B$101/100)^(I110-2024) -> 47864830 | J111: =$B$100*(1+$B$101/100)^(J110-2024) -> 49240593 | K111: =$B$100*(1+$B$101/100)^(K110-2024) -> 50655899 | L111: =$B$100*(1+$B$101/100)^(L110-2024) -> 52111884
...

Sheet Sensitivity
A1: Sensitivity of NPV for the top three markets (Base scenario, $m)
A2: Closed-form recalculation: NPV = share multiple x (margin x revenue multiple x PV revenue - PV acquisition) - PV fixed. The centre cell of each grid equals the Base NPV on Cases.
A4: ="Rank 1: "&Cases!$B$59 -> Rank 1: Tanzania
A5: Grid 1: operator share (multiple of Base) across, revenue per user (multiple of Base) down | H5: Grid 2: fixed-cost multiple across, contribution margin down
B6: 0.5 | C6: 0.75 | D6: 1 | E6: 1.25 | F6: 1.5 | I6: 0.5 | J6: 0.75 | K6: 1 | L6: 1.5 | M6: 2
A7: 0.6 | B7: =B$6*(Inputs!$D$29*$A7*Cases!B91-Cases!B92)-Cases!B93 -> -90.277126 | C7: =C$6*(Inputs!$D$29*$A7*Cases!B91-Cases!B92)-Cases!B93 -> -69.160831 | D7: =D$6*(Inputs!$D$29*$A7*Cases!B91-Cases!B92)-Cases!B93 -> -48.044537 | E7: =E$6*(Inputs!$D$29*$A7*Cases!B91-Cases!B92)-Cases!B93 -> -26.928242 | F7: =F$6*(Inputs!$D$29*$A7*Cases!B91-Cases!B92)-Cases!B93 -> -5.8119474 | H7: 0.35 | I7: =($H7*Cases!B91-Cases!B92)-(Cases!B87+I$6*(Cases!B93-Cases!B87)) -> 20.642881 | J7: =($H7*Cases!B91-Cases!B92)-(Cases!B87+J$6*(Cases!B93-Cases!B87)) -> -6.0103943 | K7: =($H7*Cases!B91-Cases!B92)-(Cases!B87+K$6*(Cases!B93-Cases!B87)) -> -32.663669 | L7: =($H7*Cases!B91-Cases!B92)-(Cases!B87+L$6*(Cases!B93-Cases!B87)) -> -85.97022 | M7: =($H7*Cases!B91-Cases!B92)-(Cases!B87+M$6*(Cases!B93-Cases!B87)) -> -139.27677
A8: 0.8 | B8: =B$6*(Inputs!$D$29*$A8*Cases!B91-Cases!B92)-Cases!B93 -> -74.896259 | C8: =C$6*(Inputs!$D$29*$A8*Cases!B91-Cases!B92)-Cases!B93 -> -46.08953 | D8: =D$6*(Inputs!$D$29*$A8*Cases!B91-Cases!B92)-Cases!B93 -> -17.282802 | E8: =E$6*(Inputs!$D$29*$A8*Cases!B91-Cases!B92)-Cases!B93 -> 11.523926 | F8: =F$6*(Inputs!$D$29*$A8*Cases!B91-Cases!B92)-Cases!B93 -> 40.330655 | H8: 0.425 | I8: =($H8*Cases!B91-Cases!B92)-(Cases!B87+I$6*(Cases!B93-Cases!B87)) -> 43.714182 | J8: =($H8*Cases!B91-Cases!B92)-(Cases!B87+J$6*(Cases!B93-Cases!B87)) -> 17.060907 | K8: =($H8*Cases!B91-Cases!B92)-(Cases!B87+K$6*(Cases!B93-Cases!B87)) -> -9.5923684 | L8: =($H8*Cases!B91-Cases!B92)-(Cases!B87+L$6*(Cases!B93-Cases!B87)) -> -62.898919 | M8: =($H8*Cases!B91-Cases!B92)-(Cases!B87+M$6*(Cases!B93-Cases!B87)) -> -116.20547
A9: 1 | B9: =B$6*(Inputs!$D$29*$A9*Cases!B91-Cases!B92)-Cases!B93 -> -59.515391 | C9: =C$6*(Inputs!$D$29*$A9*Cases!B91-Cases!B92)-Cases!B93 -> -23.018229 | D9: =D$6*(Inputs!$D$29*$A9*Cases!B91-Cases!B92)-Cases!B93 -> 13.478933 | E9: =E$6*(Inputs!$D$29*$A9*Cases!B91-Cases!B92)-Cases!B93 -> 49.976095 | F9: =F$6*(Inputs!$D$29*$A9*Cases!B91-Cases!B92)-Cases!B93 -> 86.473257 | H9: 0.5 | I9: =($H9*Cases!B91-Cases!B92)-(Cases!B87+I$6*(Cases!B93-Cases!B87)) -> 66.785483 | J9: =($H9*Cases!B91-Cases!B92)-(Cases!B87+J$6*(Cases!B93-Cases!B87)) -> 40.132208 | K9: =($H9*Cases!B91-Cases!B92)-(Cases!B87+K$6*(Cases!B93-Cases!B87)) -> 13.478933 | L9: =($H9*Cases!B91-Cases!B92)-(Cases!B87+L$6*(Cases!B93-Cases!B87)) -> -39.827618 | M9: =($H9*Cases!B91-Cases!B92)-(Cases!B87+M$6*(Cases!B93-Cases!B87)) -> -93.134168
A10: 1.2 | B10: =B$6*(Inputs!$D$29*$A10*Cases!B91-Cases!B92)-Cases!B93 -> -44.134524 | C10: =C$6*(Inputs!$D$29*$A10*Cases!B91-Cases!B92)-Cases!B93 -> 0.053071656 | D10: =D$6*(Inputs!$D$29*$A10*Cases!B91-Cases!B92)-Cases!B93 -> 44.240667 | E10: =E$6*(Inputs!$D$29*$A10*Cases!B91-Cases!B92)-Cases!B93 -> 88.428263 | F10: =F$6*(Inputs!$D$29*$A10*Cases!B91-Cases!B92)-Cases!B93 -> 132.61586 | H10: 0.575 | I10: =($H10*Cases!B91-Cases!B92)-(Cases!B87+I$6*(Cases!B93-Cases!B87)) -> 89.856784 | J10: =($H10*Cases!B91-Cases!B92)-(Cases!B87+J$6*(Cases!B93-Cases!B87)) -> 63.203509 | K10: =($H10*Cases!B91-Cases!B92)-(Cases!B87+K$6*(Cases!B93-Cases!B87)) -> 36.550234 | L10: =($H10*Cases!B91-Cases!B92)-(Cases!B87+L$6*(Cases!B93-Cases!B87)) -> -16.756317 | M10: =($H10*Cases!B91-Cases!B92)-(Cases!B87+M$6*(Cases!B93-Cases!B87)) -> -70.062867
A11: 1.4 | B11: =B$6*(Inputs!$D$29*$A11*Cases!B91-Cases!B92)-Cases!B93 -> -28.753657 | C11: =C$6*(Inputs!$D$29*$A11*Cases!B91-Cases!B92)-Cases!B93 -> 23.124373 | D11: =D$6*(Inputs!$D$29*$A11*Cases!B91-Cases!B92)-Cases!B93 -> 75.002402 | E11: =E$6*(Inputs!$D$29*$A11*Cases!B91-Cases!B92)-Cases!B93 -> 126.88043 | F11: =F$6*(Inputs!$D$29*$A11*Cases!B91-Cases!B92)-Cases!B93 -> 178.75846 | H11: 0.65 | I11: =($H11*Cases!B91-Cases!B92)-(Cases!B87+I$6*(Cases!B93-Cases!B87)) -> 112.92809 | J11: =($H11*Cases!B91-Cases!B92)-(Cases!B87+J$6*(Cases!B93-Cases!B87)) -> 86.27481 | K11: =($H11*Cases!B91-Cases!B92)-(Cases!B87+K$6*(Cases!B93-Cases!B87)) -> 59.621535 | L11: =($H11*Cases!B91-Cases!B92)-(Cases!B87+L$6*(Cases!B93-Cases!B87)) -> 6.3149844 | M11: =($H11*Cases!B91-Cases!B92)-(Cases!B87+M$6*(Cases!B93-Cases!B87)) -> -46.991566
A14: ="Rank 2: "&Cases!$B$179 -> Rank 2: Cote d'Ivoire
A15: Grid 1: operator share (multiple of Base) across, revenue per user (multiple of Base) down | H15: Grid 2: fixed-cost multiple across, contribution margin down
B16: 0.5 | C16: 0.75 | D16: 1 | E16: 1.25 | F16: 1.5 | I16: 0.5 | J16: 0.75 | K16: 1 | L16: 1.5 | M16: 2
A17: 0.6 | B17: =B$16*(Inputs!$D$29*$A17*Cases!B211-Cases!B212)-Cases!B213 -> -73.664661 | C17: =C$16*(Inputs!$D$29*$A17*Cases!B211-Cases!B212)-Cases!B213 -> -60.604071 | D17: =D$16*(Inputs!$D$29*$A17*Cases!B211-Cases!B212)-Cases!B213 -> -47.54348 | E17: =E$16*(Inputs!$D$29*$A17*Cases!B211-Cases!B212)-Cases!B213 -> -34.48289 | F17: =F$16*(Inputs!$D$29*$A17*Cases!B211-Cases!B212)-Cases!B213 -> -21.4223 | H17: 0.35 | I17: =($H17*Cases!B211-Cases!B212)-(Cases!B207+I$16*(Cases!B213-Cases!B207)) -> 2.0032987 | J17: =($H17*Cases!B211-Cases!B212)-(Cases!B207+J$16*(Cases!B213-Cases!B207)) -> -18.117537 | K17: =($H17*Cases!B211-Cases!B212)-(Cases!B207+K$16*(Cases!B213-Cases!B207)) -> -38.238373 | L17: =($H17*Cases!B211-Cases!B212)-(Cases!B207+L$16*(Cases!B213-Cases!B207)) -> -78.480046 | M17: =($H17*Cases!B211-Cases!B212)-(Cases!B207+M$16*(Cases!B213-Cases!B207)) -> -118.72172
A18: 0.8 | B18: =B$16*(Inputs!$D$29*$A18*Cases!B211-Cases!B212)-Cases!B213 -> -64.359554 | C18: =C$16*(Inputs!$D$29*$A18*Cases!B211-Cases!B212)-Cases!B213 -> -46.64641 | D18: =D$16*(Inputs!$D$29*$A18*Cases!B211-Cases!B212)-Cases!B213 -> -28.933266 | E18: =E$16*(Inputs!$D$29*$A18*Cases!B211-Cases!B212)-Cases!B213 -> -11.220123 | F18: =F$16*(Inputs!$D$29*$A18*Cases!B211-Cases!B212)-Cases!B213 -> 6.4930211 | H18: 0.425 | I18: =($H18*Cases!B211-Cases!B212)-(Cases!B207+I$16*(Cases!B213-Cases!B207)) -> 15.960959 | J18: =($H18*Cases!B211-Cases!B212)-(Cases!B207+J$16*(Cases!B213-Cases!B207)) -> -4.1598769 | K18: =($H18*Cases!B211-Cases!B212)-(Cases!B207+K$16*(Cases!B213-Cases!B207)) -> -24.280713 | L18: =($H18*Cases!B211-Cases!B212)-(Cases!B207+L$16*(Cases!B213-Cases!B207)) -> -64.522385 | M18: =($H18*Cases!B211-Cases!B212)-(Cases!B207+M$16*(Cases!B213-Cases!B207)) -> -104.76406
A19: 1 | B19: =B$16*(Inputs!$D$29*$A19*Cases!B211-Cases!B212)-Cases!B213 -> -55.054447 | C19: =C$16*(Inputs!$D$29*$A19*Cases!B211-Cases!B212)-Cases!B213 -> -32.68875 | D19: =D$16*(Inputs!$D$29*$A19*Cases!B211-Cases!B212)-Cases!B213 -> -10.323053 | E19: =E$16*(Inputs!$D$29*$A19*Cases!B211-Cases!B212)-Cases!B213 -> 12.042645 | F19: =F$16*(Inputs!$D$29*$A19*Cases!B211-Cases!B212)-Cases!B213 -> 34.408342 | H19: 0.5 | I19: =($H19*Cases!B211-Cases!B212)-(Cases!B207+I$16*(Cases!B213-Cases!B207)) -> 29.91862 | J19: =($H19*Cases!B211-Cases!B212)-(Cases!B207+J$16*(Cases!B213-Cases!B207)) -> 9.7977836 | K19: =($H19*Cases!B211-Cases!B212)-(Cases!B207+K$16*(Cases!B213-Cases!B207)) -> -10.323053 | L19: =($H19*Cases!B211-Cases!B212)-(Cases!B207+L$16*(Cases!B213-Cases!B207)) -> -50.564725 | M19: =($H19*Cases!B211-Cases!B212)-(Cases!B207+M$16*(Cases!B213-Cases!B207)) -> -90.806397
A20: 1.2 | B20: =B$16*(Inputs!$D$29*$A20*Cases!B211-Cases!B212)-Cases!B213 -> -45.74934 | C20: =C$16*(Inputs!$D$29*$A20*Cases!B211-Cases!B212)-Cases!B213 -> -18.731089 | D20: =D$16*(Inputs!$D$29*$A20*Cases!B211-Cases!B212)-Cases!B213 -> 8.2871615 | E20: =E$16*(Inputs!$D$29*$A20*Cases!B211-Cases!B212)-Cases!B213 -> 35.305412 | F20: =F$16*(Inputs!$D$29*$A20*Cases!B211-Cases!B212)-Cases!B213 -> 62.323663 | H20: 0.575 | I20: =($H20*Cases!B211-Cases!B212)-(Cases!B207+I$16*(Cases!B213-Cases!B207)) -> 43.87628 | J20: =($H20*Cases!B211-Cases!B212)-(Cases!B207+J$16*(Cases!B213-Cases!B207)) -> 23.755444 | K20: =($H20*Cases!B211-Cases!B212)-(Cases!B207+K$16*(Cases!B213-Cases!B207)) -> 3.634608 | L20: =($H20*Cases!B211-Cases!B212)-(Cases!B207+L$16*(Cases!B213-Cases!B207)) -> -36.607064 | M20: =($H20*Cases!B211-Cases!B212)-(Cases!B207+M$16*(Cases!B213-Cases!B207)) -> -76.848736
A21: 1.4 | B21: =B$16*(Inputs!$D$29*$A21*Cases!B211-Cases!B212)-Cases!B213 -> -36.444233 | C21: =C$16*(Inputs!$D$29*$A21*Cases!B211-Cases!B212)-Cases!B213 -> -4.7734288 | D21: =D$16*(Inputs!$D$29*$A21*Cases!B211-Cases!B212)-Cases!B213 -> 26.897375 | E21: =E$16*(Inputs!$D$29*$A21*Cases!B211-Cases!B212)-Cases!B213 -> 58.56818 | F21: =F$16*(Inputs!$D$29*$A21*Cases!B211-Cases!B212)-Cases!B213 -> 90.238984 | H21: 0.65 | I21: =($H21*Cases!B211-Cases!B212)-(Cases!B207+I$16*(Cases!B213-Cases!B207)) -> 57.833941 | J21: =($H21*Cases!B211-Cases!B212)-(Cases!B207+J$16*(Cases!B213-Cases!B207)) -> 37.713105 | K21: =($H21*Cases!B211-Cases!B212)-(Cases!B207+K$16*(Cases!B213-Cases!B207)) -> 17.592268 | L21: =($H21*Cases!B211-Cases!B212)-(Cases!B207+L$16*(Cases!B213-Cases!B207)) -> -22.649404 | M21: =($H21*Cases!B211-Cases!B212)-(Cases!B207+M$16*(Cases!B213-Cases!B207)) -> -62.891076
A24: ="Rank 3: "&Cases!$B$299 -> Rank 3: Uganda
A25: Grid 1: operator share (multiple of Base) across, revenue per user (multiple of Base) down | H25: Grid 2: fixed-cost multiple across, contribution margin down
B26: 0.5 | C26: 0.75 | D26: 1 | E26: 1.25 | F26: 1.5 | I26: 0.5 | J26: 0.75 | K26: 1 | L26: 1.5 | M26: 2
A27: 0.6 | B27: =B$26*(Inputs!$D$29*$A27*Cases!B331-Cases!B332)-Cases!B333 -> -91.182477 | C27: =C$26*(Inputs!$D$29*$A27*Cases!B331-Cases!B332)-Cases!B333 -> -78.658345 | D27: =D$26*(Inputs!$D$29*$A27*Cases!B331-Cases!B332)-Cases!B333 -> -66.134213 | E27: =E$26*(Inputs!$D$29*$A27*Cases!B331-Cases!B332)-Cases!B333 -> -53.61008 | F27: =F$26*(Inputs!$D$29*$A27*Cases!B331-Cases!B332)-Cases!B333 -> -41.085948 | H27: 0.35 | I27: =($H27*Cases!B331-Cases!B332)-(Cases!B327+I$26*(Cases!B333-Cases!B327)) -> -10.282237 | J27: =($H27*Cases!B331-Cases!B332)-(Cases!B327+J$26*(Cases!B333-Cases!B327)) -> -33.679068 | K27: =($H27*Cases!B331-Cases!B332)-(Cases!B327+K$26*(Cases!B333-Cases!B327)) -> -57.075899 | L27: =($H27*Cases!B331-Cases!B332)-(Cases!B327+L$26*(Cases!B333-Cases!B327)) -> -103.86956 | M27: =($H27*Cases!B331-Cases!B332)-(Cases!B327+M$26*(Cases!B333-Cases!B327)) -> -150.66323
A28: 0.8 | B28: =B$26*(Inputs!$D$29*$A28*Cases!B331-Cases!B332)-Cases!B333 -> -82.124164 | C28: =C$26*(Inputs!$D$29*$A28*Cases!B331-Cases!B332)-Cases!B333 -> -65.070875 | D28: =D$26*(Inputs!$D$29*$A28*Cases!B331-Cases!B332)-Cases!B333 -> -48.017586 | E28: =E$26*(Inputs!$D$29*$A28*Cases!B331-Cases!B332)-Cases!B333 -> -30.964297 | F28: =F$26*(Inputs!$D$29*$A28*Cases!B331-Cases!B332)-Cases!B333 -> -13.911008 | H28: 0.425 | I28: =($H28*Cases!B331-Cases!B332)-(Cases!B327+I$26*(Cases!B333-Cases!B327)) -> 3.3052334 | J28: =($H28*Cases!B331-Cases!B332)-(Cases!B327+J$26*(Cases!B333-Cases!B327)) -> -20.091598 | K28: =($H28*Cases!B331-Cases!B332)-(Cases!B327+K$26*(Cases!B333-Cases!B327)) -> -43.488429 | L28: =($H28*Cases!B331-Cases!B332)-(Cases!B327+L$26*(Cases!B333-Cases!B327)) -> -90.282092 | M28: =($H28*Cases!B331-Cases!B332)-(Cases!B327+M$26*(Cases!B333-Cases!B327)) -> -137.07576
A29: 1 | B29: =B$26*(Inputs!$D$29*$A29*Cases!B331-Cases!B332)-Cases!B333 -> -73.065851 | C29: =C$26*(Inputs!$D$29*$A29*Cases!B331-Cases!B332)-Cases!B333 -> -51.483405 | D29: =D$26*(Inputs!$D$29*$A29*Cases!B331-Cases!B332)-Cases!B333 -> -29.90096 | E29: =E$26*(Inputs!$D$29*$A29*Cases!B331-Cases!B332)-Cases!B333 -> -8.318514 | F29: =F$26*(Inputs!$D$29*$A29*Cases!B331-Cases!B332)-Cases!B333 -> 13.263932 | H29: 0.5 | I29: =($H29*Cases!B331-Cases!B332)-(Cases!B327+I$26*(Cases!B333-Cases!B327)) -> 16.892703 | J29: =($H29*Cases!B331-Cases!B332)-(Cases!B327+J$26*(Cases!B333-Cases!B327)) -> -6.5041281 | K29: =($H29*Cases!B331-Cases!B332)-(Cases!B327+K$26*(Cases!B333-Cases!B327)) -> -29.90096 | L29: =($H29*Cases!B331-Cases!B332)-(Cases!B327+L$26*(Cases!B333-Cases!B327)) -> -76.694622 | M29: =($H29*Cases!B331-Cases!B332)-(Cases!B327+M$26*(Cases!B333-Cases!B327)) -> -123.48829
A30: 1.2 | B30: =B$26*(Inputs!$D$29*$A30*Cases!B331-Cases!B332)-Cases!B333 -> -64.007537 | C30: =C$26*(Inputs!$D$29*$A30*Cases!B331-Cases!B332)-Cases!B333 -> -37.895935 | D30: =D$26*(Inputs!$D$29*$A30*Cases!B331-Cases!B332)-Cases!B333 -> -11.784333 | E30: =E$26*(Inputs!$D$29*$A30*Cases!B331-Cases!B332)-Cases!B333 -> 14.327269 | F30: =F$26*(Inputs!$D$29*$A30*Cases!B331-Cases!B332)-Cases!B333 -> 40.438871 | H30: 0.575 | I30: =($H30*Cases!B331-Cases!B332)-(Cases!B327+I$26*(Cases!B333-Cases!B327)) -> 30.480173 | J30: =($H30*Cases!B331-Cases!B332)-(Cases!B327+J$26*(Cases!B333-Cases!B327)) -> 7.0833418 | K30: =($H30*Cases!B331-Cases!B332)-(Cases!B327+K$26*(Cases!B333-Cases!B327)) -> -16.31349 | L30: =($H30*Cases!B331-Cases!B332)-(Cases!B327+L$26*(Cases!B333-Cases!B327)) -> -63.107153 | M30: =($H30*Cases!B331-Cases!B332)-(Cases!B327+M$26*(Cases!B333-Cases!B327)) -> -109.90082
A31: 1.4 | B31: =B$26*(Inputs!$D$29*$A31*Cases!B331-Cases!B332)-Cases!B333 -> -54.949224 | C31: =C$26*(Inputs!$D$29*$A31*Cases!B331-Cases!B332)-Cases!B333 -> -24.308465 | D31: =D$26*(Inputs!$D$29*$A31*Cases!B331-Cases!B332)-Cases!B333 -> 6.3322935 | E31: =E$26*(Inputs!$D$29*$A31*Cases!B331-Cases!B332)-Cases!B333 -> 36.973052 | F31: =F$26*(Inputs!$D$29*$A31*Cases!B331-Cases!B332)-Cases!B333 -> 67.613811 | H31: 0.65 | I31: =($H31*Cases!B331-Cases!B332)-(Cases!B327+I$26*(Cases!B333-Cases!B327)) -> 44.067643 | J31: =($H31*Cases!B331-Cases!B332)-(Cases!B327+J$26*(Cases!B333-Cases!B327)) -> 20.670812 | K31: =($H31*Cases!B331-Cases!B332)-(Cases!B327+K$26*(Cases!B333-Cases!B327)) -> -2.7260197 | L31: =($H31*Cases!B331-Cases!B332)-(Cases!B327+L$26*(Cases!B333-Cases!B327)) -> -49.519683 | M31: =($H31*Cases!B331-Cases!B332)-(Cases!B327+M$26*(Cases!B333-Cases!B327)) -> -96.313345

Sheet Robustness
A1: Robustness and validation (static results from analysis/model.py)
A2: These come from estimation in Python (regression, back-test, Monte Carlo). They are not live formulas; re-run model.py to refresh.
A4: A. Does an economic-fundamentals model predict mobile-money adoption? (leave-one-country-out test)
A5: Prediction error for 2024 adoption, countries held out one at a time (percentage points, RMSE)
A6: Fundamentals model (income, urbanisation, phones, electricity, remittances, survey wave) | B6: 25.530422
A7: Benchmark with no fundamentals (survey-wave average only) | B7: 21.008754
A8: Countries tested | B8: 30
A9: Reading: fundamentals do not beat the benchmark out-of-sample, so mobile-money success depends on the local ecosystem (regulation, operator, agents). That is why the plan includes a due-diligence gate.
A11: B. Regression coefficients (dependent variable: logit of mobile-money adoption; country-clustered standard errors)
A12: Variable | B12: Model A coefficient | C12: Std. error | D12: t | E12: Model B coefficient | F12: Std. error | G12: t
A13: const | B13: -2.9695879 | C13: 3.3476167 | D13: -0.88707524 | E13: -0.9346541 | F13: 4.183948 | G13: -0.22339047
A14: ln_gdppc | B14: -0.067648624 | C14: 0.50095528 | D14: -0.13503925 | E14: -0.38709928 | F14: 0.63002041 | G14: -0.6144234
A15: urban | B15: 0.0034660772 | C15: 0.017073293 | D15: 0.20301165 | E15: 0.0088191295 | F15: 0.016993843 | G15: 0.51896026
A16: subs | B16: 0.013237965 | C16: 0.0080393511 | D16: 1.6466459 | E16: 0.015822685 | F16: 0.0084029161 | G16: 1.8829993
A17: elec | B17: -0.0097154535 | C17: 0.015411278 | D17: -0.63041194 | E17: -0.01222308 | F17: 0.014800904 | G17: -0.8258334
A18: remit | B18: 0.00070825129 | C18: 0.04025323 | D18: 0.017594894 | E18: -0.0065211656 | F18: 0.043211699 | G18: -0.15091204
A19: fi | E19: 1.1905993 | F19: 1.3063547 | G19: 0.91139056
A20: wave_2017 | B20: 1.295528 | C20: 0.18799005 | D20: 6.8914712 | E20: 1.2205205 | F20: 0.20188084 | G20: 6.0457472
A21: wave_2021 | B21: 1.7176454 | C21: 0.26316716 | D21: 6.5268229 | E21: 1.632636 | F21: 0.29572677 | G21: 5.5207582
A22: wave_2024 | B22: 2.2493712 | C22: 0.27485993 | D22: 8.1837 | E22: 2.1839126 | F22: 0.28720045 | G22: 7.6041406
A23: R-squared | B23: 0.39665254 | E23: 0.40569654
A24: Observations / countries | B24: 124 / 36
A26: C. Back-test of the adoption forecast: forecast 2024 from data up to the 2022 round
A27: Weight on country's own trend | B27: Mean absolute error (pp) | C27: Bias (pp) | D27: Error if no growth is assumed (pp) | E27: Countries | F27: Pooled growth g0
A28: 0 | B28: 7.3609744 | C28: 2.7903506 | D28: 11.413946 | E28: 34 | F28: 0.22742284
A29: 0.25 | B29: 7.987298 | C29: 3.3537723 | D29: 11.413946 | E29: 34 | F29: 0.22742284
A30: 0.5 | B30: 8.7545677 | C30: 3.891021 | D30: 11.413946 | E30: 34 | F30: 0.22742284
A31: 0.75 | B31: 9.657324 | C31: 4.3922042 | D31: 11.413946 | E31: 34 | F31: 0.22742284
A32: 1 | B32: 10.842672 | C32: 4.8046875 | D32: 11.413946 | E32: 34 | F32: 0.22742284
A33: Reading: a common growth rate beats country-specific trends, and any growth beats none. A positive bias means the forecast runs high, so the Low scenario matters.
A35: D. How stable is the ranking? 5,000 random draws of all scoring weights
A36: Market | B36: Base-weights rank | C36: Ranked #1 | D36: In top 2 | E36: In top 3
A37: Tanzania | B37: 1 | C37: 0.263 | D37: 0.4914 | E37: 0.5858
A38: Cote d'Ivoire | B38: 2 | C38: 0.0256 | D38: 0.1242 | E38: 0.2506
A39: Uganda | B39: 3 | C39: 0.001 | D39: 0.0772 | E39: 0.2964
A40: Congo, Dem. Rep. | B40: 4 | C40: 0.2464 | D40: 0.3954 | E40: 0.5014
A41: Benin | B41: 5 | C41: 0.007 | D41: 0.0272 | E41: 0.0746
A42: Senegal | B42: 6 | C42: 0.0606 | D42: 0.1984 | E42: 0.2526
A43: Zambia | B43: 7 | C43: 0.0032 | D43: 0.02 | E43: 0.0462
A44: Togo | B44: 8 | C44: 0.1196 | D44: 0.1838 | E44: 0.2614
A45: Madagascar | B45: 9 | C45: 0.0236 | D45: 0.0588 | E45: 0.0978
A46: Liberia | B46: 10 | C46: 0.2218 | D46: 0.3138 | E46: 0.368
A47: Ghana | B47: 11 | C47: 0.002 | D47: 0.007 | E47: 0.0244
A48: Guinea | B48: 12 | C48: 0.0008 | D48: 0.0118 | E48: 0.024
... A61: Niger | B61: 25 | C61: 0.0016 | D61: 0.0036 | E61: 0.006

Sheet Sources
A1: Sources and limitations
A3: ID | B3: Source | C3: Publisher | D3: Link | E3: Used for
A4: S1 | B4: Global Findex Database 2025 (survey year 2024; earlier rounds 2011-2021/22) | C4: World Bank / Gates Foundation / Gallup | D4: https://www.worldbank.org/en/publication/globalfindex | E4: Mobile money, account and merchant-payment adoption; gender, income and rural gaps; adult population
A5: S2 | B5: World Development Indicators (DataBank extract, last updated 8 Oct 2026) | C5: World Bank | D5: https://databank.worldbank.org/source/world-development-indicators | E5: GDP per capita, urbanisation, mobile subscriptions, internet, electricity, remittances, inflation, exchange rate, population growth
A6: S3 | B6: Safaricom FY2026 results (year to March 2026), M-Pesa revenue and active customers | C6: Safaricom PLC, as reported by HapaKenya | D6: https://hapakenya.com | E6: Calibration of revenue per active user in the home market
A7: S4 | B7: Airtel Africa FY2026 final results: Airtel Money revenue and customers by region | C7: Airtel Africa plc | D7: https://www.airtel.africa/ | E7: Calibration of revenue per customer in East Africa and Nigeria; low-revenue bank-led markets
A8: S5 | B8: Harmonized List of Fragile and Conflict-Affected Situations, FY26 | C8: World Bank | D8: https://www.worldbank.org/en/topic/fragilityconflictviolence/brief/harmonized-list-of-fragile-situations | E8: Institutional stability score (conflict = 0, institutional/social fragility = 40, not listed = 100)
A10: Limitations (also stated in the deck and the methods appendix)
A11: L1 | B11: Governance indicators (WGI: government effectiveness GE.EST, regulatory quality RQ.EST) were not in the data supplied. Institutional stability is therefore proxied by the World Bank FY26 fragility list, which is coarse (three levels). Adding WGI is the first extension.
A12: L2 | B12: No Findex codebook was available. Variable meanings were taken from names and checked against published headline figures (for example Kenya's mobile-money adoption).
A13: L3 | B13: Rwanda, Burundi, Somalia and South Sudan have no 2024 Findex mobile-money result, so they cannot be scored.
A14: L4 | B14: Findex measures the share of adults reporting a mobile money account. Operator-reported 'active users' are defined differently and are not comparable one-to-one.
A15: L5 | B15: Revenue per user is calibrated on two company disclosures reported in the press (S3, S4), not audited filings. It is scaled to other markets by income and by how mobile-led the market is. The Low/High range spans the uncertainty.
A16: L6 | B16: Judgement inputs, flagged [A] in the workbook: proximity to Kenya, operator share of new and existing users, margin, fixed cost, launch investment, terminal multiple and discount-rate premia. Each is tested in the Sensitivity sheet or through the break-even share.
A17: L7 | B17: A cross-country regression of adoption on economic fundamentals does not predict adoption out-of-sample (leave-one-country-out error 25.5 points against 21.0 for a no-fundamentals benchmark). The regression is therefore reported, not used in scoring.
A18: L8 | B18: The adoption forecast over-predicted 2024 levels by 2.8 points on average in a back-test from 2022. The Low scenario halves the trend to cover this.
A19: L9 | B19: Ranks beyond the top two are sensitive to the scoring weights (see Robustness). The recommendation rests on the top of the ranking and on the gate sequence, not on a precise ordering.
A20: L10 | B20: Business-case values are an illustrative, entry-level screen (no tax, no working capital, no currency path beyond the discount-rate premium). They are not a valuation.

Sheet PyRef
A1: Python reference results (static values from analysis/model.py)
A2: Independent implementation. Columns V onward compare the workbook with these values; the Checks sheet totals the differences.
A5: Country | B5: ISO3 | C5: Candidate | D5: Adoption 2030 Base | E5: Pool 2030 Base ($m) | F5: Winnable revenue Base ($m) | G5: Attractiveness | H5: Ease | I5: Priority | J5: Rank | K5: Discount rate | L5: NPV Low | M5: NPV Base | N5: NPV High | O5: Expected NPV | P5: Peak funding Base | Q5: Break-even share multiple | R5: Top-1 frequency | S5: Top-2 frequency | T5: Top-3 frequency | V5: diff adoption | W5: diff pool | X5: diff winnable | Y5: diff A | Z5: diff E | AA5: diff priority | AB5: diff rank | AC5: diff WACC
A6: Benin | B6: BEN | C6: 1 | D6: 0.70402795 | E6: 129.37709 | F6: 9.5111853 | G6: 43.37119 | H6: 71.033009 | I6: 55.504829 | J6: 5 | K6: 0.12375724 | L6: -66.507508 | M6: -40.6569 | N6: 2.4786814 | O6: -36.335657 | P6: 50.297752 | Q6: 2.2628918 | R6: 0.007 | S6: 0.0272 | T6: 0.0746 | V6: =ABS(Forecast!J6-D6) -> 0 | W6: =ABS(Pools!L6-E6) -> 0 | X6: =ABS(Pools!R6-F6) -> 0 | Y6: =IF(C6=1,ABS(Scorecard!AC6-G6),0) -> 0 | Z6: =IF(C6=1,ABS(Scorecard!AQ6-H6),0) -> 0 | AA6: =IF(C6=1,ABS(Scorecard!AR6-I6),0) -> 0 | AB6: =IF(C6=1,ABS(Scorecard!AS6-J6),0) -> 0 | AC6: =IF(C6=1,ABS(Scorecard!AT6-K6),0) -> 0
A7: Botswana | B7: BWA | C7: 0 | D7: 0.75714636 | E7: 39.419487 | F7: 2.6880546 | V7: =ABS(Forecast!J7-D7) -> 0 | W7: =ABS(Pools!L7-E7) -> 0 | X7: =ABS(Pools!R7-F7) -> 0 | Y7: =IF(C7=1,ABS(Scorecard!AC7-G7),0) -> 0 | Z7: =IF(C7=1,ABS(Scorecard!AQ7-H7),0) -> 0 | AA7: =IF(C7=1,ABS(Scorecard!AR7-I7),0) -> 0 | AB7: =IF(C7=1,ABS(Scorecard!AS7-J7),0) -> 0 | AC7: =IF(C7=1,ABS(Scorecard!AT7-K7),0) -> 0
A8: Burkina Faso | B8: BFA | C8: 1 | D8: 0.69795622 | E8: 174.90816 | F8: 12.957196 | G8: 46.83604 | H8: 38.75993 | I8: 42.607061 | J8: 21 | K8: 0.17225921 | L8: -67.909752 | M8: -42.062855 | N8: 1.9052418 | O8: -37.532555 | P8: 55.682841 | Q8: 2.3123186 | R8: 0 | S8: 0 | T8: 0 | V8: =ABS(Forecast!J8-D8) -> 0 | W8: =ABS(Pools!L8-E8) -> 0 | X8: =ABS(Pools!R8-F8) -> 0 | Y8: =IF(C8=1,ABS(Scorecard!AC8-G8),0) -> 0 | Z8: =IF(C8=1,ABS(Scorecard!AQ8-H8),0) -> 0 | AA8: =IF(C8=1,ABS(Scorecard!AR8-I8),0) -> 0 | AB8: =IF(C8=1,ABS(Scorecard!AS8-J8),0) -> 0 | AC8: =IF(C8=1,ABS(Scorecard!AT8-K8),0) -> 0
A9: Cameroon | B9: CMR | C9: 1 | D9: 0.78171317 | E9: 330.66089 | F9: 21.64823 | G9: 48.177479 | H9: 51.923556 | I9: 50.015458 | J9: 14 | K9: 0.17139103 | L9: -69.915433 | M9: -28.042088 | N9: 37.050104 | O9: -22.237376 | P9: 45.339954 | Q9: 1.5278946 | R9: 0.0098 | S9: 0.039 | T9: 0.0678 | V9: =ABS(Forecast!J9-D9) -> 0 | W9: =ABS(Pools!L9-E9) -> 0 | X9: =ABS(Pools!R9-F9) -> 0 | Y9: =IF(C9=1,ABS(Scorecard!AC9-G9),0) -> 0 | Z9: =IF(C9=1,ABS(Scorecard!AQ9-H9),0) -> 0 | AA9: =IF(C9=1,ABS(Scorecard!AR9-I9),0) -> 0 | AB9: =IF(C9=1,ABS(Scorecard!AS9-J9),0) -> 0 | AC9: =IF(C9=1,ABS(Scorecard!AT9-K9),0) -> 0
A10: Chad | B10: TCD | C10: 1 | D10: 0.31019278 | E10: 51.557008 | F10: 5.0736873 | G10: 44.952903 | H10: 35.626108 | I10: 40.018708 | J10: 22 | K10: 0.15464262 | L10: -68.680104 | M10: -52.976523 | N10: -15.7784 | O10: -47.602888 | P10: 72.889032 | Q10: 3.9202315 | R10: 0.0002 | S10: 0.0006 | T10: 0.003 | V10: =ABS(Forecast!J10-D10) -> 0 | W10: =ABS(Pools!L10-E10) -> 0 | X10: =ABS(Pools!R10-F10) -> 0 | Y10: =IF(C10=1,ABS(Scorecard!AC10-G10),0) -> 0 | Z10: =IF(C10=1,ABS(Scorecard!AQ10-H10),0) -> 0 | AA10: =IF(C10=1,ABS(Scorecard!AR10-I10),0) -> 0 | AB10: =IF(C10=1,ABS(Scorecard!AS10-J10),0) -> 0 | AC10: =IF(C10=1,ABS(Scorecard!AT10-K10),0) -> 0
A11: Comoros | B11: COM | C11: 0 | D11: 0.32406347 | E11: 1.2952684 | F11: 0.12669152 | V11: =ABS(Forecast!J11-D11) -> 0 | W11: =ABS(Pools!L11-E11) -> 0 | X11: =ABS(Pools!R11-F11) -> 0 | Y11: =IF(C11=1,ABS(Scorecard!AC11-G11),0) -> 0 | Z11: =IF(C11=1,ABS(Scorecard!AQ11-H11),0) -> 0 | AA11: =IF(C11=1,ABS(Scorecard!AR11-I11),0) -> 0 | AB11: =IF(C11=1,ABS(Scorecard!AS11-J11),0) -> 0 | AC11: =IF(C11=1,ABS(Scorecard!AT11-K11),0) -> 0
A12: Congo, Dem. Rep. | B12: COD | C12: 1 | D12: 0.61266217 | E12: 620.39175 | F12: 50.385198 | G12: 63.786352 | H12: 56.945809 | I12: 60.269108 | J12: 4 | K12: 0.16466025 | L12: -111.57089 | M12: 2.1813478 | N12: 208.78313 | O12: 25.393734 | P12: 69.537657 | Q12: 0.98424469 | R12: 0.2464 | S12: 0.3954 | T12: 0.5014 | V12: =ABS(Forecast!J12-D12) -> 0 | W12: =ABS(Pools!L12-E12) -> 0 | X12: =ABS(Pools!R12-F12) -> 0 | Y12: =IF(C12=1,ABS(Scorecard!AC12-G12),0) -> 0 | Z12: =IF(C12=1,ABS(Scorecard!AQ12-H12),0) -> 0 | AA12: =IF(C12=1,ABS(Scorecard!AR12-I12),0) -> 0 | AB12: =IF(C12=1,ABS(Scorecard!AS12-J12),0) -> 0 | AC12: =IF(C12=1,ABS(Scorecard!AT12-K12),0) -> 0
A13: Congo, Rep. | B13: COG | C13: 1 | D13: 0.7569571 | E13: 77.635606 | F13: 5.2956252 | G13: 36.947665 | H13: 59.293913 | I13: 46.80568 | J13: 19 | K13: 0.15781991 | L13: -52.08454 | M13: -40.795228 | N13: -22.858536 | O13: -39.133383 | P13: 55.119543 | Q13: 3.8621885 | R13: 0.0054 | S13: 0.012 | T13: 0.0208 | V13: =ABS(Forecast!J13-D13) -> 0 | W13: =ABS(Pools!L13-E13) -> 0 | X13: =ABS(Pools!R13-F13) -> 0 | Y13: =IF(C13=1,ABS(Scorecard!AC13-G13),0) -> 0 | Z13: =IF(C13=1,ABS(Scorecard!AQ13-H13),0) -> 0 | AA13: =IF(C13=1,ABS(Scorecard!AR13-I13),0) -> 0 | AB13: =IF(C13=1,ABS(Scorecard!AS13-J13),0) -> 0 | AC13: =IF(C13=1,ABS(Scorecard!AT13-K13),0) -> 0
A14: Cote d'Ivoire | B14: CIV | C14: 1 | D14: 0.7699166 | E14: 408.8148 | F14: 27.308259 | G14: 51.384197 | H14: 71.547241 | I14: 60.633303 | J14: 2 | K14: 0.12533993 | L14: -80.890126 | M14: -10.323053 | N14: 99.301836 | O14: -0.55859887 | P14: 43.586782 | Q14: 1.1153893 | R14: 0.0256 | S14: 0.1242 | T14: 0.2506 | V14: =ABS(Forecast!J14-D14) -> 0 | W14: =ABS(Pools!L14-E14) -> 0 | X14: =ABS(Pools!R14-F14) -> 0 | Y14: =IF(C14=1,ABS(Scorecard!AC14-G14),0) -> 0 | Z14: =IF(C14=1,ABS(Scorecard!AQ14-H14),0) -> 0 | AA14: =IF(C14=1,ABS(Scorecard!AR14-I14),0) -> 0 | AB14: =IF(C14=1,ABS(Scorecard!AS14-J14),0) -> 0 | AC14: =IF(C14=1,ABS(Scorecard!AT14-K14),0) -> 0
A15: Eswatini | B15: SWZ | C15: 0 | D15: 0.74812543 | E15: 15.799012 | F15: 1.0924519 | V15: =ABS(Forecast!J15-D15) -> 0 | W15: =ABS(Pools!L15-E15) -> 0 | X15: =ABS(Pools!R15-F15) -> 0 | Y15: =IF(C15=1,ABS(Scorecard!AC15-G15),0) -> 0 | Z15: =IF(C15=1,ABS(Scorecard!AQ15-H15),0) -> 0 | AA15: =IF(C15=1,ABS(Scorecard!AR15-I15),0) -> 0 | AB15: =IF(C15=1,ABS(Scorecard!AS15-J15),0) -> 0 | AC15: =IF(C15=1,ABS(Scorecard!AT15-K15),0) -> 0
A16: Ethiopia | B16: ETH | C16: 1 | D16: 0.23380419 | E16: 103.8991 | F16: 10.542931 | G16: 58.126283 | H16: 26.919982 | I16: 39.557028 | J16: 23 | K16: 0.17933966 | L16: -144.38643 | M16: -121.34792 | N16: -57.272581 | O16: -111.08871 | P16: 178.81636 | Q16: 5.7080942 | R16: 0 | S16: 0.0026 | T16: 0.0076 | V16: =ABS(Forecast!J16-D16) -> 0 | W16: =ABS(Pools!L16-E16) -> 0 | X16: =ABS(Pools!R16-F16) -> 0 | Y16: =IF(C16=1,ABS(Scorecard!AC16-G16),0) -> 0 | Z16: =IF(C16=1,ABS(Scorecard!AQ16-H16),0) -> 0 | AA16: =IF(C16=1,ABS(Scorecard!AR16-I16),0) -> 0 | AB16: =IF(C16=1,ABS(Scorecard!AS16-J16),0) -> 0 | AC16: =IF(C16=1,ABS(Scorecard!AT16-K16),0) -> 0
A17: Gabon | B17: GAB | C17: 0 | D17: 0.82444003 | E17: 44.62845 | F17: 2.6901434 | V17: =ABS(Forecast!J17-D17) -> 0 | W17: =ABS(Pools!L17-E17) -> 0 | X17: =ABS(Pools!R17-F17) -> 0 | Y17: =IF(C17=1,ABS(Scorecard!AC17-G17),0) -> 0 | Z17: =IF(C17=1,ABS(Scorecard!AQ17-H17),0) -> 0 | AA17: =IF(C17=1,ABS(Scorecard!AR17-I17),0) -> 0 | AB17: =IF(C17=1,ABS(Scorecard!AS17-J17),0) -> 0 | AC17: =IF(C17=1,ABS(Scorecard!AT17-K17),0) -> 0
A18: Gambia, The | B18: GMB | C18: 0 | D18: 0.40808086 | E18: 7.6697055 | F18: 0.71994259 | V18: =ABS(Forecast!J18-D18) -> 0 | W18: =ABS(Pools!L18-E18) -> 0 | X18: =ABS(Pools!R18-F18) -> 0 | Y18: =IF(C18=1,ABS(Scorecard!AC18-G18),0) -> 0 | Z18: =IF(C18=1,ABS(Scorecard!AQ18-H18),0) -> 0 | AA18: =IF(C18=1,ABS(Scorecard!AR18-I18),0) -> 0 | AB18: =IF(C18=1,ABS(Scorecard!AS18-J18),0) -> 0 | AC18: =IF(C18=1,ABS(Scorecard!AT18-K18),0) -> 0
A19: Ghana | B19: GHA | C19: 1 | D19: 0.91329134 | E19: 584.03577 | F19: 27.533692 | G19: 39.312784 | H19: 68.744969 | I19: 51.986114 | J19: 11 | K19: 0.1473334 | L19: -80.394265 | M19: -31.657465 | N19: 39.046587 | O19: -26.165652 | P19: 46.101759 | Q19: 1.4762239 | R19: 0.002 | S19: 0.007 | T19: 0.0244 | V19: =ABS(Forecast!J19-D19) -> 0 | W19: =ABS(Pools!L19-E19) -> 0 | X19: =ABS(Pools!R19-F19) -> 0 | Y19: =IF(C19=1,ABS(Scorecard!AC19-G19),0) -> 0 | Z19: =IF(C19=1,ABS(Scorecard!AQ19-H19),0) -> 0 | AA19: =IF(C19=1,ABS(Scorecard!AR19-I19),0) -> 0 | AB19: =IF(C19=1,ABS(Scorecard!AS19-J19),0) -> 0 | AC19: =IF(C19=1,ABS(Scorecard!AT19-K19),0) -> 0
A20: Guinea | B20: GIN | C20: 1 | D20: 0.50427951 | E20: 79.592719 | F20: 7.0481954 | G20: 45.636315 | H20: 58.825665 | I20: 51.812996 | J20: 12 | K20: 0.13015186 | L20: -67.83337 | M20: -46.857166 | N20: -6.0453475 | O20: -41.898262 | P20: 59.582593 | Q20: 2.8669482 | R20: 0.0008 | S20: 0.0118 | T20: 0.024 | V20: =ABS(Forecast!J20-D20) -> 0 | W20: =ABS(Pools!L20-E20) -> 0 | X20: =ABS(Pools!R20-F20) -> 0 | Y20: =IF(C20=1,ABS(Scorecard!AC20-G20),0) -> 0 | Z20: =IF(C20=1,ABS(Scorecard!AQ20-H20),0) -> 0 | AA20: =IF(C20=1,ABS(Scorecard!AR20-I20),0) -> 0 | AB20: =IF(C20=1,ABS(Scorecard!AS20-J20),0) -> 0 | AC20: =IF(C20=1,ABS(Scorecard!AT20-K20),0) -> 0
A21: Kenya | B21: KEN | C21: 0 | D21: 0.92 | E21: 894.37952 | F21: 32.081691 | V21: =ABS(Forecast!J21-D21) -> 0 | W21: =ABS(Pools!L21-E21) -> 0 | X21: =ABS(Pools!R21-F21) -> 0 | Y21: =IF(C21=1,ABS(Scorecard!AC21-G21),0) -> 0 | Z21: =IF(C21=1,ABS(Scorecard!AQ21-H21),0) -> 0 | AA21: =IF(C21=1,ABS(Scorecard!AR21-I21),0) -> 0 | AB21: =IF(C21=1,ABS(Scorecard!AS21-J21),0) -> 0 | AC21: =IF(C21=1,ABS(Scorecard!AT21-K21),0) -> 0
A22: Lesotho | B22: LSO | C22: 0 | D22: 0.7705641 | E22: 21.140798 | F22: 1.4106566 | V22: =ABS(Forecast!J22-D22) -> 0 | W22: =ABS(Pools!L22-E22) -> 0 | X22: =ABS(Pools!R22-F22) -> 0 | Y22: =IF(C22=1,ABS(Scorecard!AC22-G22),0) -> 0 | Z22: =IF(C22=1,ABS(Scorecard!AQ22-H22),0) -> 0 | AA22: =IF(C22=1,ABS(Scorecard!AR22-I22),0) -> 0 | AB22: =IF(C22=1,ABS(Scorecard!AS22-J22),0) -> 0 | AC22: =IF(C22=1,ABS(Scorecard!AT22-K22),0) -> 0
A23: Liberia | B23: LBR | C23: 1 | D23: 0.72580701 | E23: 40.90941 | F23: 2.921683 | G23: 46.72092 | H23: 61.940661 | I23: 53.795211 | J23: 10 | K23: 0.13096788 | L23: -58.898724 | M23: -51.589248 | N23: -39.562499 | O23: -50.40993 | P23: 65.099062 | Q23: 6.6579849 | R23: 0.2218 | S23: 0.3138 | T23: 0.368 | V23: =ABS(Forecast!J23-D23) -> 0 | W23: =ABS(Pools!L23-E23) -> 0 | X23: =ABS(Pools!R23-F23) -> 0 | Y23: =IF(C23=1,ABS(Scorecard!AC23-G23),0) -> 0 | Z23: =IF(C23=1,ABS(Scorecard!AQ23-H23),0) -> 0 | AA23: =IF(C23=1,ABS(Scorecard!AR23-I23),0) -> 0 | AB23: =IF(C23=1,ABS(Scorecard!AS23-J23),0) -> 0 | AC23: =IF(C23=1,ABS(Scorecard!AT23-K23),0) -> 0
A24: Madagascar | B24: MDG | C24: 1 | D24: 0.41223283 | E24: 117.79208 | F24: 11.032172 | G24: 53.522103 | H24: 54.901383 | I24: 54.207356 | J24: 9 | K24: 0.13175402 | L24: -92.490708 | M24: -58.211053 | N24: 14.345827 | O24: -48.641747 | P24: 75.16882 | Q24: 2.4442202 | R24: 0.0236 | S24: 0.0588 | T24: 0.0978 | V24: =ABS(Forecast!J24-D24) -> 0 | W24: =ABS(Pools!L24-E24) -> 0 | X24: =ABS(Pools!R24-F24) -> 0 | Y24: =IF(C24=1,ABS(Scorecard!AC24-G24),0) -> 0 | Z24: =IF(C24=1,ABS(Scorecard!AQ24-H24),0) -> 0 | AA24: =IF(C24=1,ABS(Scorecard!AR24-I24),0) -> 0 | AB24: =IF(C24=1,ABS(Scorecard!AS24-J24),0) -> 0 | AC24: =IF(C24=1,ABS(Scorecard!AT24-K24),0) -> 0
A25: Malawi | B25: MWI | C25: 1 | D25: 0.72476782 | E25: 162.22223 | F25: 11.6023 | G25: 44.375404 | H25: 57.564393 | I25: 50.5415 | J25: 13 | K25: 0.14773061 | L25: -71.953419 | M25: -45.445257 | N25: -1.6943356 | O25: -41.134567 | P25: 58.66904 | Q25: 2.3749015 | R25: 0 | S25: 0.0006 | T25: 0.0058 | V25: =ABS(Forecast!J25-D25) -> 0 | W25: =ABS(Pools!L25-E25) -> 0 | X25: =ABS(Pools!R25-F25) -> 0 | Y25: =IF(C25=1,ABS(Scorecard!AC25-G25),0) -> 0 | Z25: =IF(C25=1,ABS(Scorecard!AQ25-H25),0) -> 0 | AA25: =IF(C25=1,ABS(Scorecard!AR25-I25),0) -> 0 | AB25: =IF(C25=1,ABS(Scorecard!AS25-J25),0) -> 0 | AC25: =IF(C25=1,ABS(Scorecard!AT25-K25),0) -> 0
A26: Mali | B26: MLI | C26: 1 | D26: 0.73259813 | E26: 198.02577 | F26: 14.008502 | G26: 50.112931 | H26: 45.048962 | I26: 47.51353 | J26: 17 | K26: 0.16914497 | L26: -66.5351 | M26: -38.10222 | N26: 8.4992361 | O26: -33.560076 | P26: 50.479471 | Q26: 2.0714918 | R26: 0 | S26: 0 | T26: 0 | V26: =ABS(Forecast!J26-D26) -> 0 | W26: =ABS(Pools!L26-E26) -> 0 | X26: =ABS(Pools!R26-F26) -> 0 | Y26: =IF(C26=1,ABS(Scorecard!AC26-G26),0) -> 0 | Z26: =IF(C26=1,ABS(Scorecard!AQ26-H26),0) -> 0 | AA26: =IF(C26=1,ABS(Scorecard!AR26-I26),0) -> 0 | AB26: =IF(C26=1,ABS(Scorecard!AS26-J26),0) -> 0 | AC26: =IF(C26=1,ABS(Scorecard!AT26-K26),0) -> 0
A27: Mauritius | B27: MUS | C27: 0 | D27: 0.24771755 | E27: 2.1246825 | F27: 0.2144701 | V27: =ABS(Forecast!J27-D27) -> 0 | W27: =ABS(Pools!L27-E27) -> 0 | X27: =ABS(Pools!R27-F27) -> 0 | Y27: =IF(C27=1,ABS(Scorecard!AC27-G27),0) -> 0 | Z27: =IF(C27=1,ABS(Scorecard!AQ27-H27),0) -> 0 | AA27: =IF(C27=1,ABS(Scorecard!AR27-I27),0) -> 0 | AB27: =IF(C27=1,ABS(Scorecard!AS27-J27),0) -> 0 | AC27: =IF(C27=1,ABS(Scorecard!AT27-K27),0) -> 0
A28: Mozambique | B28: MOZ | C28: 1 | D28: 0.7111102 | E28: 211.26568 | F28: 15.389805 | G28: 49.845521 | H28: 46.423596 | I28: 48.10414 | J28: 16 | K28: 0.16962438 | L28: -78.129922 | M28: -47.069603 | N28: 5.3029608 | O28: -41.741542 | P28: 62.489301 | Q28: 2.2226719 | R28: 0 | S28: 0.0106 | T28: 0.0312 | V28: =ABS(Forecast!J28-D28) -> 0 | W28: =ABS(Pools!L28-E28) -> 0 | X28: =ABS(Pools!R28-F28) -> 0 | Y28: =IF(C28=1,ABS(Scorecard!AC28-G28),0) -> 0 | Z28: =IF(C28=1,ABS(Scorecard!AQ28-H28),0) -> 0 | AA28: =IF(C28=1,ABS(Scorecard!AR28-I28),0) -> 0 | AB28: =IF(C28=1,ABS(Scorecard!AS28-J28),0) -> 0 | AC28: =IF(C28=1,ABS(Scorecard!AT28-K28),0) -> 0
A29: Namibia | B29: NAM | C29: 0 | D29: 0.73306647 | E29: 32.426984 | F29: 2.2923817 | V29: =ABS(Forecast!J29-D29) -> 0 | W29: =ABS(Pools!L29-E29) -> 0 | X29: =ABS(Pools!R29-F29) -> 0 | Y29: =IF(C29=1,ABS(Scorecard!AC29-G29),0) -> 0 | Z29: =IF(C29=1,ABS(Scorecard!AQ29-H29),0) -> 0 | AA29: =IF(C29=1,ABS(Scorecard!AR29-I29),0) -> 0 | AB29: =IF(C29=1,ABS(Scorecard!AS29-J29),0) -> 0 | AC29: =IF(C29=1,ABS(Scorecard!AT29-K29),0) -> 0
A30: Niger | B30: NER | C30: 1 | D30: 0.15012976 | E30: 16.560831 | F30: 1.7295544 | G30: 45.033287 | H30: 25.295115 | I30: 33.750884 | J30: 25 | K30: 0.16309859 | L30: -77.2396 | M30: -72.296855 | N30: -56.984655 | O30: -69.704492 | P30: 102.61817 | Q30: 14.068105 | R30: 0.0016 | S30: 0.0036 | T30: 0.006 | V30: =ABS(Forecast!J30-D30) -> 0 | W30: =ABS(Pools!L30-E30) -> 0 | X30: =ABS(Pools!R30-F30) -> 0 | Y30: =IF(C30=1,ABS(Scorecard!AC30-G30),0) -> 0 | Z30: =IF(C30=1,ABS(Scorecard!AQ30-H30),0) -> 0 | AA30: =IF(C30=1,ABS(Scorecard!AR30-I30),0) -> 0 | AB30: =IF(C30=1,ABS(Scorecard!AS30-J30),0) -> 0 | AC30: =IF(C30=1,ABS(Scorecard!AT30-K30),0) -> 0
A31: Nigeria | B31: NGA | C31: 1 | D31: 0.58775638 | E31: 1320.9712 | F31: 109.70977 | G31: 68.731423 | H31: 30.497663 | I31: 45.783706 | J31: 20 | K31: 0.18958428 | L31: -120.72189 | M31: 89.404178 | N31: 479.09814 | O31: 134.29615 | P31: 77.488048 | Q31: 0.64886515 | R31: 0.0048 | S31: 0.013 | T31: 0.0406 | V31: =ABS(Forecast!J31-D31) -> 0 | W31: =ABS(Pools!L31-E31) -> 0 | X31: =ABS(Pools!R31-F31) -> 0 | Y31: =IF(C31=1,ABS(Scorecard!AC31-G31),0) -> 0 | Z31: =IF(C31=1,ABS(Scorecard!AQ31-H31),0) -> 0 | AA31: =IF(C31=1,ABS(Scorecard!AR31-I31),0) -> 0 | AB31: =IF(C31=1,ABS(Scorecard!AS31-J31),0) -> 0 | AC31: =IF(C31=1,ABS(Scorecard!AT31-K31),0) -> 0
A32: Senegal | B32: SEN | C32: 1 | D32: 0.85527644 | E32: 223.56055 | F32: 12.545741 | G32: 41.41908 | H32: 74.128645 | I32: 55.410651 | J32: 6 | K32: 0.1286206 | L32: -71.966074 | M32: -43.20941 | N32: -1.8613378 | O32: -40.061558 | P32: 52.626136 | Q32: 2.1540217 | R32: 0.0606 | S32: 0.1984 | T32: 0.2526 | V32: =ABS(Forecast!J32-D32) -> 0 | W32: =ABS(Pools!L32-E32) -> 0 | X32: =ABS(Pools!R32-F32) -> 0 | Y32: =IF(C32=1,ABS(Scorecard!AC32-G32),0) -> 0 | Z32: =IF(C32=1,ABS(Scorecard!AQ32-H32),0) -> 0 | AA32: =IF(C32=1,ABS(Scorecard!AR32-I32),0) -> 0 | AB32: =IF(C32=1,ABS(Scorecard!AS32-J32),0) -> 0 | AC32: =IF(C32=1,ABS(Scorecard!AT32-K32),0) -> 0
